Workbook

Sheet pokemon
A1: # | B1: Name | C1: Type 1 | D1: Type 2 | E1: Total | F1: HP | G1: Attack | H1: Defense | I1: Sp. Atk | J1: Sp. Def | K1: Speed | L1: Generation | M1: Legendary
A2: 1 | B2: Bulbasaur | C2: Grass | D2: Poison | E2: 318 | F2: 45 | G2: 49 | H2: 49 | I2: 65 | J2: 65 | K2: 45 | L2: 1 | M2: FALSE
A3: 2 | B3: Ivysaur | C3: Grass | D3: Poison | E3: 405 | F3: 60 | G3: 62 | H3: 63 | I3: 80 | J3: 80 | K3: 60 | L3: 1 | M3: FALSE
A4: 3 | B4: Venusaur | C4: Grass | D4: Poison | E4: 525 | F4: 80 | G4: 82 | H4: 83 | I4: 100 | J4: 100 | K4: 80 | L4: 1 | M4: FALSE
A5: 4 | B5: Charmander | C5: Fire | E5: 309 | F5: 39 | G5: 52 | H5: 43 | I5: 60 | J5: 50 | K5: 65 | L5: 1 | M5: FALSE
A6: 5 | B6: Charmeleon | C6: Fire | E6: 405 | F6: 58 | G6: 64 | H6: 58 | I6: 80 | J6: 65 | K6: 80 | L6: 1 | M6: FALSE
A7: 6 | B7: Charizard | C7: Fire | D7: Flying | E7: 534 | F7: 78 | G7: 84 | H7: 78 | I7: 109 | J7: 85 | K7: 100 | L7: 1 | M7: FALSE
A8: 7 | B8: Squirtle | C8: Water | E8: 314 | F8: 44 | G8: 48 | H8: 65 | I8: 50 | J8: 64 | K8: 43 | L8: 1 | M8: FALSE
A9: 8 | B9: Wartortle | C9: Water | E9: 405 | F9: 59 | G9: 63 | H9: 80 | I9: 65 | J9: 80 | K9: 58 | L9: 1 | M9: FALSE
A10: 9 | B10: Blastoise | C10: Water | E10: 530 | F10: 79 | G10: 83 | H10: 100 | I10: 85 | J10: 105 | K10: 78 | L10: 1 | M10: FALSE
A11: 10 | B11: Caterpie | C11: Bug | E11: 195 | F11: 45 | G11: 30 | H11: 35 | I11: 20 | J11: 20 | K11: 45 | L11: 1 | M11: FALSE
A12: 11 | B12: Metapod | C12: Bug | E12: 205 | F12: 50 | G12: 20 | H12: 55 | I12: 25 | J12: 25 | K12: 30 | L12: 1 | M12: FALSE
A13: 12 | B13: Butterfree | C13: Bug | D13: Flying | E13: 395 | F13: 60 | G13: 45 | H13: 50 | I13: 90 | J13: 80 | K13: 70 | L13: 1 | M13: FALSE
A14: 13 | B14: Weedle | C14: Bug | D14: Poison | E14: 195 | F14: 40 | G14: 35 | H14: 30 | I14: 20 | J14: 20 | K14: 50 | L14: 1 | M14: FALSE
A15: 14 | B15: Kakuna | C15: Bug | D15: Poison | E15: 205 | F15: 45 | G15: 25 | H15: 50 | I15: 25 | J15: 25 | K15: 35 | L15: 1 | M15: FALSE
A16: 15 | B16: Beedrill | C16: Bug | D16: Poison | E16: 395 | F16: 65 | G16: 90 | H16: 40 | I16: 45 | J16: 80 | K16: 75 | L16: 1 | M16: FALSE
A17: 16 | B17: Pidgey | C17: Normal | D17: Flying | E17: 251 | F17: 40 | G17: 45 | H17: 40 | I17: 35 | J17: 35 | K17: 56 | L17: 1 | M17: FALSE
A18: 17 | B18: Pidgeotto | C18: Normal | D18: Flying | E18: 349 | F18: 63 | G18: 60 | H18: 55 | I18: 50 | J18: 50 | K18: 71 | L18: 1 | M18: FALSE
A19: 18 | B19: Pidgeot | C19: Normal | D19: Flying | E19: 479 | F19: 83 | G19: 80 | H19: 75 | I19: 70 | J19: 70 | K19: 101 | L19: 1 | M19: FALSE
A20: 19 | B20: Rattata | C20: Normal | E20: 253 | F20: 30 | G20: 56 | H20: 35 | I20: 25 | J20: 35 | K20: 72 | L20: 1 | M20: FALSE
A21: 20 | B21: Raticate | C21: Normal | E21: 413 | F21: 55 | G21: 81 | H21: 60 | I21: 50 | J21: 70 | K21: 97 | L21: 1 | M21: FALSE
A22: 21 | B22: Spearow | C22: Normal | D22: Flying | E22: 262 | F22: 40 | G22: 60 | H22: 30 | I22: 31 | J22: 31 | K22: 70 | L22: 1 | M22: FALSE
A23: 22 | B23: Fearow | C23: Normal | D23: Flying | E23: 442 | F23: 65 | G23: 90 | H23: 65 | I23: 61 | J23: 61 | K23: 100 | L23: 1 | M23: FALSE
A24: 23 | B24: Ekans | C24: Poison | E24: 288 | F24: 35 | G24: 60 | H24: 44 | I24: 40 | J24: 54 | K24: 55 | L24: 1 | M24: FALSE
A25: 24 | B25: Arbok | C25: Poison | E25: 438 | F25: 60 | G25: 85 | H25: 69 | I25: 65 | J25: 79 | K25: 80 | L25: 1 | M25: FALSE
A26: 25 | B26: Pikachu | C26: Electric | E26: 320 | F26: 35 | G26: 55 | H26: 40 | I26: 50 | J26: 50 | K26: 90 | L26: 1 | M26: FALSE
A27: 26 | B27: Raichu | C27: Electric | E27: 485 | F27: 60 | G27: 90 | H27: 55 | I27: 90 | J27: 80 | K27: 110 | L27: 1 | M27: FALSE
A28: 27 | B28: Sandshrew | C28: Ground | E28: 300 | F28: 50 | G28: 75 | H28: 85 | I28: 20 | J28: 30 | K28: 40 | L28: 1 | M28: FALSE
A29: 28 | B29: Sandslash | C29: Ground | E29: 450 | F29: 75 | G29: 100 | H29: 110 | I29: 45 | J29: 55 | K29: 65 | L29: 1 | M29: FALSE
A30: 29 | B30: Nidoran H | C30: Poison | E30: 275 | F30: 55 | G30: 47 | H30: 52 | I30: 40 | J30: 40 | K30: 41 | L30: 1 | M30: FALSE
A31: 30 | B31: Nidorina | C31: Poison | E31: 365 | F31: 70 | G31: 62 | H31: 67 | I31: 55 | J31: 55 | K31: 56 | L31: 1 | M31: FALSE
A32: 31 | B32: Nidoqueen | C32: Poison | D32: Ground | E32: 505 | F32: 90 | G32: 92 | H32: 87 | I32: 75 | J32: 85 | K32: 76 | L32: 1 | M32: FALSE
A33: 32 | B33: Nidoran M | C33: Poison | E33: 273 | F33: 46 | G33: 57 | H33: 40 | I33: 40 | J33: 40 | K33: 50 | L33: 1 | M33: FALSE
A34: 33 | B34: Nidorino | C34: Poison | E34: 365 | F34: 61 | G34: 72 | H34: 57 | I34: 55 | J34: 55 | K34: 65 | L34: 1 | M34: FALSE
A35: 34 | B35: Nidoking | C35: Poison | D35: Ground | E35: 505 | F35: 81 | G35: 102 | H35: 77 | I35: 85 | J35: 75 | K35: 85 | L35: 1 | M35: FALSE
A36: 35 | B36: Clefairy | C36: Fairy | E36: 323 | F36: 70 | G36: 45 | H36: 48 | I36: 60 | J36: 65 | K36: 35 | L36: 1 | M36: FALSE
A37: 36 | B37: Clefable | C37: Fairy | E37: 483 | F37: 95 | G37: 70 | H37: 73 | I37: 95 | J37: 90 | K37: 60 | L37: 1 | M37: FALSE
A38: 37 | B38: Vulpix | C38: Fire | E38: 299 | F38: 38 | G38: 41 | H38: 40 | I38: 50 | J38: 65 | K38: 65 | L38: 1 | M38: FALSE
A39: 38 | B39: Ninetales | C39: Fire | E39: 505 | F39: 73 | G39: 76 | H39: 75 | I39: 81 | J39: 100 | K39: 100 | L39: 1 | M39: FALSE
A40: 39 | B40: Jigglypuff | C40: Normal | D40: Fairy | E40: 270 | F40: 115 | G40: 45 | H40: 20 | I40: 45 | J40: 25 | K40: 20 | L40: 1 | M40: FALSE
A41: 40 | B41: Wigglytuff | C41: Normal | D41: Fairy | E41: 435 | F41: 140 | G41: 70 | H41: 45 | I41: 85 | J41: 50 | K41: 45 | L41: 1 | M41: FALSE
A42: 41 | B42: Zubat | C42: Poison | D42: Flying | E42: 245 | F42: 40 | G42: 45 | H42: 35 | I42: 30 | J42: 40 | K42: 55 | L42: 1 | M42: FALSE
A43: 42 | B43: Golbat | C43: Poison | D43: Flying | E43: 455 | F43: 75 | G43: 80 | H43: 70 | I43: 65 | J43: 75 | K43: 90 | L43: 1 | M43: FALSE
A44: 43 | B44: Oddish | C44: Grass | D44: Poison | E44: 320 | F44: 45 | G44: 50 | H44: 55 | I44: 75 | J44: 65 | K44: 30 | L44: 1 | M44: FALSE
A45: 44 | B45: Gloom | C45: Grass | D45: Poison | E45: 395 | F45: 60 | G45: 65 | H45: 70 | I45: 85 | J45: 75 | K45: 40 | L45: 1 | M45: FALSE
A46: 45 | B46: Vileplume | C46: Grass | D46: Poison | E46: 490 | F46: 75 | G46: 80 | H46: 85 | I46: 110 | J46: 90 | K46: 50 | L46: 1 | M46: FALSE
A47: 46 | B47: Paras | C47: Bug | D47: Grass | E47: 285 | F47: 35 | G47: 70 | H47: 55 | I47: 45 | J47: 55 | K47: 25 | L47: 1 | M47: FALSE
A48: 47 | B48: Parasect | C48: Bug | D48: Grass | E48: 405 | F48: 60 | G48: 95 | H48: 80 | I48: 60 | J48: 80 | K48: 30 | L48: 1 | M48: FALSE
A49: 48 | B49: Venonat | C49: Bug | D49: Poison | E49: 305 | F49: 60 | G49: 55 | H49: 50 | I49: 40 | J49: 55 | K49: 45 | L49: 1 | M49: FALSE
A50: 49 | B50: Venomoth | C50: Bug | D50: Poison | E50: 450 | F50: 70 | G50: 65 | H50: 60 | I50: 90 | J50: 75 | K50: 90 | L50: 1 | M50: FALSE
A51: 50 | B51: Diglett | C51: Ground | E51: 265 | F51: 10 | G51: 55 | H51: 25 | I51: 35 | J51: 45 | K51: 95 | L51: 1 | M51: FALSE
A52: 51 | B52: Dugtrio | C52: Ground | E52: 405 | F52: 35 | G52: 80 | H52: 50 | I52: 50 | J52: 70 | K52: 120 | L52: 1 | M52: FALSE
A53: 52 | B53: Meowth | C53: Normal | E53: 290 | F53: 40 | G53: 45 | H53: 35 | I53: 40 | J53: 40 | K53: 90 | L53: 1 | M53: FALSE
A54: 53 | B54: Persian | C54: Normal | E54: 440 | F54: 65 | G54: 70 | H54: 60 | I54: 65 | J54: 65 | K54: 115 | L54: 1 | M54: FALSE
A55: 54 | B55: Psyduck | C55: Water | E55: 320 | F55: 50 | G55: 52 | H55: 48 | I55: 65 | J55: 50 | K55: 55 | L55: 1 | M55: FALSE
A56: 55 | B56: Golduck | C56: Water | E56: 500 | F56: 80 | G56: 82 | H56: 78 | I56: 95 | J56: 80 | K56: 85 | L56: 1 | M56: FALSE
A57: 56 | B57: Mankey | C57: Fighting | E57: 305 | F57: 40 | G57: 80 | H57: 35 | I57: 35 | J57: 45 | K57: 70 | L57: 1 | M57: FALSE
A58: 57 | B58: Primeape | C58: Fighting | E58: 455 | F58: 65 | G58: 105 | H58: 60 | I58: 60 | J58: 70 | K58: 95 | L58: 1 | M58: FALSE
A59: 58 | B59: Growlithe | C59: Fire | E59: 350 | F59: 55 | G59: 70 | H59: 45 | I59: 70 | J59: 50 | K59: 60 | L59: 1 | M59: FALSE
A60: 59 | B60: Arcanine | C60: Fire | E60: 555 | F60: 90 | G60: 110 | H60: 80 | I60: 100 | J60: 80 | K60: 95 | L60: 1 | M60: FALSE
A61: 60 | B61: Poliwag | C61: Water | E61: 300 | F61: 40 | G61: 50 | H61: 40 | I61: 40 | J61: 40 | K61: 90 | L61: 1 | M61: FALSE
A62: 61 | B62: Poliwhirl | C62: Water | E62: 385 | F62: 65 | G62: 65 | H62: 65 | I62: 50 | J62: 50 | K62: 90 | L62: 1 | M62: FALSE
A63: 62 | B63: Poliwrath | C63: Water | D63: Fighting | E63: 510 | F63: 90 | G63: 95 | H63: 95 | I63: 70 | J63: 90 | K63: 70 | L63: 1 | M63: FALSE
A64: 63 | B64: Abra | C64: Psychic | E64: 310 | F64: 25 | G64: 20 | H64: 15 | I64: 105 | J64: 55 | K64: 90 | L64: 1 | M64: FALSE
A65: 64 | B65: Kadabra | C65: Psychic | E65: 400 | F65: 40 | G65: 35 | H65: 30 | I65: 120 | J65: 70 | K65: 105 | L65: 1 | M65: FALSE
A66: 65 | B66: Alakazam | C66: Psychic | E66: 500 | F66: 55 | G66: 50 | H66: 45 | I66: 135 | J66: 95 | K66: 120 | L66: 1 | M66: FALSE
A67: 66 | B67: Machop | C67: Fighting | E67: 305 | F67: 70 | G67: 80 | H67: 50 | I67: 35 | J67: 35 | K67: 35 | L67: 1 | M67: FALSE
A68: 67 | B68: Machoke | C68: Fighting | E68: 405 | F68: 80 | G68: 100 | H68: 70 | I68: 50 | J68: 60 | K68: 45 | L68: 1 | M68: FALSE
A69: 68 | B69: Machamp | C69: Fighting | E69: 505 | F69: 90 | G69: 130 | H69: 80 | I69: 65 | J69: 85 | K69: 55 | L69: 1 | M69: FALSE
A70: 69 | B70: Bellsprout | C70: Grass | D70: Poison | E70: 300 | F70: 50 | G70: 75 | H70: 35 | I70: 70 | J70: 30 | K70: 40 | L70: 1 | M70: FALSE
A71: 70 | B71: Weepinbell | C71: Grass | D71: Poison | E71: 390 | F71: 65 | G71: 90 | H71: 50 | I71: 85 | J71: 45 | K71: 55 | L71: 1 | M71: FALSE
A72: 71 | B72: Victreebel | C72: Grass | D72: Poison | E72: 490 | F72: 80 | G72: 105 | H72: 65 | I72: 100 | J72: 70 | K72: 70 | L72: 1 | M72: FALSE
A73: 72 | B73: Tentacool | C73: Water | D73: Poison | E73: 335 | F73: 40 | G73: 40 | H73: 35 | I73: 50 | J73: 100 | K73: 70 | L73: 1 | M73: FALSE
A74: 73 | B74: Tentacruel | C74: Water | D74: Poison | E74: 515 | F74: 80 | G74: 70 | H74: 65 | I74: 80 | J74: 120 | K74: 100 | L74: 1 | M74: FALSE
A75: 74 | B75: Geodude | C75: Rock | D75: Ground | E75: 300 | F75: 40 | G75: 80 | H75: 100 | I75: 30 | J75: 30 | K75: 20 | L75: 1 | M75: FALSE
A76: 75 | B76: Graveler | C76: Rock | D76: Ground | E76: 390 | F76: 55 | G76: 95 | H76: 115 | I76: 45 | J76: 45 | K76: 35 | L76: 1 | M76: FALSE
A77: 76 | B77: Golem | C77: Rock | D77: Ground | E77: 495 | F77: 80 | G77: 120 | H77: 130 | I77: 55 | J77: 65 | K77: 45 | L77: 1 | M77: FALSE
A78: 77 | B78: Ponyta | C78: Fire | E78: 410 | F78: 50 | G78: 85 | H78: 55 | I78: 65 | J78: 65 | K78: 90 | L78: 1 | M78: FALSE
A79: 78 | B79: Rapidash | C79: Fire | E79: 500 | F79: 65 | G79: 100 | H79: 70 | I79: 80 | J79: 80 | K79: 105 | L79: 1 | M79: FALSE
A80: 79 | B80: Slowpoke | C80: Water | D80: Psychic | E80: 315 | F80: 90 | G80: 65 | H80: 65 | I80: 40 | J80: 40 | K80: 15 | L80: 1 | M80: FALSE
A81: 80 | B81: Slowbro | C81: Water | D81: Psychic | E81: 490 | F81: 95 | G81: 75 | H81: 110 | I81: 100 | J81: 80 | K81: 30 | L81: 1 | M81: FALSE
A82: 81 | B82: Magnemite | C82: Electric | D82: Steel | E82: 325 | F82: 25 | G82: 35 | H82: 70 | I82: 95 | J82: 55 | K82: 45 | L82: 1 | M82: FALSE
A83: 82 | B83: Magneton | C83: Electric | D83: Steel | E83: 465 | F83: 50 | G83: 60 | H83: 95 | I83: 120 | J83: 70 | K83: 70 | L83: 1 | M83: FALSE
A84: 83 | B84: Farfetch'd | C84: Normal | D84: Flying | E84: 352 | F84: 52 | G84: 65 | H84: 55 | I84: 58 | J84: 62 | K84: 60 | L84: 1 | M84: FALSE
A85: 84 | B85: Doduo | C85: Normal | D85: Flying | E85: 310 | F85: 35 | G85: 85 | H85: 45 | I85: 35 | J85: 35 | K85: 75 | L85: 1 | M85: FALSE
A86: 85 | B86: Dodrio | C86: Normal | D86: Flying | E86: 460 | F86: 60 | G86: 110 | H86: 70 | I86: 60 | J86: 60 | K86: 100 | L86: 1 | M86: FALSE
A87: 86 | B87: Seel | C87: Water | E87: 325 | F87: 65 | G87: 45 | H87: 55 | I87: 45 | J87: 70 | K87: 45 | L87: 1 | M87: FALSE
A88: 87 | B88: Dewgong | C88: Water | D88: Ice | E88: 475 | F88: 90 | G88: 70 | H88: 80 | I88: 70 | J88: 95 | K88: 70 | L88: 1 | M88: FALSE
A89: 88 | B89: Grimer | C89: Poison | E89: 325 | F89: 80 | G89: 80 | H89: 50 | I89: 40 | J89: 50 | K89: 25 | L89: 1 | M89: FALSE
A90: 89 | B90: Muk | C90: Poison | E90: 500 | F90: 105 | G90: 105 | H90: 75 | I90: 65 | J90: 100 | K90: 50 | L90: 1 | M90: FALSE
A91: 90 | B91: Shellder | C91: Water | E91: 305 | F91: 30 | G91: 65 | H91: 100 | I91: 45 | J91: 25 | K91: 40 | L91: 1 | M91: FALSE
A92: 91 | B92: Cloyster | C92: Water | D92: Ice | E92: 525 | F92: 50 | G92: 95 | H92: 180 | I92: 85 | J92: 45 | K92: 70 | L92: 1 | M92: FALSE
A93: 92 | B93: Gastly | C93: Ghost | D93: Poison | E93: 310 | F93: 30 | G93: 35 | H93: 30 | I93: 100 | J93: 35 | K93: 80 | L93: 1 | M93: FALSE
A94: 93 | B94: Haunter | C94: Ghost | D94: Poison | E94: 405 | F94: 45 | G94: 50 | H94: 45 | I94: 115 | J94: 55 | K94: 95 | L94: 1 | M94: FALSE
A95: 94 | B95: Gengar | C95: Ghost | D95: Poison | E95: 500 | F95: 60 | G95: 65 | H95: 60 | I95: 130 | J95: 75 | K95: 110 | L95: 1 | M95: FALSE
A96: 95 | B96: Onix | C96: Rock | D96: Ground | E96: 385 | F96: 35 | G96: 45 | H96: 160 | I96: 30 | J96: 45 | K96: 70 | L96: 1 | M96: FALSE
A97: 96 | B97: Drowzee | C97: Psychic | E97: 328 | F97: 60 | G97: 48 | H97: 45 | I97: 43 | J97: 90 | K97: 42 | L97: 1 | M97: FALSE
A98: 97 | B98: Hypno | C98: Psychic | E98: 483 | F98: 85 | G98: 73 | H98: 70 | I98: 73 | J98: 115 | K98: 67 | L98: 1 | M98: FALSE
A99: 98 | B99: Krabby | C99: Water | E99: 325 | F99: 30 | G99: 105 | H99: 90 | I99: 25 | J99: 25 | K99: 50 | L99: 1 | M99: FALSE
A100: 99 | B100: Kingler | C100: Water | E100: 475 | F100: 55 | G100: 130 | H100: 115 | I100: 50 | J100: 50 | K100: 75 | L100: 1 | M100: FALSE
...

Sheet PKMN BULBAP
A1: # | B1: Cod | C1: Pokémon | D1: HP | E1: Attack | F1: Defense | G1: Sp. Attack | H1: Sp. Defense | I1: Speed | J1: Total | K1: Average
A2: 1 | B2: 001O | C2: Bulbasaur | D2: 45 | E2: 49 | F2: 49 | G2: 65 | H2: 65 | I2: 45 | J2: 318 | K2: 53 | L2: =LEN(B2) -> 4
A3: 2 | B3: 002O | C3: Ivysaur | D3: 60 | E3: 62 | F3: 63 | G3: 80 | H3: 80 | I3: 60 | J3: 405 | K3: 67.5 | L3: =LEN(B3) -> 4
A4: 3 | B4: 003O | C4: Venusaur | D4: 80 | E4: 82 | F4: 83 | G4: 100 | H4: 100 | I4: 80 | J4: 525 | K4: 87.5 | L4: =LEN(B4) -> 4
A5: 3 | B5: 003M | C5: Venusaur (Mega Venusaur) | D5: 80 | E5: 100 | F5: 123 | G5: 122 | H5: 120 | I5: 80 | J5: 625 | K5: 104.17 | L5: =LEN(B5) -> 4
A6: 4 | B6: 004O | C6: Charmander | D6: 39 | E6: 52 | F6: 43 | G6: 60 | H6: 50 | I6: 65 | J6: 309 | K6: 51.5 | L6: =LEN(B6) -> 4
A7: 5 | B7: 005O | C7: Charmeleon | D7: 58 | E7: 64 | F7: 58 | G7: 80 | H7: 65 | I7: 80 | J7: 405 | K7: 67.5 | L7: =LEN(B7) -> 4
A8: 6 | B8: 006O | C8: Charizard | D8: 78 | E8: 84 | F8: 78 | G8: 109 | H8: 85 | I8: 100 | J8: 534 | K8: 89 | L8: =LEN(B8) -> 4
A9: 6 | B9: 006X | C9: Charizard (Mega Charizard X) | D9: 78 | E9: 130 | F9: 111 | G9: 130 | H9: 85 | I9: 100 | J9: 634 | K9: 105.67 | L9: =LEN(B9) -> 4
A10: 6 | B10: 006Y | C10: Charizard (Mega Charizard Y) | D10: 78 | E10: 104 | F10: 78 | G10: 159 | H10: 115 | I10: 100 | J10: 634 | K10: 105.67 | L10: =LEN(B10) -> 4
A11: 7 | B11: 007O | C11: Squirtle | D11: 44 | E11: 48 | F11: 65 | G11: 50 | H11: 64 | I11: 43 | J11: 314 | K11: 52.33 | L11: =LEN(B11) -> 4
A12: 8 | B12: 008O | C12: Wartortle | D12: 59 | E12: 63 | F12: 80 | G12: 65 | H12: 80 | I12: 58 | J12: 405 | K12: 67.5 | L12: =LEN(B12) -> 4
A13: 9 | B13: 009O | C13: Blastoise | D13: 79 | E13: 83 | F13: 100 | G13: 85 | H13: 105 | I13: 78 | J13: 530 | K13: 88.33 | L13: =LEN(B13) -> 4
... A1063: 905 | B1063: 905T | C1063: Enamorus (Therian Forme) | D1063: 74 | E1063: 115 | F1063: 110 | G1063: 135 | H1063: 100 | I1063: 46 | J1063: 580 | K1063: 96.67 | L1063: =LEN(B1063) -> 4
D1065: 1-9HP = 1HP 10-39HP = 2HP 40-59HP = 3HP 60-79HP = 4HP 80-99HP = 5HP 100-119HP = 6HP 120-139HP = 7HP 140-160HP = 8HP 161-190HP = 9HP >190HP = 10 HP | E1065: 5-44At = 1d4 45-84At = 1d6 85-124 = 1d8 125-144 = 1d10 >145 = 1d12 | F1065: de 0 a 29 = 0 de 30 a 59 = 1 de 60 a 79 = 2 de 80 a 99 = 3 de 100 a 119 = 4 de 120 a 139 = 5 de 140 a 169 = 6 de 170 a 199 = 7 +200 = 8 | G1065: 5-44At = 1d4 45-84At = 1d6 85-124 = 1d8 125-144 = 1d10 >145 = 1d12 | H1065: de 0 a 29 = 0 de 30 a 59 = 1 de 60 a 79 = 2 de 80 a 99 = 3 de 100 a 119 = 4 de 120 a 139 = 5 de 140 a 169 = 6 de 170 a 199 = 7 +200 = 8 | I1065: 1-9HP = 1HP 10-39HP = 2HP 40-59HP = 3HP 60-79HP = 4HP 80-99HP = 5HP 100-119HP = 6HP 120-139HP = 7HP 140-159HP = 8HP 160-180HP = 9HP >180HP = 10 HP

Sheet Evolution Special
B2: Regions | C2: Gender | D2: Time | E2: Move | F2: Weather | G2: Benefits | H2: Hability | I2: Stat | J2: Friend
B3: Kanto+ | C3: Male | D3: Day | E3: M1 | F3: Clear | G3: Normal, Grass | H3: H1 | I3: ATQ < SPD | J3: 30
B4: Johto+ | C4: Female | D4: Night | E4: M2 | F4: Cloudy | G4: Fighting, Poison, Dark | H4: H2 | I4: ATQ > SPD | J4: 45
B5: Hoenn+ | E5: M3 | F5: Rain | G5: Water, Bug | I5: ATQ = SPD | J5: 60
B6: Shinnoh+ | E6: M4 | F6: Thunderstorm | G6: Water, Electric, Dragon | J6: 75
B7: Unova+ | F7: Snow | G7: Ice
B8: Kalos+ | F8: Blizzard | G8: Ice, Steel
B9: Alola+ | F9: Harsh sunlight | G9: Fire, Ground
B10: Galar+ | F10: Sandstorm | G10: Ground, Rock
B11: Hisui+ | F11: Fog | G11: Psychic, Ghost, Fairy
F12: Windy | G12: Flying

Sheet Breed
F1: Male | G1: Female | M1: Egg 1
C2: 1 | D2: Bulbasaur | E2: Bulbasaur | F2: 0.85 | G2: 0.15 | J2: 23 | K2: Ekans | L2: Ekans | M2: Field
C3: 2 | D3: Ivysaur | E3: Ivysaur | F3: 0.85 | G3: 0.15 | J3: 24 | K3: Arbok | L3: Arbok | M3: Field
C4: 3 | D4: Venusaur | E4: Venusaur | F4: 0.85 | G4: 0.15 | J4: 25 | K4: Pikachu | L4: Pikachu | M4: Fairy
C5: 4 | D5: Charmander | E5: Charmander | F5: 0.85 | G5: 0.15 | J5: 26 | K5: Raichu | L5: Raichu | M5: Fairy
C6: 5 | D6: Charmeleon | E6: Charmeleon | F6: 0.85 | G6: 0.15 | J6: 27 | K6: Sandshrew | L6: Sandshrew | M6: Field
C7: 6 | D7: Charizard | E7: Charizard | F7: 0.85 | G7: 0.15 | J7: 28 | K7: Sandslash | L7: Sandslash | M7: Field
C8: 7 | D8: Squirtle | E8: Squirtle | F8: 0.85 | G8: 0.15 | J8: 29 | K8: Nidoran♀ | L8: Nidoran♀ | M8: Field
C9: 8 | D9: Wartortle | E9: Wartortle | F9: 0.85 | G9: 0.15 | J9: 30 | K9: Nidorina | L9: Nidorina | M9: Undiscovered
C10: 9 | D10: Blastoise | E10: Blastoise | F10: 0.85 | G10: 0.15 | J10: 31 | K10: Nidoqueen | L10: Nidoqueen | M10: Undiscovered
C11: 10 | D11: Caterpie | E11: Caterpie | F11: 0.5 | G11: 0.5 | J11: 164 | K11: Noctowl | L11: Noctowl | M11: Flying
C12: 11 | D12: Metapod | E12: Metapod | F12: 0.5 | G12: 0.5 | J12: 165 | K12: Ledyba | L12: Ledyba | M12: Bug
C13: 12 | D13: Butterfree | E13: Butterfree | F13: 0.5 | G13: 0.5 | J13: 166 | K13: Ledian | L13: Ledian | M13: Bug
... C81: 80 | D81: Slowbro | E81: Slowbro | F81: 0.5 | G81: 0.5 | J81: 214 | K81: Heracross | L81: Heracross | M81: Bug
C82: 81 | D82: Magnemite | E82: Magnemite | F82: - | G82: - | J82: 777 | K82: Togedemaru | L82: Togedemaru | M82: Fairy
C83: 82 | D83: Magneton | E83: Magneton | F83: - | G83: - | J83: 778 | K83: Mimikyu | L83: Mimikyu | M83: Amorphous
C84: 83 | D84: Farfetch'd | E84: Farfetch'd | F84: 0.5 | G84: 0.5 | J84: 215 | K84: Sneasel | L84: Sneasel | M84: Field
C85: 84 | D85: Doduo | E85: Doduo | F85: 0.5 | G85: 0.5 | J85: 216 | K85: Teddiursa | L85: Teddiursa | M85: Field
C86: 85 | D86: Dodrio | E86: Dodrio | F86: 0.5 | G86: 0.5 | J86: 217 | K86: Ursaring | L86: Ursaring | M86: Field
C87: 86 | D87: Seel | E87: Seel | F87: 0.5 | G87: 0.5 | J87: 218 | K87: Slugma | L87: Slugma | M87: Amorphous
C88: 87 | D88: Dewgong | E88: Dewgong | F88: 0.5 | G88: 0.5 | J88: 219 | K88: Magcargo | L88: Magcargo | M88: Amorphous
C89: 88 | D89: Grimer | E89: Grimer | F89: 0.5 | G89: 0.5 | J89: 220 | K89: Swinub | L89: Swinub | M89: Field
C90: 89 | D90: Muk | E90: Muk | F90: 0.5 | G90: 0.5 | J90: 221 | K90: Piloswine | L90: Piloswine | M90: Field
C91: 90 | D91: Shellder | E91: Shellder | F91: 0.5 | G91: 0.5 | J91: 222 | K91: Corsola | L91: Corsola | M91: Water 3
C92: 91 | D92: Cloyster | E92: Cloyster | F92: 0.5 | G92: 0.5 | J92: 223 | K92: Remoraid | L92: Remoraid | M92: Water 2
C93: 92 | D93: Gastly | E93: Gastly | F93: 0.5 | G93: 0.5 | J93: 224 | K93: Octillery | L93: Octillery | M93: Water 2
C94: 93 | D94: Haunter | E94: Haunter | F94: 0.5 | G94: 0.5 | J94: 225 | K94: Delibird | L94: Delibird | M94: Field
C95: 94 | D95: Gengar | E95: Gengar | F95: 0.5 | G95: 0.5 | J95: 226 | K95: Mantine | L95: Mantine | M95: Water 3
... C100: 99 | D100: Kingler | E100: Kingler | F100: 0.5 | G100: 0.5 | J100: 231 | K100: Phanpy | L100: Phanpy | M100: Field
C101: 100 | D101: Voltorb | E101: Voltorb | F101: - | G101: - | J101: 779 | K101: Bruxish | L101: Bruxish | M101: Water 2
C102: 101 | D102: Electrode | E102: Electrode | F102: - | G102: - | J102: 780 | K102: Drampa | L102: Drampa | M102: Dragon
C103: 102 | D103: Exeggcute | E103: Exeggcute | F103: 0.5 | G103: 0.5 | J103: 232 | K103: Donphan | L103: Donphan | M103: Field
C104: 103 | D104: Exeggutor | E104: Exeggutor | F104: 0.5 | G104: 0.5 | J104: 233 | K104: Porygon2 | L104: Porygon2 | M104: Mineral
C105: 104 | D105: Cubone | E105: Cubone | F105: 0.5 | G105: 0.5 | J105: 234 | K105: Stantler | L105: Stantler | M105: Field
C106: 105 | D106: Marowak | E106: Marowak | F106: 0.5 | G106: 0.5 | J106: 235 | K106: Smeargle | L106: Smeargle | M106: Field
C107: 106 | D107: Hitmonlee | E107: Hitmonlee | F107: 1 | G107: 0 | J107: 4 | K107: Charmander | L107: Charmander | M107: Dragon
C108: 107 | D108: Hitmonchan | E108: Hitmonchan | F108: 1 | G108: 0 | J108: 5 | K108: Charmeleon | L108: Charmeleon | M108: Dragon
C109: 108 | D109: Lickitung | E109: Lickitung | F109: 0.5 | G109: 0.5 | J109: 236 | K109: Tyrogue | L109: Tyrogue | M109: Undiscovered
C110: 109 | D110: Koffing | E110: Koffing | F110: 0.5 | G110: 0.5 | J110: 237 | K110: Hitmontop | L110: Hitmontop | M110: Human-Like
C111: 110 | D111: Weezing | E111: Weezing | F111: 0.5 | G111: 0.5 | J111: 238 | K111: Smoochum | L111: Smoochum | M111: Undiscovered
C112: 111 | D112: Rhyhorn | E112: Rhyhorn | F112: 0.5 | G112: 0.5 | J112: 239 | K112: Elekid | L112: Elekid | M112: Undiscovered
C113: 112 | D113: Rhydon | E113: Rhydon | F113: 0.5 | G113: 0.5 | J113: 240 | K113: Magby | L113: Magby | M113: Undiscovered
C114: 113 | D114: Chansey | E114: Chansey | F114: 0 | G114: 1 | J114: 746 | K114: Wishiwashi | L114: Wishiwashi | M114: Water 2
... C120: 119 | D120: Seaking | E120: Seaking | F120: 0.5 | G120: 0.5 | J120: 245 | K120: Suicune | L120: Suicune | M120: Undiscovered
C121: 120 | D121: Staryu | E121: Staryu | F121: - | G121: - | J121: 781 | K121: Dhelmise | L121: Dhelmise | M121: Mineral
C122: 121 | D122: Starmie | E122: Starmie | F122: - | G122: - | J122: 782 | K122: Jangmo-o | L122: Jangmo-o | M122: Dragon
C123: 122 | D123: Mr. Mime | E123: Mr. Mime | F123: 0.5 | G123: 0.5 | J123: 246 | K123: Larvitar | L123: Larvitar | M123: Monster
C124: 123 | D124: Scyther | E124: Scyther | F124: 0.5 | G124: 0.5 | J124: 247 | K124: Pupitar | L124: Pupitar | M124: Monster
C125: 124 | D125: Jynx | E125: Jynx | F125: 0 | G125: 1 | J125: 748 | K125: Toxapex | L125: Toxapex | M125: Water 2
C126: 125 | D126: Electabuzz | E126: Electabuzz | F126: 0.75 | G126: 0.25 | J126: 153 | K126: Bayleef | L126: Bayleef | M126: Grass
C127: 126 | D127: Magmar | E127: Magmar | F127: 0.75 | G127: 0.25 | J127: 154 | K127: Meganium | L127: Meganium | M127: Grass
C128: 127 | D128: Pinsir | E128: Pinsir | F128: 0.5 | G128: 0.5 | J128: 248 | K128: Tyranitar | L128: Tyranitar | M128: Monster
C129: 128 | D129: Tauros | E129: Tauros | F129: 1 | G129: 0 | J129: 6 | K129: Charizard | L129: Charizard | M129: Dragon
C130: 129 | D130: Magikarp | E130: Magikarp | F130: 0.5 | G130: 0.5 | J130: 249 | K130: Lugia | L130: Lugia | M130: Undiscovered
C131: 130 | D131: Gyarados | E131: Gyarados | F131: 0.5 | G131: 0.5 | J131: 250 | K131: Ho-Oh | L131: Ho-Oh | M131: Undiscovered
C132: 131 | D132: Lapras | E132: Lapras | F132: 0.5 | G132: 0.5 | J132: 251 | K132: Celebi | L132: Celebi | M132: Undiscovered
C133: 132 | D133: Ditto | E133: Ditto* | F133: - | G133: - | J133: 812 | K133: Rillaboom | L133: Rillaboom | M133: Grass
C134: 133 | D134: Eevee | E134: Eevee | F134: 0.85 | G134: 0.15 | J134: 32 | K134: Nidoran♂ | L134: Nidoran♂ | M134: Field
C135: 134 | D135: Vaporeon | E135: Vaporeon | F135: 0.85 | G135: 0.15 | J135: 33 | K135: Nidorino | L135: Nidorino | M135: Field
C136: 135 | D136: Jolteon | E136: Jolteon | F136: 0.85 | G136: 0.15 | J136: 34 | K136: Nidoking | L136: Nidoking | M136: Field
C137: 136 | D137: Flareon | E137: Flareon | F137: 0.85 | G137: 0.15 | J137: 35 | K137: Clefairy | L137: Clefairy | M137: Fairy
C138: 137 | D138: Porygon | E138: Porygon | F138: - | G138: - | J138: 783 | K138: Hakamo-o | L138: Hakamo-o | M138: Dragon
C139: 138 | D139: Omanyte | E139: Omanyte | F139: 0.85 | G139: 0.15 | J139: 36 | K139: Clefable | L139: Clefable | M139: Fairy
C140: 139 | D140: Omastar | E140: Omastar | F140: 0.85 | G140: 0.15 | J140: 37 | K140: Vulpix | L140: Vulpix | M140: Field
C141: 140 | D141: Kabuto | E141: Kabuto | F141: 0.85 | G141: 0.15 | J141: 38 | K141: Ninetales | L141: Ninetales | M141: Field
C142: 141 | D142: Kabutops | E142: Kabutops | F142: 0.85 | G142: 0.15 | J142: 39 | K142: Jigglypuff | L142: Jigglypuff | M142: Fairy
C143: 142 | D143: Aerodactyl | E143: Aerodactyl | F143: 0.85 | G143: 0.15 | J143: 40 | K143: Wigglytuff | L143: Wigglytuff | M143: Fairy
C144: 143 | D144: Snorlax | E144: Snorlax | F144: 0.85 | G144: 0.15 | J144: 41 | K144: Zubat | L144: Zubat | M144: Flying
C145: 144 | D145: Articuno | E145: Articuno | F145: - | G145: - | J145: 813 | K145: Scorbunny | L145: Scorbunny | M145: Field
C146: 145 | D146: Zapdos | E146: Zapdos | F146: - | G146: - | J146: 814 | K146: Raboot | L146: Raboot | M146: Field
C147: 146 | D147: Moltres | E147: Moltres | F147: - | G147: - | J147: 815 | K147: Cinderace | L147: Cinderace | M147: Field
C148: 147 | D148: Dratini | E148: Dratini | F148: 0.5 | G148: 0.5 | J148: 252 | K148: Treecko | L148: Treecko | M148: Dragon
C149: 148 | D149: Dragonair | E149: Dragonair | F149: 0.5 | G149: 0.5 | J149: 253 | K149: Grovyle | L149: Grovyle | M149: Dragon
C150: 149 | D150: Dragonite | E150: Dragonite | F150: 0.5 | G150: 0.5 | J150: 254 | K150: Sceptile | L150: Sceptile | M150: Dragon
C151: 150 | D151: Mewtwo | E151: Mewtwo | F151: - | G151: - | J151: 816 | K151: Sobble | L151: Sobble | M151: Water 1
C152: 151 | D152: Mew | E152: Mew | F152: - | G152: - | J152: 817 | K152: Drizzile | L152: Drizzile | M152: Water 1
C153: 152 | D153: Chikorita | E153: Chikorita | F153: 0.85 | G153: 0.15 | J153: 42 | K153: Golbat | L153: Golbat | M153: Flying
C154: 153 | D154: Bayleef | E154: Bayleef | F154: 0.85 | G154: 0.15 | J154: 43 | K154: Oddish | L154: Oddish | M154: Grass
C155: 154 | D155: Meganium | E155: Meganium | F155: 0.85 | G155: 0.15 | J155: 44 | K155: Gloom | L155: Gloom | M155: Grass
C156: 155 | D156: Cyndaquil | E156: Cyndaquil | F156: 0.85 | G156: 0.15 | J156: 45 | K156: Vileplume | L156: Vileplume | M156: Grass
C157: 156 | D157: Quilava | E157: Quilava | F157: 0.85 | G157: 0.15 | J157: 46 | K157: Paras | L157: Paras | M157: Bug
C158: 157 | D158: Typhlosion | E158: Typhlosion | F158: 0.85 | G158: 0.15 | J158: 47 | K158: Parasect | L158: Parasect | M158: Bug
C159: 158 | D159: Totodile | E159: Totodile | F159: 0.85 | G159: 0.15 | J159: 48 | K159: Venonat | L159: Venonat | M159: Bug
C160: 159 | D160: Croconaw | E160: Croconaw | F160: 0.85 | G160: 0.15 | J160: 49 | K160: Venomoth | L160: Venomoth | M160: Bug
C161: 160 | D161: Feraligatr | E161: Feraligatr | F161: 0.85 | G161: 0.15 | J161: 50 | K161: Diglett | L161: Diglett | M161: Field
C162: 161 | D162: Sentret | E162: Sentret | F162: 0.5 | G162: 0.5 | J162: 255 | K162: Torchic | L162: Torchic | M162: Field
C163: 162 | D163: Furret | E163: Furret | F163: 0.5 | G163: 0.5 | J163: 256 | K163: Combusken | L163: Combusken | M163: Field
C164: 163 | D164: Hoothoot | E164: Hoothoot | F164: 0.5 | G164: 0.5 | J164: 257 | K164: Blaziken | L164: Blaziken | M164: Field
... C201: 200 | D201: Misdreavus | E201: Misdreavus | F201: 0.5 | G201: 0.5 | J201: 287 | K201: Slakoth | L201: Slakoth | M201: Field
C202: 201 | D202: Unown | E202: Unown | F202: - | G202: - | J202: 818 | K202: Inteleon | L202: Inteleon | M202: Water 1
C203: 202 | D203: Wobbuffet | E203: Wobbuffet | F203: 0.5 | G203: 0.5 | J203: 288 | K203: Vigoroth | L203: Vigoroth | M203: Field
C204: 203 | D204: Girafarig | E204: Girafarig | F204: 0.5 | G204: 0.5 | J204: 289 | K204: Slaking | L204: Slaking | M204: Field
C205: 204 | D205: Pineco | E205: Pineco | F205: 0.5 | G205: 0.5 | J205: 290 | K205: Nincada | L205: Nincada | M205: Bug
C206: 205 | D206: Forretress | E206: Forretress | F206: 0.5 | G206: 0.5 | J206: 291 | K206: Ninjask | L206: Ninjask | M206: Bug
C207: 206 | D207: Dunsparce | E207: Dunsparce | F207: 0.5 | G207: 0.5 | J207: 292 | K207: Shedinja | L207: Shedinja | M207: Mineral
C208: 207 | D208: Gligar | E208: Gligar | F208: 0.5 | G208: 0.5 | J208: 293 | K208: Whismur | L208: Whismur | M208: Field
C209: 208 | D209: Steelix | E209: Steelix | F209: 0.5 | G209: 0.5 | J209: 294 | K209: Loudred | L209: Loudred | M209: Field
C210: 209 | D210: Snubbull | E210: Snubbull | F210: 0.25 | G210: 0.75 | J210: 724 | K210: Decidueye | L210: Decidueye | M210: Flying
C211: 210 | D211: Granbull | E211: Granbull | F211: 0.25 | G211: 0.75 | J211: 725 | K211: Litten | L211: Litten | M211: Field
C212: 211 | D212: Qwilfish | E212: Qwilfish | F212: 0.5 | G212: 0.5 | J212: 295 | K212: Exploud | L212: Exploud | M212: Field
...

Sheet Pokemon Db
A1: Real Games | Z1: Pokemon Tabletop Stats | AE1: Habilities and Moves | AM1: Resistances and Weaknessess
A2: Basic | G2: Evolution | L2: Special contditions to get this stage | S2: Original stats | AE2: Habilities | AI2: Moves
A3: # | B3: Name | C3: Generation | D3: Type 1 | E3: Type 2 | F3: TAG | G3: Stage | H3: Family | I3: Chain nº | J3: Preevolution | K3: Evolves with | L3: Friend | M3: Gender | N3: Move | O3: Weather | P3: Time | Q3: Hability | R3: Stat | S3: Total | T3: HP | U3: Attack | V3: Defense | W3: Sp. Atk | X3: Sp. Def | Y3: Speed | Z3: HP | AA3: Attack | AB3: Speed | AC3: Overall | AD3: Tier | AE3: Habilidad 1 | AF3: Tipo | AG3: Habilidad 2 | AH3: Tipo | AI3: Movimiento 1 | AJ3: Movimiento 2 | AK3: Movimiento 3 | AL3: Movimiento 4 | AM3: Debilidades | AN3: Resistencias | AO3: Debilidades simp. | AP3: Resistencias Simp.
A4: 149 | B4: Dragonite | C4: Kanto | D4: Dragon | E4: Flying | F4: NORMAL | G4: L | H4: Dratini | I4: 31 | J4: Dragonair | K4: Fully evolved | S4: 600 | T4: 91 | U4: 134 | V4: 95 | W4: 100 | X4: 100 | Y4: 80 | Z4: 19 | AA4: 9.5 | AB4: 8 | AC4: =SUM(Z4:AB4) -> 36.5 | AD4: A | AE4: Ilusión | AF4: C | AH4: C | AI4: Vel. Extrema | AJ4: Cometa draco | AK4: Trueno | AL4: Danza dragón | AM4: Hada / Dragón / Roca / Hielo | AN4: Tierra / Planta / Lucha / Fuego / Bicho / Agua | AO4: Hada / Dragón / Roca / Hielo | AP4: Tierra / Planta / Lucha / Fuego / Bicho / Agua
A5: 248 | B5: Tyranitar | C5: Johto | D5: Rock | E5: Dark | F5: NORMAL | G5: L | H5: Larvitar | I5: 31 | J5: Pupitar | K5: Fully evolved | S5: 600 | T5: 100 | U5: 134 | V5: 110 | W5: 95 | X5: 100 | Y5: 61 | Z5: 21 | AA5: 10.5 | AB5: 6 | AC5: =SUM(Z5:AB5) -> 37.5 | AD5: S
A6: 136 | B6: Flareon | C6: Kanto | D6: Fire | F6: NORMAL | G6: L | H6: Eevee | I6: 23 | J6: Eevee | K6: Fully evolved | O6: Harsh sunlight | S6: 525 | T6: 65 | U6: 130 | V6: 60 | W6: 95 | X6: 110 | Y6: 65 | Z6: 16 | AA6: 8.5 | AB6: 7 | AC6: =SUM(Z6:AB6) -> 31.5 | AD6: B | AE6: Agallas | AF6: C | AH6: C | AI6: Bola sombra | AJ6: Humareda | AK6: Arenas ardientes | AL6: Fuerza bruta | AM6: Tierra / Roca / Agua | AN6: Bicho / Fuego / Acero / Hielo / Planta / Hada | AO6: Tierra / Roca / Agua | AP6: Bicho / Fuego / Acero / Hielo / Planta / Hada
A7: 250 | B7: Ho-oh | C7: Johto | D7: Fire | E7: Flying | F7: LEGEND | G7: L | H7: Ho-oh | I7: 11 | J7: - | K7: Fully evolved | S7: 680 | T7: 106 | U7: 130 | V7: 90 | W7: 110 | X7: 154 | Y7: 90 | Z7: 23 | AA7: 12 | AB7: 9 | AC7: =SUM(Z7:AB7) -> 44 | AD7: S
A8: 99 | B8: Kingler | C8: Kanto | D8: Water | F8: NORMAL | G8: L | H8: Krabby | I8: 21 | J8: Krabby | K8: Fully evolved | S8: 475 | T8: 55 | U8: 130 | V8: 115 | W8: 50 | X8: 50 | Y8: 75 | Z8: 15 | AA8: 8.5 | AB8: 8 | AC8: =SUM(Z8:AB8) -> 31.5 | AD8: B | AE8: Defensor | AF8: T | AH8: T | AI8: Tijera X | AJ8: Martillazo | AK8: Fuerza bruta | AL8: Fuerza equina | AM8: Eléctrico / Planta | AN8: Agua / Acero / Fuego / Hielo | AO8: Eléctrico / Planta | AP8: Agua / Acero / Fuego / Hielo
A9: 68 | B9: Machamp | C9: Kanto | D9: Fighting | F9: NORMAL | G9: L | H9: Machop | I9: 31 | J9: Machoke | K9: Fully evolved | S9: 505 | T9: 90 | U9: 130 | V9: 80 | W9: 65 | X9: 85 | Y9: 55 | Z9: 17 | AA9: 7.5 | AB9: 6 | AC9: =SUM(Z9:AB9) -> 30.5 | AD9: B | AE9: Peleón | AF9: T | AH9: T | AI9: Puño bala | AJ9: Tajo cruzado | AK9: Puño hielo | AL9: Lariat oscuro | AM9: Volador / Hada / Psíquico | AN9: Bicho / Siniestro / Roca | AO9: Volador / Hada / Psíquico | AP9: Bicho / Siniestro / Roca
A10: 112 | B10: Rhydon | C10: Kanto | D10: Ground | E10: Rock | F10: NORMAL | G10: L | H10: Rhyhorn | I10: 21 | J10: Rhyhorn | K10: Fully evolved | S10: 485 | T10: 105 | U10: 130 | V10: 120 | W10: 45 | X10: 45 | Y10: 40 | Z10: 18 | AA10: 7.5 | AB10: 4 | AC10: =SUM(Z10:AB10) -> 29.5 | AD10: B | AE10: Irascible | AF10: C | AH10: C | AI10: Megacuerno | AJ10: Cuerpo pesado | AK10: Carga dragón | AL10: Terremoto | AM10: Acero / Lucha / Tierra / Hielo / Planta / Agua | AN10: Eléctrico / Veneno / Fuego / Volador / Normal / Roca | AO10: Acero / Lucha / Tierra / Hielo / Planta / Agua | AP10: Eléctrico / Veneno / Fuego / Volador / Normal / Roca
A11: 212 | B11: Scizor | C11: Johto | D11: Bug | E11: Steel | F11: NORMAL | G11: L | H11: Scyther | I11: 21 | J11: Scyther | K11: Fully evolved | N11: M4 | S11: 500 | T11: 70 | U11: 130 | V11: 100 | W11: 55 | X11: 80 | Y11: 65 | Z11: 17 | AA11: 8.5 | AB11: 7 | AC11: =SUM(Z11:AB11) -> 32.5 | AD11: B
A12: 217 | B12: Ursaring | C12: Johto | D12: Normal | F12: NORMAL | G12: L | H12: Teddiursa | I12: 21 | J12: Teddiursa | K12: Fully evolved | S12: 500 | T12: 90 | U12: 130 | V12: 75 | W12: 75 | X12: 75 | Y12: 55 | Z12: 16 | AA12: 9.5 | AB12: 6 | AC12: =SUM(Z12:AB12) -> 31.5 | AD12: B
A13: 214 | B13: Heracross | C13: Johto | D13: Bug | E13: Fighting | F13: NORMAL | G13: L | H13: Heracross | I13: 11 | J13: - | K13: Fully evolved | S13: 500 | T13: 80 | U13: 125 | V13: 75 | W13: 40 | X13: 95 | Y13: 85 | Z13: 17 | AA13: 7.5 | AB13: 9 | AC13: =SUM(Z13:AB13) -> 33.5 | AD13: A
A14: 130 | B14: Gyarados | C14: Kanto | D14: Water | E14: Flying | F14: NORMAL | G14: L | H14: Magikarp | I14: 21 | J14: Magikarp | K14: Fully evolved | S14: 540 | T14: 95 | U14: 125 | V14: 79 | W14: 60 | X14: 100 | Y14: 81 | Z14: 18 | AA14: 9.5 | AB14: 8 | AC14: =SUM(Z14:AB14) -> 35.5 | AD14: A | AE14: Autoestima | AF14: C | AH14: C | AI14: Cascada | AJ14: Triturar | AK14: Enfado | AL14: Danza dragón | AM14: Eléctrico / Roca | AN14: Tierra / Bicho / Fuego / Acero / Agua / Lucha | AO14: Eléctrico / Roca | AP14: Tierra / Bicho / Fuego / Acero / Agua / Lucha
A15: 127 | B15: Pinsir | C15: Kanto | D15: Bug | F15: NORMAL | G15: L | H15: Pinsir | I15: 11 | J15: - | K15: Fully evolved | S15: 500 | T15: 65 | U15: 125 | V15: 100 | W15: 55 | X15: 70 | Y15: 85 | Z15: 16 | AA15: 7 | AB15: 9 | AC15: =SUM(Z15:AB15) -> 32 | AD15: B | AE15: Duelista | AF15: T | AH15: T | AI15: Picadura | AJ15: A Bocajarro | AK15: Avalancha | AL15: Guillotina | AM15: Volador / Fuego / Roca | AN15: Planta / Tierra / Lucha | AO15: Volador / Fuego / Roca | AP15: Planta / Tierra / Lucha
A16: 76 | B16: Golem | C16: Kanto | D16: Rock | E16: Ground | F16: NORMAL | G16: L | H16: Geodude | I16: 31 | J16: Graveler | K16: Fully evolved | S16: 495 | T16: 80 | U16: 120 | V16: 130 | W16: 55 | X16: 65 | Y16: 45 | Z16: 18 | AA16: 7.5 | AB16: 5 | AC16: =SUM(Z16:AB16) -> 30.5 | AD16: B | AE16: Autodestrucción | AF16: T | AG16: Robustez | AH16: C | AI16: Avalancha | AJ16: Terremoto | AK16: Puño fuego | AL16: Aligerar | AM16: Acero / Lucha / Tierra / Hielo / Planta / Agua | AN16: Eléctrico / Veneno / Fuego / Volador / Normal / Roca | AO16: Acero / Lucha / Tierra / Hielo / Planta / Agua | AP16: Eléctrico / Veneno / Fuego / Volador / Normal / Roca
A17: 232 | B17: Donphan | C17: Johto | D17: Ground | F17: NORMAL | G17: L | H17: Phanpy | I17: 21 | J17: Phanpy | K17: Fully evolved | S17: 500 | T17: 90 | U17: 120 | V17: 120 | W17: 60 | X17: 60 | Y17: 50 | Z17: 18 | AA17: 8.5 | AB17: 5 | AC17: =SUM(Z17:AB17) -> 31.5 | AD17: B
A18: 210 | B18: Granbull | C18: Johto | D18: Fairy | F18: NORMAL | G18: L | H18: Snubbull | I18: 21 | J18: Snubbull | K18: Fully evolved | S18: 450 | T18: 90 | U18: 120 | V18: 75 | W18: 60 | X18: 60 | Y18: 45 | Z18: 15 | AA18: 8.5 | AB18: 5 | AC18: =SUM(Z18:AB18) -> 28.5 | AD18: C
A19: 106 | B19: Hitmonlee | C19: Kanto | D19: Fighting | F19: NORMAL | G19: L | H19: Tyrogue | I19: 21 | J19: Tyrogue | K19: Fully evolved | R19: ATQ < SPD | S19: 455 | T19: 50 | U19: 120 | V19: 53 | W19: 35 | X19: 110 | Y19: 87 | Z19: 14 | AA19: 7 | AB19: 9 | AC19: =SUM(Z19:AB19) -> 30 | AD19: B | AE19: Jugón | AF19: T | AH19: T | AI19: Patada ígnea | AJ19: Pat. S. Alta | AK19: Golpe bajo | AL19: Bote | AM19: Volador / Hada / Psíquico | AN19: Bicho / Siniestro / Roca | AO19: Volador / Hada / Psíquico | AP19: Bicho / Siniestro / Roca
A20: 244 | B20: Entei | C20: Johto | D20: Fire | F20: LEGEND | G20: L | H20: Entei | I20: 11 | J20: - | K20: Fully evolved | S20: 580 | T20: 115 | U20: 115 | V20: 85 | W20: 90 | X20: 75 | Y20: 100 | Z20: 18 | AA20: 9.5 | AB20: 10 | AC20: =SUM(Z20:AB20) -> 37.5 | AD20: S
A21: 141 | B21: Kabutops | C21: Kanto | D21: Rock | E21: Water | F21: NORMAL | G21: L | H21: Kabuto | I21: 21 | J21: Kabuto | K21: Fully evolved | S21: 495 | T21: 60 | U21: 115 | V21: 105 | W21: 65 | X21: 70 | Y21: 80 | Z21: 16 | AA21: 10.5 | AB21: 8 | AC21: =SUM(Z21:AB21) -> 34.5 | AD21: A | AE21: Poder antiguo | AF21: T | AH21: T | AI21: Acua jet | AJ21: Chupavidas | AK21: Poder pasado | AL21: Tierra viva | AM21: Tierra / Lucha / Eléctrico / Planta | AN21: Fuego / Hielo / Veneno / Volador / Normal | AO21: Tierra / Lucha / Eléctrico / Planta | AP21: Fuego / Hielo / Veneno / Volador / Normal
A22: 85 | B22: Dodrio | C22: Kanto | D22: Flying | E22: Normal | F22: NORMAL | G22: L | H22: Doduo | I22: 21 | J22: Doduo | K22: Fully evolved | S22: 460 | T22: 60 | U22: 110 | V22: 70 | W22: 60 | X22: 60 | Y22: 100 | Z22: 13 | AA22: 8.5 | AB22: 10 | AC22: =SUM(Z22:AB22) -> 31.5 | AD22: B | AE22: Ultra impulso | AF22: T | AH22: T | AI22: Pico taladro | AJ22: Triataque | AK22: Patada Salto | AL22: Persecución | AM22: Eléctrico / Hielo / Roca | AN22: Tierra / Fantasma / Bicho / Planta | AO22: Eléctrico / Hielo / Roca | AP22: Tierra / Fantasma / Bicho / Planta
A23: 59 | B23: Arcanine | C23: Kanto | D23: Fire | F23: NORMAL | G23: L | H23: Growlithe | I23: 21 | J23: Growlithe | K23: Fully evolved | S23: 555 | T23: 90 | U23: 110 | V23: 80 | W23: 100 | X23: 80 | Y23: 95 | Z23: 17 | AA23: 7.5 | AB23: 10 | AC23: =SUM(Z23:AB23) -> 34.5 | AD23: A | AE23: Policía | AF23: T | AH23: T | AI23: Colm. Rayo | AJ23: Envite ígneo | AK23: Vel. Extrema | AL23: Sol matinal | AM23: Tierra / Roca / Agua | AN23: Bicho / Fuego / Acero / Hielo / Planta / Hada | AO23: Tierra / Roca / Agua | AP23: Bicho / Fuego / Acero / Hielo / Planta / Hada
A24: 150 | B24: Mewtwo | C24: Kanto | D24: Psychic | F24: LEGEND | G24: L | H24: Mewtwo | I24: 11 | J24: - | K24: Fully evolved | S24: 680 | T24: 106 | U24: 110 | V24: 90 | W24: 154 | X24: 90 | Y24: 130 | Z24: 19 | AA24: 12 | AB24: 13 | AC24: =SUM(Z24:AB24) -> 44 | AD24: S | AE24: Clonación | AF24: T | AH24: T | AI24: Onda mental | AJ24: Rayo Hielo | AK24: Bola voltio | AL24: Esfera aural | AM24: Siniestro / Fantasma / Bicho | AN24: Psíquico / Lucha | AO24: Siniestro / Fantasma / Bicho | AP24: Psíquico / Lucha
A25: 123 | B25: Scyther | C25: Kanto | D25: Bug | E25: Flying | F25: NORMAL | G25: S | H25: Scyther | I25: 11 | J25: - | K25: Trading | S25: 500 | T25: 70 | U25: 110 | V25: 80 | W25: 55 | X25: 80 | Y25: 105 | Z25: 15 | AA25: 6 | AB25: 11 | AC25: =SUM(Z25:AB25) -> 32 | AD25: B | AE25: Vengador | AF25: C | AH25: C | AI25: Tijera X | AJ25: Tajo aéreo | AK25: Psicocorte | AL25: Tajo umbrío | AM25: Eléctrico / Fuego / Volador / Hielo / Roca | AN25: Tierra / Planta / Lucha / Bicho | AO25: Eléctrico / Fuego / Volador / Hielo / Roca | AP25: Tierra / Planta / Lucha / Bicho
A26: 143 | B26: Snorlax | C26: Kanto | D26: Normal | F26: NORMAL | G26: L | H26: Snorlax | I26: 11 | J26: - | K26: Fully evolved | S26: 540 | T26: 160 | U26: 110 | V26: 65 | W26: 65 | X26: 110 | Y26: 30 | Z26: 22 | AA26: 9.5 | AB26: 3 | AC26: =SUM(Z26:AB26) -> 34.5 | AD26: A | AE26: Remolón | AF26: T | AG26: Sonámbulo | AH26: C | AI26: Descanso | AJ26: Ronquido | AK26: Eructo | AL26: Giga impacto | AM26: Lucha | AN26: Fantasma | AO26: Lucha | AP26: Fantasma
A27: 142 | B27: Aerodactyl | C27: Kanto | D27: Rock | E27: Flying | F27: NORMAL | G27: L | H27: Aerodactyl | I27: 11 | J27: - | K27: Fully evolved | S27: 515 | T27: 80 | U27: 105 | V27: 65 | W27: 60 | X27: 75 | Y27: 130 | Z27: 15 | AA27: 7.5 | AB27: 13 | AC27: =SUM(Z27:AB27) -> 35.5 | AD27: A | AE27: Cazador primitivo | AF27: T | AH27: T | AI27: Ala bis | AJ27: Roca afilada | AK27: Hyperrayo | AL27: Llamarada | AM27: Hielo / Eléctrico / Roca / Acero / Agua | AN27: Tierra / Bicho / Veneno / Normal / Fuego / Volador | AO27: Hielo / Eléctrico / Roca / Acero / Agua | AP27: Tierra / Bicho / Veneno / Normal / Fuego / Volador
A28: 71 | B28: Victreebel | C28: Kanto | D28: Grass | E28: Poison | F28: NORMAL | G28: L | H28: Bellsprout | I28: 31 | J28: Weepinbell | K28: Fully evolved | S28: 490 | T28: 80 | U28: 105 | V28: 65 | W28: 100 | X28: 70 | Y28: 70 | Z28: 14 | AA28: 7 | AB28: 7 | AC28: =SUM(Z28:AB28) -> 28 | AD28: C | AE28: Atrapamoscas | AF28: T | AG28: Clorofila | AH28: C | AI28: Latigazo | AJ28: Bomba ácida | AK28: Estrujón | AL28: Golpe bajo | AM28: Fuego / Volador / Hielo / Psíquico | AN28: Planta / Hada / Lucha / Agua / Eléctrico | AO28: Fuego / Volador / Hielo / Psíquico | AP28: Planta / Hada / Lucha / Agua / Eléctrico
A29: 89 | B29: Muk | C29: Kanto | D29: Poison | F29: NORMAL | G29: L | H29: Grimer | I29: 21 | J29: Grimer | K29: Fully evolved | S29: 500 | T29: 105 | U29: 105 | V29: 75 | W29: 65 | X29: 100 | Y29: 50 | Z29: 19 | AA29: 6 | AB29: 5 | AC29: =SUM(Z29:AB29) -> 30 | AD29: B | AE29: Pestilente | AF29: T | AG29: Punto tóxico | AH29: C | AI29: Lanza mugre | AJ29: Llamarada | AK29: Sombra vil | AL29: Puño incremento | AM29: Tierra / Psíquico | AN29: Bicho / Lucha / Veneno / Planta / Hada | AO29: Tierra / Psíquico | AP29: Bicho / Lucha / Veneno / Planta / Hada
A30: 98 | B30: Krabby | C30: Kanto | D30: Water | F30: NORMAL | G30: S | H30: Krabby | I30: 11 | J30: - | K30: Candy | S30: 325 | T30: 30 | U30: 105 | V30: 90 | W30: 25 | X30: 25 | Y30: 50 | Z30: 10 | AA30: 5 | AB30: 5 | AC30: =SUM(Z30:AB30) -> 20 | AD30: D | AE30: Defensor | AF30: T | AH30: T | AI30: Agarre | AJ30: Concha filo | AK30: Demolición | AL30: Pataleta | AM30: Eléctrico / Planta | AN30: Agua / Acero / Fuego / Hielo | AO30: Eléctrico / Planta | AP30: Agua / Acero / Fuego / Hielo
A31: 57 | B31: Primeape | C31: Kanto | D31: Fighting | F31: NORMAL | G31: L | H31: Mankey | I31: 21 | J31: Mankey | K31: Fully evolved | S31: 455 | T31: 65 | U31: 105 | V31: 60 | W31: 60 | X31: 70 | Y31: 95 | Z31: 13 | AA31: 6 | AB31: 10 | AC31: =SUM(Z31:AB31) -> 29 | AD31: C | AE31: Cólera | AF31: C | AH31: C | AI31: Avalancha | AJ31: Demolición | AK31: Enfado | AL31: Sofoco | AM31: Volador / Hada / Psíquico | AN31: Bicho / Siniestro / Roca | AO31: Volador / Hada / Psíquico | AP31: Bicho / Siniestro / Roca
A32: 224 | B32: Octillery | C32: Johto | D32: Water | F32: NORMAL | G32: L | H32: Remoraid | I32: 21 | J32: Remoraid | K32: Fully evolved | S32: 480 | T32: 75 | U32: 105 | V32: 75 | W32: 105 | X32: 75 | Y32: 45 | Z32: 15 | AA32: 10.5 | AB32: 5 | AC32: =SUM(Z32:AB32) -> 30.5 | AD32: B
A33: 160 | B33: Feraligatr | C33: Johto | D33: Water | F33: STARTER | G33: L | H33: Totodile | I33: 31 | J33: Croconaw | K33: Fully evolved | S33: 530 | T33: 85 | U33: 105 | V33: 100 | W33: 79 | X33: 83 | Y33: 78 | Z33: 18 | AA33: 8.5 | AB33: 8 | AC33: =SUM(Z33:AB33) -> 34.5 | AD33: A
A34: 107 | B34: Hitmonchan | C34: Kanto | D34: Fighting | F34: NORMAL | G34: L | H34: Tyrogue | I34: 22 | J34: Tyrogue | K34: Fully evolved | R34: ATQ > SPD | S34: 455 | T34: 50 | U34: 105 | V34: 79 | W34: 35 | X34: 110 | Y34: 76 | Z34: 16 | AA34: 7 | AB34: 8 | AC34: =SUM(Z34:AB34) -> 31 | AD34: B | AE34: ¡Al ring! | AF34: T | AH34: T | AI34: Puño hielo | AJ34: Puño drenaje | AK34: Puño bala | AL34: Desarme | AM34: Volador / Hada / Psíquico | AN34: Bicho / Siniestro / Roca | AO34: Volador / Hada / Psíquico | AP34: Bicho / Siniestro / Roca
A35: 34 | B35: Nidoking | C35: Kanto | D35: Poison | E35: Ground | F35: NORMAL | G35: L | H35: Nidoran M | I35: 31 | J35: Nidorino | K35: Fully evolved | S35: 505 | T35: 81 | U35: 102 | V35: 77 | W35: 85 | X35: 75 | Y35: 85 | Z35: 16 | AA35: 7.5 | AB35: 9 | AC35: =SUM(Z35:AB35) -> 32.5 | AD35: B | AE35: Lealtad | AF35: C | AH35: C | AI35: Terremoto | AJ35: Lanzallamas | AK35: Rayo hielo | AL35: Rayo | AM35: Tierra / Hielo / Psíquico / Agua | AN35: Eléctrico / Veneno / Bicho / Hada / Lucha / Roca | AO35: Tierra / Hielo / Psíquico / Agua | AP35: Eléctrico / Veneno / Bicho / Hada / Lucha / Roca
A36: 251 | B36: Celebi | C36: Johto | D36: Psychic | E36: Grass | F36: NORMAL | G36: L | H36: Celebi | I36: 11 | J36: - | K36: Fully evolved | S36: 600 | T36: 100 | U36: 100 | V36: 100 | W36: 100 | X36: 100 | Y36: 100 | Z36: 20 | AA36: 9.5 | AB36: 10 | AC36: =SUM(Z36:AB36) -> 39.5 | AD36: S
A37: 67 | B37: Machoke | C37: Kanto | D37: Fighting | F37: NORMAL | G37: M | H37: Machop | I37: 21 | J37: Machop | K37: Trading | S37: 405 | T37: 80 | U37: 100 | V37: 70 | W37: 50 | X37: 60 | Y37: 45 | Z37: 14 | AA37: 6 | AB37: 5 | AC37: =SUM(Z37:AB37) -> 25 | AD37: D | AE37: Peleón | AF37: T | AH37: T | AI37: Tumba rocas | AJ37: Demolición | AK37: Puño hielo | AL37: Vendetta | AM37: Volador / Hada / Psíquico | AN37: Bicho / Siniestro / Roca | AO37: Volador / Hada / Psíquico | AP37: Bicho / Siniestro / Roca
A38: 151 | B38: Mew | C38: Kanto | D38: Psychic | F38: LEGEND | G38: L | H38: Mew | I38: 11 | J38: - | K38: Fully evolved | S38: 600 | T38: 100 | U38: 100 | V38: 100 | W38: 100 | X38: 100 | Y38: 100 | Z38: 20 | AA38: 9.5 | AB38: 10 | AC38: =SUM(Z38:AB38) -> 39.5 | AD38: S | AE38: Tinovictoria | AF38: T | AH38: T | AI38: Psíquico | AJ38: Fitoimpulso | AK38: Poltergeist | AL38: Esfera aural | AM38: Siniestro / Fantasma / Bicho | AN38: Psíquico / Lucha | AO38: Siniestro / Fantasma / Bicho | AP38: Psíquico / Lucha
A39: 146 | B39: Moltres | C39: Kanto | D39: Fire | E39: Flying | F39: LEGEND | G39: L | H39: Moltres | I39: 11 | J39: - | K39: Fully evolved | S39: 580 | T39: 90 | U39: 100 | V39: 90 | W39: 125 | X39: 85 | Y39: 90 | Z39: 18 | AA39: 10.5 | AB39: 9 | AC39: =SUM(Z39:AB39) -> 37.5 | AD39: S | AE39: Restauración | AF39: T | AH39: T | AI39: Ataque aéreo | AJ39: Llamarada | AK39: Rayo solar | AL39: Arenas ardientes | AM39: Eléctrico / Roca / Agua | AN39: Tierra / Bicho / Planta / Hada / Lucha / Fuego / Acero | AO39: Eléctrico / Roca / Agua | AP39: Tierra / Bicho / Planta / Hada / Lucha / Fuego / Acero
A40: 78 | B40: Rapidash | C40: Kanto | D40: Fire | F40: NORMAL | G40: L | H40: Ponyta | I40: 21 | J40: Ponyta | K40: Fully evolved | S40: 500 | T40: 65 | U40: 100 | V40: 70 | W40: 80 | X40: 80 | Y40: 105 | Z40: 14 | AA40: 7.5 | AB40: 11 | AC40: =SUM(Z40:AB40) -> 32.5 | AD40: B | AE40: Ultra impulso | AF40: T | AH40: T | AI40: Bote | AJ40: Llamarada | AK40: Hypnosis | AL40: Fuerza equina | AM40: Tierra / Roca / Agua | AN40: Bicho / Fuego / Acero / Hielo / Planta / Hada | AO40: Tierra / Roca / Agua | AP40: Bicho / Fuego / Acero / Hielo / Planta / Hada
A41: 28 | B41: Sandslash | C41: Kanto | D41: Ground | F41: NORMAL | G41: L | H41: Sandshrew | I41: 21 | J41: Sandshrew | K41: Fully evolved | S41: 450 | T41: 75 | U41: 100 | V41: 110 | W41: 45 | X41: 55 | Y41: 65 | Z41: 16 | AA41: 7.5 | AB41: 7 | AC41: =SUM(Z41:AB41) -> 30.5 | AD41: B | AE41: Cuchillada | AF41: T | AH41: T | AI41: Garra brutal | AJ41: Terremoto | AK41: Puya nociva | AL41: Avalancha | AM41: Planta / Hielo / Agua | AN41: Eléctrico / Roca / Veneno | AO41: Planta / Hielo / Agua | AP41: Eléctrico / Roca / Veneno
A42: 185 | B42: Sudowoodo | C42: Johto | D42: Rock | F42: NORMAL | G42: L | H42: Sudowoodo | I42: 11 | J42: - | K42: Fully evolved | S42: 410 | T42: 70 | U42: 100 | V42: 115 | W42: 30 | X42: 65 | Y42: 30 | Z42: 17 | AA42: 7 | AB42: 3 | AC42: =SUM(Z42:AB42) -> 27 | AD42: C
A43: 221 | B43: Piloswine | C43: Johto | D43: Ice | E43: Ground | F43: NORMAL | G43: L | H43: Swinub | I43: 21 | J43: Swinub | K43: Fully evolved | S43: 450 | T43: 100 | U43: 100 | V43: 80 | W43: 60 | X43: 60 | Y43: 50 | Z43: 16 | AA43: 7.5 | AB43: 5 | AC43: =SUM(Z43:AB43) -> 28.5 | AD43: C
A44: 128 | B44: Tauros | C44: Kanto | D44: Normal | F44: NORMAL | G44: L | H44: Tauros | I44: 11 | J44: - | K44: Fully evolved | S44: 490 | T44: 75 | U44: 100 | V44: 95 | W44: 40 | X44: 70 | Y44: 110 | Z44: 16 | AA44: 6 | AB44: 11 | AC44: =SUM(Z44:AB44) -> 33 | AD44: B | AE44: Retroceso | AF44: C | AH44: C | AI44: Golpe cuerpo | AJ44: Ventisca | AK44: Cabezazo zen | AL44: Llamarada | AM44: Lucha | AN44: Fantasma | AO44: Lucha | AP44: Fantasma
A45: 103 | B45: Exeggutor | C45: Kanto | D45: Grass | E45: Psychic | F45: NORMAL | G45: L | H45: Exeggcute | I45: 21 | J45: Exeggcute | K45: Fully evolved | S45: 520 | T45: 95 | U45: 95 | V45: 85 | W45: 125 | X45: 65 | Y45: 55 | Z45: 16 | AA45: 7.5 | AB45: 6 | AC45: =SUM(Z45:AB45) -> 29.5 | AD45: B | AE45: Espacio raro | AF45: C | AG45: Coshecha | AH45: C | AI45: Energibola | AJ45: Psíquico | AK45: Somnífero | AL45: Pesadilla | AM45: Fuego / Volador / Fantasma / Siniestro / Hielo / Veneno / Bicho | AN45: Agua / Lucha / Psíquico / Tierra / Planta / Eléctrico | AO45: Fuego / Volador / Fantasma / Siniestro / Hielo / Veneno / Bicho | AP45: Agua / Lucha / Psíquico / Tierra / Planta / Eléctrico
A46: 75 | B46: Graveler | C46: Kanto | D46: Rock | E46: Ground | F46: NORMAL | G46: M | H46: Geodude | I46: 21 | J46: Geodude | K46: Trading | S46: 390 | T46: 55 | U46: 95 | V46: 115 | W46: 45 | X46: 45 | Y46: 35 | Z46: 14 | AA46: 4 | AB46: 4 | AC46: =SUM(Z46:AB46) -> 22 | AD46: D | AE46: Autodestrucción | AF46: T | AG46: Robustez | AH46: T | AI46: Lanzarrocas | AJ46: Magnitud | AK46: Megapuño | AL46: Pulimiento | AM46: Acero / Lucha / Tierra / Hielo / Planta / Agua | AN46: Eléctrico / Veneno / Fuego / Volador / Normal / Roca | AO46: Acero / Lucha / Tierra / Hielo / Planta / Agua | AP46: Eléctrico / Veneno / Fuego / Volador / Normal / Roca
A47: 230 | B47: Kingdra | C47: Johto | D47: Water | E47: Dragon | F47: NORMAL | G47: L | H47: Horsea | I47: 31 | J47: Seadra | K47: Fully evolved | N47: M2 | S47: 540 | T47: 75 | U47: 95 | V47: 95 | W47: 95 | X47: 95 | Y47: 85 | Z47: 18 | AA47: 9.5 | AB47: 9 | AC47: =SUM(Z47:AB47) -> 36.5 | AD47: A
A48: 115 | B48: Kangaskhan | C48: Kanto | D48: Normal | F48: NORMAL | G48: L | H48: Kangaskhan | I48: 11 | J48: - | K48: Fully evolved | S48: 490 | T48: 105 | U48: 95 | V48: 80 | W48: 40 | X48: 80 | Y48: 90 | Z48: 18 | AA48: 10.5 | AB48: 9 | AC48: =SUM(Z48:AB48) -> 37.5 | AD48: S | AE48: Marsupial | AF48: T | AH48: T | AI48: Puño mareo | AJ48: Triturar | AK48: Machada | AL48: Giga impacto | AM48: Lucha | AN48: Fantasma | AO48: Lucha | AP48: Fantasma
A49: 126 | B49: Magmar | C49: Kanto | D49: Fire | F49: NORMAL | G49: L | H49: Magby | I49: 21 | J49: Magby | K49: Fully evolved | S49: 495 | T49: 65 | U49: 95 | V49: 57 | W49: 100 | X49: 85 | Y49: 93 | Z49: 14 | AA49: 8.5 | AB49: 9 | AC49: =SUM(Z49:AB49) -> 31.5 | AD49: B | AE49: Resquicio | AF49: C | AH49: C | AI49: Tajo cruzado | AJ49: Lanzallamas | AK49: Puño trueno | AL49: Niebla clara | AM49: Tierra / Roca / Agua | AN49: Bicho / Fuego / Acero / Hielo / Planta / Hada | AO49: Tierra / Roca / Agua | AP49: Bicho / Fuego / Acero / Hielo / Planta / Hada
A50: 47 | B50: Parasect | C50: Kanto | D50: Bug | E50: Grass | F50: NORMAL | G50: L | H50: Paras | I50: 21 | J50: Paras | K50: Fully evolved | S50: 405 | T50: 60 | U50: 95 | V50: 80 | W50: 60 | X50: 80 | Y50: 30 | Z50: 15 | AA50: 6 | AB50: 3 | AC50: =SUM(Z50:AB50) -> 24 | AD50: D | AE50: Efecto Espora | AF50: C | AH50: C | AI50: Tijera X | AJ50: Gigadrenado | AK50: Veneno X | AL50: Polvo ira | AM50: Hielo / Veneno / Roca / Bicho / Fuego / Volador | AN50: Planta / Tierra / Lucha / Agua / Eléctrico | AO50: Hielo / Veneno / Roca / Bicho / Fuego / Volador | AP50: Planta / Tierra / Lucha / Agua / Eléctrico
A51: 62 | B51: Poliwrath | C51: Kanto | D51: Water | E51: Fighting | F51: NORMAL | G51: L | H51: Poliwag | I51: 31 | J51: Poliwhirl | K51: Fully evolved | S51: 510 | T51: 90 | U51: 95 | V51: 95 | W51: 70 | X51: 90 | Y51: 70 | Z51: 18 | AA51: 8.5 | AB51: 7 | AC51: =SUM(Z51:AB51) -> 33.5 | AD51: A | AE51: Pura potencia | AF51: C | AH51: C | AI51: Cascada | AJ51: Puñodinámico | AK51: Terremoto | AL51: Puño hielo | AM51: Volador / Hada / Psíquico / Eléctrico / Planta | AN51: Bicho / Siniestro / Acero / Roca / Hielo / Agua / Fuego | AO51: Volador / Hada / Psíquico / Eléctrico / Planta | AP51: Bicho / Siniestro / Acero / Roca / Hielo / Agua / Fuego
A52: 211 | B52: Qwilfish | C52: Johto | D52: Water | E52: Poison | F52: NORMAL | G52: L | H52: Qwilfish | I52: 11 | J52: - | K52: Fully evolved | S52: 430 | T52: 65 | U52: 95 | V52: 75 | W52: 55 | X52: 55 | Y52: 85 | Z52: 13 | AA52: 7.5 | AB52: 9 | AC52: =SUM(Z52:AB52) -> 29.5 | AD52: B
A53: 91 | B53: Cloyster | C53: Kanto | D53: Water | E53: Ice | F53: NORMAL | G53: L | H53: Shellder | I53: 21 | J53: Shellder | K53: Fully evolved | S53: 525 | T53: 50 | U53: 95 | V53: 180 | W53: 85 | X53: 45 | Y53: 70 | Z53: 18 | AA53: 7 | AB53: 7 | AC53: =SUM(Z53:AB53) -> 32 | AD53: B | AE53: Encadenado | AF53: C | AH53: C | AI53: Carámbano | AJ53: Pedrada | AK53: Concha filo | AL53: Rompecoraza | AM53: Lucha / Eléctrico / Roca / Planta | AN53: Hielo / Agua | AO53: Lucha / Eléctrico / Roca / Planta | AP53: Hielo / Agua
A54: 215 | B54: Sneasel | C54: Johto | D54: Dark | E54: Ice | F54: NORMAL | G54: L | H54: Sneasel | I54: 11 | J54: - | K54: Fully evolved | S54: 430 | T54: 55 | U54: 95 | V54: 55 | W54: 35 | X54: 75 | Y54: 115 | Z54: 12 | AA54: 7 | AB54: 12 | AC54: =SUM(Z54:AB54) -> 31 | AD54: B
A55: 234 | B55: Stantler | C55: Johto | D55: Normal | F55: NORMAL | G55: L | H55: Stantler | I55: 11 | J55: - | K55: Fully evolved | S55: 465 | T55: 73 | U55: 95 | V55: 62 | W55: 85 | X55: 65 | Y55: 85 | Z55: 13 | AA55: 8.5 | AB55: 9 | AC55: =SUM(Z55:AB55) -> 30.5 | AD55: B
A56: 237 | B56: Hitmontop | C56: Johto | D56: Fighting | F56: NORMAL | G56: L | H56: Tyrogue | I56: 23 | J56: Tyrogue | K56: Fully evolved | R56: ATQ = SPD | S56: 455 | T56: 50 | U56: 95 | V56: 95 | W56: 35 | X56: 110 | Y56: 70 | Z56: 17 | AA56: 7 | AB56: 7 | AC56: =SUM(Z56:AB56) -> 31 | AD56: B
A57: 119 | B57: Seaking | C57: Kanto | D57: Water | F57: NORMAL | G57: L | H57: Goldeen | I57: 21 | J57: Goldeen | K57: Fully evolved | S57: 450 | T57: 80 | U57: 92 | V57: 65 | W57: 65 | X57: 80 | Y57: 68 | Z57: 15 | AA57: 6 | AB57: 7 | AC57: =SUM(Z57:AB57) -> 28 | AD57: C | AE57: Ensañamiento | AF57: C | AG57: Pararrayos | AH57: C | AI57: Bote | AJ57: Megacuerno | AK57: Hidroariete | AL57: Taladradora | AM57: Eléctrico / Planta | AN57: Agua / Acero / Fuego / Hielo | AO57: Eléctrico / Planta | AP57: Agua / Acero / Fuego / Hielo
A58: 31 | B58: Nidoqueen | C58: Kanto | D58: Poison | E58: Ground | F58: NORMAL | G58: L | H58: Nidoran H | I58: 31 | J58: Nidorina | K58: Fully evolved | S58: 505 | T58: 90 | U58: 92 | V58: 87 | W58: 75 | X58: 85 | Y58: 76 | Z58: 17 | AA58: 7.5 | AB58: 8 | AC58: =SUM(Z58:AB58) -> 32.5 | AD58: B | AE58: Lealtad | AF58: C | AH58: C | AI58: Triturar | AJ58: Onda tóxica | AK58: Tierra viva | AL58: Fuerza bruta | AM58: Tierra / Hielo / Psíquico / Agua | AN58: Eléctrico / Veneno / Bicho / Hada / Lucha / Roca | AO58: Tierra / Hielo / Psíquico / Agua | AP58: Eléctrico / Veneno / Bicho / Hada / Lucha / Roca
A59: 70 | B59: Weepinbell | C59: Kanto | D59: Grass | E59: Poison | F59: NORMAL | G59: M | H59: Bellsprout | I59: 21 | J59: Bellsprout | K59: Stone | S59: 390 | T59: 65 | U59: 90 | V59: 50 | W59: 85 | X59: 45 | Y59: 55 | Z59: 11 | AA59: 5 | AB59: 6 | AC59: =SUM(Z59:AB59) -> 22 | AD59: D | AE59: Aclimatación | AF59: T | AG59: Clorofila | AH59: C | AI59: Paralizador | AJ59: Ácido | AK59: Constricción | AL59: Desarme | AM59: Fuego / Volador / Hielo / Psíquico | AN59: Planta / Hada / Lucha / Agua / Eléctrico | AO59: Fuego / Volador / Hielo / Psíquico | AP59: Planta / Hada / Lucha / Agua / Eléctrico
A60: 229 | B60: Houndoom | C60: Johto | D60: Dark | E60: Fire | F60: NORMAL | G60: L | H60: Houndour | I60: 21 | J60: Houndour | K60: Fully evolved | S60: 500 | T60: 75 | U60: 90 | V60: 50 | W60: 110 | X60: 80 | Y60: 95 | Z60: 14 | AA60: 9.5 | AB60: 10 | AC60: =SUM(Z60:AB60) -> 33.5 | AD60: A
A61: 110 | B61: Weezing | C61: Kanto | D61: Poison | F61: NORMAL | G61: L | H61: Koffing | I61: 21 | J61: Koffing | K61: Fully evolved | S61: 490 | T61: 65 | U61: 90 | V61: 120 | W61: 85 | X61: 70 | Y61: 60 | Z61: 17 | AA61: 7.5 | AB61: 6 | AC61: =SUM(Z61:AB61) -> 30.5 | AD61: B | AE61: Gas reactivo | AF61: C | AH61: C | AI61: Onda ígnea | AJ61: Onda tóxica | AK61: Gas corrosivo | AL61: Pulso umbío | AM61: Tierra / Psíquico | AN61: Bicho / Lucha / Veneno / Planta / Hada | AO61: Tierra / Psíquico | AP61: Bicho / Lucha / Veneno / Planta / Hada
A62: 249 | B62: Lugia | C62: Johto | D62: Psychic | E62: Flying | F62: LEGEND | G62: L | H62: Lugia | I62: 11 | J62: - | K62: Fully evolved | S62: 680 | T62: 106 | U62: 90 | V62: 130 | W62: 90 | X62: 154 | Y62: 110 | Z62: 26 | AA62: 8.5 | AB62: 11 | AC62: =SUM(Z62:AB62) -> 45.5 | AD62: S
A63: 26 | B63: Raichu | C63: Kanto | D63: Electric | F63: NORMAL | G63: L | H63: Pichu | I63: 31 | J63: Pikachu | K63: Fully evolved | S63: 485 | T63: 60 | U63: 90 | V63: 55 | W63: 90 | X63: 80 | Y63: 110 | Z63: 13 | AA63: 7.5 | AB63: 11 | AC63: =SUM(Z63:AB63) -> 31.5 | AD63: B | AE63: Aspirante | AF63: T | AH63: T | AI63: Placaj. eléc. | AJ63: Rayo | AK63: Carantoña | AL63: Surf | AM63: Tierra | AN63: Acero / Eléctrico / Volador | AO63: Tierra | AP63: Acero / Eléctrico / Volador
A64: 205 | B64: Forretress | C64: Johto | D64: Bug | E64: Steel | F64: NORMAL | G64: L | H64: Pineco | I64: 21 | J64: Pineco | K64: Fully evolved | S64: 465 | T64: 75 | U64: 90 | V64: 140 | W64: 60 | X64: 60 | Y64: 40 | Z64: 18 | AA64: 7.5 | AB64: 4 | AC64: =SUM(Z64:AB64) -> 29.5 | AD64: B
A65: 22 | B65: Fearow | C65: Kanto | D65: Flying | E65: Normal | F65: NORMAL | G65: L | H65: Spearow | I65: 21 | J65: Spearow | K65: Fully evolved | S65: 442 | T65: 65 | U65: 90 | V65: 65 | W65: 61 | X65: 61 | Y65: 100 | Z65: 13 | AA65: 7 | AB65: 10 | AC65: =SUM(Z65:AB65) -> 30 | AD65: B | AE65: Cartero | AF65: T | AH65: T | AI65: Pico taladro | AJ65: Ataque furia | AK65: Golpe mordaza | AL65: Taladradora | AM65: Eléctrico / Hielo / Roca | AN65: Tierra / Fantasma / Bicho / Planta | AO65: Eléctrico / Hielo / Roca | AP65: Tierra / Fantasma / Bicho / Planta
A66: 168 | B66: Ariados | C66: Johto | D66: Bug | E66: Poison | F66: NORMAL | G66: L | H66: Spinarak | I66: 21 | J66: Spinarak | K66: Fully evolved | S66: 390 | T66: 70 | U66: 90 | V66: 70 | W66: 60 | X66: 60 | Y66: 40 | Z66: 13 | AA66: 7.5 | AB66: 4 | AC66: =SUM(Z66:AB66) -> 24.5 | AD66: D
A67: 15 | B67: Beedrill | C67: Kanto | D67: Bug | E67: Poison | F67: NORMAL | G67: L | H67: Weedle | I67: 31 | J67: Kakuna | K67: Fully evolved | S67: 395 | T67: 65 | U67: 90 | V67: 40 | W67: 45 | X67: 80 | Y67: 75 | Z67: 12 | AA67: 7 | AB67: 8 | AC67: =SUM(Z67:AB67) -> 27 | AD67: C | AE67: Enjambre | AF67: C | AH67: C | AI67: Púas tóxicas | AJ67: Puya nociva | AK67: Aguijón letal | AL67: Taladradora | AM67: Fuego / Volador / Psíquico / Roca | AN67: Planta / Lucha / Veneno / Bicho / Hada | AO67: Fuego / Volador / Psíquico / Roca | AP67: Planta / Lucha / Veneno / Bicho / Hada
A68: 145 | B68: Zapdos | C68: Kanto | D68: Electric | E68: Flying | F68: LEGEND | G68: L | H68: Zapdos | I68: 11 | J68: - | K68: Fully evolved | S68: 580 | T68: 90 | U68: 90 | V68: 85 | W68: 125 | X68: 90 | Y68: 100 | Z68: 18 | AA68: 10.5 | AB68: 10 | AC68: =SUM(Z68:AB68) -> 38.5 | AD68: S | AE68: Presión | AF68: C | AH68: C | AI68: Pico taladro | AJ68: Trueno | AK68: Onda ígnea | AL68: Viento aciago | AM68: Hielo / Roca | AN68: Tierra / Bicho / Volador / Acero / Planta / Lucha | AO68: Hielo / Roca | AP68: Tierra / Bicho / Volador / Acero / Planta / Lucha
A69: 169 | B69: Crobat | C69: Johto | D69: Poison | E69: Flying | F69: NORMAL | G69: L | H69: Zubat | I69: 31 | J69: Golbat | K69: Fully evolved | L69: 60 | S69: 535 | T69: 85 | U69: 90 | V69: 80 | W69: 70 | X69: 80 | Y69: 130 | Z69: 16 | AA69: 7.5 | AB69: 13 | AC69: =SUM(Z69:AB69) -> 36.5 | AD69: A
A70: 144 | B70: Articuno | C70: Kanto | D70: Ice | E70: Flying | F70: LEGEND | G70: L | H70: Articuno | I70: 11 | J70: - | K70: Fully evolved | S70: 580 | T70: 90 | U70: 85 | V70: 100 | W70: 95 | X70: 125 | Y70: 85 | Z70: 21 | AA70: 10.5 | AB70: 9 | AC70: =SUM(Z70:AB70) -> 40.5 | AD70: S | AE70: Afortunado | AF70: T | AH70: T | AI70: Vendaval | AJ70: Ventisca | AK70: Paranormal | AL70: Poder pasado | AM70: Eléctrico / Fuego / Acero / Roca | AN70: Tierra / Bicho / Planta | AO70: Eléctrico / Fuego / Acero / Roca | AP70: Tierra / Bicho / Planta
A71: 84 | B71: Doduo | C71: Kanto | D71: Flying | E71: Normal | F71: NORMAL | G71: S | H71: Doduo | I71: 11 | J71: - | K71: Candy | S71: 310 | T71: 35 | U71: 85 | V71: 45 | W71: 35 | X71: 35 | Y71: 75 | Z71: 8 | AA71: 4 | AB71: 8 | AC71: =SUM(Z71:AB71) -> 20 | AD71: D | AE71: Pies rápidos | AF71: T | AH71: T | AI71: Picotazo | AJ71: Ataque furia | AK71: At. Rápido | AL71: Persecución | AM71: Eléctrico / Hielo / Roca | AN71: Tierra / Fantasma / Bicho / Planta | AO71: Eléctrico / Hielo / Roca | AP71: Tierra / Fantasma / Bicho / Planta
A72: 24 | B72: Arbok | C72: Kanto | D72: Poison | F72: NORMAL | G72: L | H72: Ekans | I72: 21 | J72: Ekans | K72: Fully evolved | S72: 438 | T72: 60 | U72: 85 | V72: 69 | W72: 65 | X72: 79 | Y72: 80 | Z72: 14 | AA72: 7.5 | AB72: 8 | AC72: =SUM(Z72:AB72) -> 29.5 | AD72: B | AE72: Intimidación | AF72: C | AH72: C | AI72: Enrosque | AJ72: Colm. Veneno | AK72: Pulso umbrío | AL72: Bomba germen | AM72: Tierra / Psíquico | AN72: Bicho / Lucha / Veneno / Planta / Hada | AO72: Tierra / Psíquico | AP72: Bicho / Lucha / Veneno / Planta / Hada
A73: 131 | B73: Lapras | C73: Kanto | D73: Water | E73: Ice | F73: NORMAL | G73: L | H73: Lapras | I73: 11 | J73: - | K73: Fully evolved | S73: 535 | T73: 130 | U73: 85 | V73: 80 | W73: 85 | X73: 95 | Y73: 60 | Z73: 20 | AA73: 7.5 | AB73: 6 | AC73: =SUM(Z73:AB73) -> 33.5 | AD73: A | AE73: Rey del mar | AF73: T | AH73: T | AI73: Liofilización | AJ73: Hidrobomba | AK73: Trueno | AL73: Pulso dragón | AM73: Lucha / Eléctrico / Roca / Planta | AN73: Hielo / Agua | AO73: Lucha / Eléctrico / Roca / Planta | AP73: Hielo / Agua
A74: 198 | B74: Murkrow | C74: Johto | D74: Dark | E74: Flying | F74: NORMAL | G74: L | H74: Murkrow | I74: 11 | J74: - | K74: Fully evolved | S74: 405 | T74: 60 | U74: 85 | V74: 42 | W74: 85 | X74: 42 | Y74: 91 | Z74: 10 | AA74: 8.5 | AB74: 9 | AC74: =SUM(Z74:AB74) -> 27.5 | AD74: C
A75: 208 | B75: Steelix | C75: Johto | D75: Steel | E75: Ground | F75: NORMAL | G75: L | H75: Onix | I75: 21 | J75: Onix | K75: Fully evolved | N75: M1 | S75: 510 | T75: 75 | U75: 85 | V75: 200 | W75: 55 | X75: 65 | Y75: 30 | Z75: 23 | AA75: 7 | AB75: 3 | AC75: =SUM(Z75:AB75) -> 33 | AD75: B
A76: 77 | B76: Ponyta | C76: Kanto | D76: Fire | F76: NORMAL | G76: S | H76: Ponyta | I76: 11 | J76: - | K76: Candy | S76: 410 | T76: 50 | U76: 85 | V76: 55 | W76: 65 | X76: 65 | Y76: 90 | Z76: 11 | AA76: 5 | AB76: 9 | AC76: =SUM(Z76:AB76) -> 25 | AD76: D | AE76: Impulso | AF76: T | AH76: T | AI76: Doble patada | AJ76: Rueda fuego | AK76: Hypnosis | AL76: Fuerza equina | AM76: Tierra / Roca / Agua | AN76: Bicho / Fuego / Acero / Hielo / Planta / Hada | AO76: Tierra / Roca / Agua | AP76: Bicho / Fuego / Acero / Hielo / Planta / Hada
A77: 243 | B77: Raikou | C77: Johto | D77: Electric | F77: LEGEND | G77: L | H77: Raikou | I77: 11 | J77: - | K77: Fully evolved | S77: 580 | T77: 90 | U77: 85 | V77: 75 | W77: 115 | X77: 100 | Y77: 115 | Z77: 18 | AA77: 8.5 | AB77: 12 | AC77: =SUM(Z77:AB77) -> 38.5 | AD77: S
A78: 111 | B78: Rhyhorn | C78: Kanto | D78: Ground | E78: Rock | F78: NORMAL | G78: S | H78: Rhyhorn | I78: 11 | J78: - | K78: Candy | S78: 345 | T78: 80 | U78: 85 | V78: 95 | W78: 30 | X78: 30 | Y78: 25 | Z78: 14 | AA78: 5 | AB78: 3 | AC78: =SUM(Z78:AB78) -> 22 | AD78: D | AE78: Irascible | AF78: C | AH78: C | AI78: Cornada | AJ78: Pedrada | AK78: Placaje | AL78: Terratemblor | AM78: Acero / Lucha / Tierra / Hielo / Planta / Agua | AN78: Eléctrico / Veneno / Fuego / Volador / Normal / Roca | AO78: Acero / Lucha / Tierra / Hielo / Planta / Agua | AP78: Eléctrico / Veneno / Fuego / Volador / Normal / Roca
A79: 195 | B79: Quagsire | C79: Johto | D79: Water | E79: Ground | F79: NORMAL | G79: L | H79: Wooper | I79: 21 | J79: Wooper | K79: Fully evolved | S79: 430 | T79: 95 | U79: 85 | V79: 85 | W79: 65 | X79: 65 | Y79: 35 | Z79: 16 | AA79: 7.5 | AB79: 4 | AC79: =SUM(Z79:AB79) -> 27.5 | AD79: C
A80: 6 | B80: Charizard | C80: Kanto | D80: Fire | E80: Flying | F80: STARTER | G80: L | H80: Charmander | I80: 31 | J80: Charmeleon | K80: Fully evolved | S80: 534 | T80: 78 | U80: 84 | V80: 78 | W80: 109 | X80: 85 | Y80: 100 | Z80: 16 | AA80: 7.5 | AB80: 10 | AC80: =SUM(Z80:AB80) -> 33.5 | AD80: A | AE80: Rivalidad | AF80: C | AH80: C | AI80: Puño trueno | AJ80: Lanzallamas | AK80: Viento aciago | AL80: Tajo aéreo | AM80: Eléctrico / Roca / Agua | AN80: Tierra / Bicho / Planta / Hada / Lucha / Fuego / Acero | AO80: Eléctrico / Roca / Agua | AP80: Tierra / Bicho / Planta / Hada / Lucha / Fuego / Acero
A81: 157 | B81: Typhlosion | C81: Johto | D81: Fire | F81: STARTER | G81: L | H81: Cyndaquil | I81: 31 | J81: Quilava | K81: Fully evolved | S81: 534 | T81: 78 | U81: 84 | V81: 78 | W81: 109 | X81: 85 | Y81: 100 | Z81: 16 | AA81: 9.5 | AB81: 10 | AC81: =SUM(Z81:AB81) -> 35.5 | AD81: A
A82: 148 | B82: Dragonair | C82: Kanto | D82: Dragon | F82: NORMAL | G82: M | H82: Dratini | I82: 21 | J82: Dratini | K82: Candy | S82: 420 | T82: 61 | U82: 84 | V82: 65 | W82: 70 | X82: 70 | Y82: 70 | Z82: 13 | AA82: 7 | AB82: 7 | AC82: =SUM(Z82:AB82) -> 27 | AD82: C | AE82: Iluminación | AF82: T | AH82: T | AI82: Vel. Extrema | AJ82: Dragoaliento | AK82: Rayo | AL82: Aqua jet | AM82: Hada / Dragón / Hielo | AN82: Agua / Fuego / Planta / Eléctrico | AO82: Hada / Dragón / Hielo | AP82: Agua / Fuego / Planta / Eléctrico
A83: 247 | B83: Pupitar | C83: Johto | D83: Rock | E83: Ground | F83: NORMAL | G83: M | H83: Larvitar | I83: 21 | J83: Larvitar | K83: Candy | S83: 410 | T83: 70 | U83: 84 | V83: 70 | W83: 65 | X83: 70 | Y83: 51 | Z83: 14 | AA83: 7 | AB83: 5 | AC83: =SUM(Z83:AB83) -> 26 | AD83: C
A84: 125 | B84: Electabuzz | C84: Kanto | D84: Electric | F84: NORMAL | G84: L | H84: Elekid | I84: 21 | J84: Elekid | K84: Fully evolved | S84: 490 | T84: 65 | U84: 83 | V84: 57 | W84: 95 | X84: 85 | Y84: 105 | Z84: 14 | AA84: 7.5 | AB84: 11 | AC84: =SUM(Z84:AB84) -> 32.5 | AD84: B | AE84: Intrépido | AF84: C | AH84: C | AI84: Puño hielo | AJ84: Rayo | AK84: Patada baja | AL84: Puño mareo | AM84: Tierra | AN84: Acero / Eléctrico / Volador | AO84: Tierra | AP84: Acero / Eléctrico / Volador
A85: 9 | B85: Blastoise | C85: Kanto | D85: Water | F85: STARTER | G85: L | H85: Squirtle | I85: 31 | J85: Wartortle | K85: Fully evolved | S85: 530 | T85: 79 | U85: 83 | V85: 100 | W85: 85 | X85: 105 | Y85: 78 | Z85: 19 | AA85: 7.5 | AB85: 8 | AC85: =SUM(Z85:AB85) -> 34.5 | AD85: A | AE85: Doble Cañón | AF85: C | AH85: C | AI85: Ventisca | AJ85: Hidrobomba | AK85: Cabezazo zen | AL85: Foco resplandor | AM85: Eléctrico / Planta | AN85: Agua / Acero / Fuego / Hielo | AO85: Eléctrico / Planta | AP85: Agua / Acero / Fuego / Hielo
A86: 3 | B86: Venusaur | C86: Kanto | D86: Grass | E86: Poison | F86: STARTER | G86: L | H86: Bulbasaur | I86: 31 | J86: Ivysaur | K86: Fully evolved | S86: 525 | T86: 80 | U86: 82 | V86: 83 | W86: 100 | X86: 100 | Y86: 80 | Z86: 18 | AA86: 7.5 | AB86: 8 | AC86: =SUM(Z86:AB86) -> 33.5 | AD86: A | AE86: Sebo | AF86: C | AG86: Clorofila | AH86: C | AI86: Somnífero | AJ86: Gigadrenado | AK86: Terremoto | AL86: Onda tóxica | AM86: Fuego / Volador / Hielo / Psíquico | AN86: Planta / Hada / Lucha / Agua / Eléctrico | AO86: Fuego / Volador / Hielo / Psíquico | AP86: Planta / Hada / Lucha / Agua / Eléctrico
A87: 154 | B87: Meganium | C87: Johto | D87: Grass | F87: STARTER | G87: L | H87: Chikorita | I87: 31 | J87: Bayleef | K87: Fully evolved | S87: 525 | T87: 80 | U87: 82 | V87: 100 | W87: 83 | X87: 100 | Y87: 80 | Z87: 19 | AA87: 7.5 | AB87: 8 | AC87: =SUM(Z87:AB87) -> 34.5 | AD87: A
A88: 55 | B88: Golduck | C88: Kanto | D88: Water | F88: NORMAL | G88: L | H88: Psyduck | I88: 21 | J88: Psyduck | K88: Fully evolved | S88: 500 | T88: 80 | U88: 82 | V88: 78 | W88: 95 | X88: 80 | Y88: 85 | Z88: 16 | AA88: 7 | AB88: 9 | AC88: =SUM(Z88:AB88) -> 32 | AD88: B | AE88: Nadador | AF88: T | AH88: T | AI88: Cabezazo zen | AJ88: Surf | AK88: Hypnosis | AL88: Tajo cruzado | AM88: Eléctrico / Planta | AN88: Agua / Acero / Fuego / Hielo | AO88: Eléctrico / Planta | AP88: Agua / Acero / Fuego / Hielo
A89: 20 | B89: Raticate | C89: Kanto | D89: Normal | F89: NORMAL | G89: L | H89: Rattata | I89: 21 | J89: Rattata | K89: Fully evolved | S89: 413 | T89: 55 | U89: 81 | V89: 60 | W89: 50 | X89: 70 | Y89: 97 | Z89: 12 | AA89: 6 | AB89: 10 | AC89: =SUM(Z89:AB89) -> 28 | AD89: C | AE89: Fuga | AF89: C | AH89: C | AI89: Superdiente | AJ89: Hipercolmillo | AK89: Voltio cruel | AL89: Golpe bajo | AM89: Lucha | AN89: Fantasma | AO89: Lucha | AP89: Fantasma
A90: 105 | B90: Marowak | C90: Kanto | D90: Ground | F90: NORMAL | G90: L | H90: Cubone | I90: 21 | J90: Cubone | K90: Fully evolved | S90: 425 | T90: 60 | U90: 80 | V90: 110 | W90: 50 | X90: 80 | Y90: 45 | Z90: 17 | AA90: 7.5 | AB90: 5 | AC90: =SUM(Z90:AB90) -> 29.5 | AD90: B | AE90: Receptor | AF90: C | AG90: Sombratrampa | AH90: C | AI90: Cabeza de hierro | AJ90: Huesomerang | AK90: Puño fuego | AL90: Maldición | AM90: Planta / Hielo / Agua | AN90: Eléctrico / Roca / Veneno | AO90: Planta / Hielo / Agua | AP90: Eléctrico / Roca / Veneno
A91: 51 | B91: Dugtrio | C91: Kanto | D91: Ground | F91: NORMAL | G91: L | H91: Diglett | I91: 21 | J91: Diglett | K91: Fully evolved | S91: 405 | T91: 35 | U91: 80 | V91: 50 | W91: 50 | X91: 70 | Y91: 120 | Z91: 10 | AA91: 6 | AB91: 12 | AC91: =SUM(Z91:AB91) -> 28 | AD91: C | AE91: Excavador | AF91: T | AH91: T | AI91: Terremoto | AJ91: Fisura | AK91: Golpe bajo | AL91: Garra umbía | AM91: Planta / Hielo / Agua | AN91: Eléctrico / Roca / Veneno | AO91: Planta / Hielo / Agua | AP91: Eléctrico / Roca / Veneno
A92: 74 | B92: Geodude | C92: Kanto | D92: Rock | E92: Ground | F92: NORMAL | G92: S | H92: Geodude | I92: 11 | J92: - | K92: Candy | S92: 300 | T92: 40 | U92: 80 | V92: 100 | W92: 30 | X92: 30 | Y92: 20 | Z92: 11 | AA92: 2 | AB92: 2 | AC92: =SUM(Z92:AB92) -> 15 | AD92: F | AE92: Autodestrucción | AF92: T | AG92: Robustez | AH92: T | AI92: Rodar | AJ92: Magnitud | AK92: Placaje | AL92: Pulimiento | AM92: Acero / Lucha / Tierra / Hielo / Planta / Agua | AN92: Eléctrico / Veneno / Fuego / Volador / Normal / Roca | AO92: Acero / Lucha / Tierra / Hielo / Planta / Agua | AP92: Eléctrico / Veneno / Fuego / Volador / Normal / Roca
A93: 203 | B93: Girafarig | C93: Johto | D93: Normal | E93: Psychic | F93: NORMAL | G93: L | H93: Girafarig | I93: 11 | J93: - | K93: Fully evolved | S93: 455 | T93: 70 | U93: 80 | V93: 65 | W93: 90 | X93: 65 | Y93: 85 | Z93: 13 | AA93: 8.5 | AB93: 9 | AC93: =SUM(Z93:AB93) -> 30.5 | AD93: B
A94: 88 | B94: Grimer | C94: Kanto | D94: Poison | F94: NORMAL | G94: S | H94: Grimer | I94: 11 | J94: - | K94: Candy | S94: 325 | T94: 80 | U94: 80 | V94: 50 | W94: 40 | X94: 50 | Y94: 25 | Z94: 12 | AA94: 4 | AB94: 3 | AC94: =SUM(Z94:AB94) -> 19 | AD94: E | AE94: Pestilente | AF94: T | AG94: Punto tóxico | AH94: C | AI94: Residuos | AJ94: Polución | AK94: Lengüetazo | AL94: Destructor | AM94: Tierra / Psíquico | AN94: Bicho / Lucha / Veneno / Planta / Hada | AO94: Tierra / Psíquico | AP94: Bicho / Lucha / Veneno / Planta / Hada
A95: 140 | B95: Kabuto | C95: Kanto | D95: Rock | E95: Water | F95: NORMAL | G95: S | H95: Kabuto | I95: 11 | J95: - | K95: Candy | S95: 355 | T95: 30 | U95: 80 | V95: 90 | W95: 55 | X95: 45 | Y95: 55 | Z95: 11 | AA95: 5 | AB95: 6 | AC95: =SUM(Z95:AB95) -> 22 | AD95: D | AE95: Poder antiguo | AF95: T | AH95: T | AI95: Acua jet | AJ95: Absorber | AK95: Tumba rocas | AL95: Disparo lodo | AM95: Tierra / Lucha / Eléctrico / Planta | AN95: Fuego / Hielo / Veneno / Volador / Normal | AO95: Tierra / Lucha / Eléctrico / Planta | AP95: Fuego / Hielo / Veneno / Volador / Normal
A96: 66 | B96: Machop | C96: Kanto | D96: Fighting | F96: NORMAL | G96: S | H96: Machop | I96: 11 | J96: - | K96: Candy | S96: 305 | T96: 70 | U96: 80 | V96: 50 | W96: 35 | X96: 35 | Y96: 35 | Z96: 10 | AA96: 4 | AB96: 4 | AC96: =SUM(Z96:AB96) -> 18 | AD96: E | AE96: Peleón | AF96: T | AH96: T | AI96: Tumba rocas | AJ96: Golpe karáte | AK96: Puño hielo | AL96: Lanzamiento | AM96: Volador / Hada / Psíquico | AN96: Bicho / Siniestro / Roca | AO96: Volador / Hada / Psíquico | AP96: Bicho / Siniestro / Roca
A97: 56 | B97: Mankey | C97: Kanto | D97: Fighting | F97: NORMAL | G97: S | H97: Mankey | I97: 11 | J97: - | K97: Candy | S97: 305 | T97: 40 | U97: 80 | V97: 35 | W97: 35 | X97: 45 | Y97: 70 | Z97: 8 | AA97: 4 | AB97: 7 | AC97: =SUM(Z97:AB97) -> 19 | AD97: E | AE97: Cólera | AF97: C | AH97: C | AI97: Golpes furia | AJ97: Patada baja | AK97: Golpe bis | AL97: Bofetón lodo | AM97: Volador / Hada / Psíquico | AN97: Bicho / Siniestro / Roca | AO97: Volador / Hada / Psíquico | AP97: Bicho / Siniestro / Roca
A98: 241 | B98: Miltank | C98: Johto | D98: Normal | F98: NORMAL | G98: L | H98: Miltank | I98: 11 | J98: - | K98: Fully evolved | S98: 490 | T98: 95 | U98: 80 | V98: 105 | W98: 40 | X98: 70 | Y98: 100 | Z98: 18 | AA98: 6 | AB98: 10 | AC98: =SUM(Z98:AB98) -> 34 | AD98: A
A99: 45 | B99: Vileplume | C99: Kanto | D99: Grass | E99: Poison | F99: NORMAL | G99: L | H99: Oddish | I99: 31 | J99: Gloom | K99: Fully evolved | S99: 490 | T99: 75 | U99: 80 | V99: 85 | W99: 110 | X99: 90 | Y99: 50 | Z99: 17 | AA99: 7.5 | AB99: 5 | AC99: =SUM(Z99:AB99) -> 29.5 | AD99: B | AE99: Alma cura | AF99: C | AG99: Poder solar | AH99: C | AI99: Tóxico | AJ99: Gigadrenado | AK99: Bomba lodo | AL99: Fuerza lunar | AM99: Fuego / Volador / Hielo / Psíquico | AN99: Planta / Hada / Lucha / Agua / Eléctrico | AO99: Fuego / Volador / Hielo / Psíquico | AP99: Planta / Hada / Lucha / Agua / Eléctrico
A100: 182 | B100: Bellossom | C100: Johto | D100: Grass | F100: NORMAL | G100: L | H100: Oddish | I100: 32 | J100: Gloom | K100: Fully evolved | P100: Day | S100: 490 | T100: 75 | U100: 80 | V100: 95 | W100: 90 | X100: 100 | Y100: 50 | Z100: 18 | AA100: 8.5 | AB100: 5 | AC100: =SUM(Z100:AB100) -> 31.5 | AD100: B
...

Sheet Analisis lideres
B2: PKMN | C2: HP | D2: ATT | E2: SPD | F2: ALL | G2: SUM
B3: Sandshrew de Brock | C3: 11 | D3: 4 | E3: 4 | F3: =SUM(C3:E3) -> 19 | G3: =SUM(F3:F4) -> 48
B4: Onix de Brock | C4: 16 | D4: 6 | E4: 7 | F4: =SUM(C4:E4) -> 29
B5: Psyduck de Misty | C5: 9.8666667 | D5: 4 | E5: 5.5 | F5: =SUM(C5:E5) -> 19.366667 | G5: =SUM(F5:F6) -> 55.2
B6: Starmie de Misty | C6: 15.333333 | D6: 9 | E6: 11.5 | F6: =SUM(C6:E6) -> 35.833333
B7: Raichu de Lt Surge | C7: 13 | D7: 8 | E7: 11 | F7: =SUM(C7:E7) -> 32 | G7: =SUM(F7:F8) -> 64.3
B8: Electabuzz de Lt Surge | C8: 13.8 | D8: 8 | E8: 10.5 | F8: =SUM(C8:E8) -> 32.3
B9: Parasect de Erika | C9: 14.666667 | D9: 6 | E9: 3 | F9: =SUM(C9:E9) -> 23.666667 | G9: =SUM(F9:F10) -> 53.333333
B10: Vileplume de Erika | C10: 16.666667 | D10: 8 | E10: 5 | F10: =SUM(C10:E10) -> 29.666667
B11: Jynx de Sabrina | C11: 13 | D11: 7 | E11: 9.5 | F11: =SUM(C11:E11) -> 29.5 | G11: =SUM(F11:F12) -> 63.5
B12: Alakazam de Sabrina | C12: 13 | D12: 9 | E12: 12 | F12: =SUM(C12:E12) -> 34
B13: Arbok de Koga | C13: 13.866667 | D13: 8 | E13: 8 | F13: =SUM(C13:E13) -> 29.866667 | G13: =SUM(F13:F14) -> 56.533333
B14: Venomoth de Koga | C14: 13.666667 | D14: 4 | E14: 9 | F14: =SUM(C14:E14) -> 26.666667
B15: Arcanine de Blaine | C15: 16.666667 | D15: 8 | E15: 9.5 | F15: =SUM(C15:E15) -> 34.166667 | G15: =SUM(F15:F16) -> 66.266667
B16: Magmar de Blaine | C16: 13.8 | D16: 9 | E16: 9.3 | F16: =SUM(C16:E16) -> 32.1
B17: Rhydon de Giovanni | C17: 18 | D17: 8 | E17: 4 | F17: 30 | G17: =SUM(F17:F18) -> 67.666667
B18: Kangaskhan de Giovanni | C18: 17.666667 | D18: 11 | E18: 9 | F18: =SUM(C18:E18) -> 37.666667
B21: PKMN | C21: HP | D21: ATT | E21: SPD | F21: ALL | G21: SUM
B22: Gengar | C22: 13 | D22: 9 | E22: 11 | F22: =SUM(C22:E22) -> 33 | G22: =SUM(F22:F24) -> 94.866667
B23: Hypno | C23: 18 | D23: 8 | E23: 6.7 | F23: =SUM(C23:E23) -> 32.7
B24: Marowak | C24: 16.666667 | D24: 8 | E24: 4.5 | F24: =SUM(C24:E24) -> 29.166667
B25: Machamp | C25: 17 | D25: 8 | E25: 5.5 | F25: =SUM(C25:E25) -> 30.5 | G25: =SUM(F25:F27) -> 90.933333
B26: Hitmonlee | C26: 14.2 | D26: 7 | E26: 8.7 | F26: =SUM(C26:E26) -> 29.9
B27: Hitmonchan | C27: 15.933333 | D27: 7 | E27: 7.6 | F27: =SUM(C27:E27) -> 30.533333
B28: Charizard | C28: 16.066667 | D28: 8 | E28: 10 | F28: =SUM(C28:E28) -> 34.066667 | G28: =SUM(F28:F30) -> 106.8
B29: Aerodactyl | C29: 14.666667 | D29: 8 | E29: 13 | F29: =SUM(C29:E29) -> 35.666667
B30: Dragonite | C30: 19.066667 | D30: 10 | E30: 8 | F30: =SUM(C30:E30) -> 37.066667
B31: Cloyster | C31: 18.333333 | D31: 7 | E31: 7 | F31: =SUM(C31:E31) -> 32.333333 | G31: =SUM(F31:F33) -> 96.5
B32: Exeggutor | C32: 16.333333 | D32: 8 | E32: 5.5 | F32: =SUM(C32:E32) -> 29.833333
B33: Lapras | C33: 20.333333 | D33: 8 | E33: 6 | F33: =SUM(C33:E33) -> 34.333333
F35: =SUM(F22:F33)/3 -> 129.7

Sheet Pokemon Data
A1: Real Games
A2: Basic | M2: Evolution | P2: Original stats
A3: # | B3: Name | C3: Cod | D3: Male | E3: Female | F3: Egg | G3: Generation | H3: Type 1 | I3: Type 2 | J3: TAG | K3: Rarity | L3: Family | M3: Preevolution | N3: Stage | O3: Method | P3: Total | Q3: HP | R3: Attack | S3: Defense | T3: Sp. Atk | U3: Sp. Def
A4: 1 | B4: Bulbasaur | C4: 0001A0 | D4: 0.85 | E4: 0.15 | F4: Grass | G4: Kanto | H4: Grass | I4: Poison | J4: Starter | K4: Rare | L4: 0001A0 | M4: - | N4: Basic | O4: - | P4: 318 | Q4: 45 | R4: 49 | S4: 49 | T4: 65 | U4: 65 | V4: 45
A5: 2 | B5: Ivysaur | C5: 0002A0 | D5: 0.85 | E5: 0.15 | F5: Grass | G5: Kanto | H5: Grass | I5: Poison | J5: Starter | K5: Rare | L5: 0001A0 | M5: 0001A0 | N5: Middle | O5: Experience | P5: 405 | Q5: 60 | R5: 62 | S5: 63 | T5: 80 | U5: 80 | V5: 60
A6: 3 | B6: Venusaur | C6: 0003A0 | D6: 0.85 | E6: 0.15 | F6: Grass | G6: Kanto | H6: Grass | I6: Poison | J6: Starter | K6: Rare | L6: 0001A0 | M6: 0002A0 | N6: Final | O6: Experience | P6: 525 | Q6: 80 | R6: 82 | S6: 83 | T6: 100 | U6: 100 | V6: 80
A7: 3 | B7: Venusaur (Mega Venusaur) | C7: 0003M0 | D7: 0.85 | E7: 0.15 | F7: Grass | G7: Kanto | H7: Grass | I7: Poison | J7: Mega | K7: Non available | L7: 0001A0 | M7: 0003A0 | N7: Mega | O7: Megastone | P7: 625 | Q7: 80 | R7: 100 | S7: 123 | T7: 122 | U7: 120 | V7: 80
A8: 4 | B8: Charmander | C8: 0004A0 | D8: 0.85 | E8: 0.15 | F8: Dragon | G8: Kanto | H8: Fire | I8: - | J8: Starter | K8: Rare | L8: 0004A0 | M8: - | N8: Basic | O8: - | P8: 309 | Q8: 39 | R8: 52 | S8: 43 | T8: 60 | U8: 50 | V8: 65
A9: 5 | B9: Charmeleon | C9: 0005A0 | D9: 0.85 | E9: 0.15 | F9: Dragon | G9: Kanto | H9: Fire | I9: - | J9: Starter | K9: Rare | L9: 0004A0 | M9: 0004A0 | N9: Middle | O9: Experience | P9: 405 | Q9: 58 | R9: 64 | S9: 58 | T9: 80 | U9: 65 | V9: 80
A10: 6 | B10: Charizard | C10: 0006A0 | D10: 0.85 | E10: 0.15 | F10: Dragon | G10: Kanto | H10: Fire | I10: Flying | J10: Starter | K10: Rare | L10: 0004A0 | M10: 0005A0 | N10: Final | O10: Experience | P10: 534 | Q10: 78 | R10: 84 | S10: 78 | T10: 109 | U10: 85 | V10: 100
A11: 6 | B11: Charizard (Mega Charizard X) | C11: 0006M0 | D11: 0.85 | E11: 0.15 | F11: Dragon | G11: Kanto | H11: Fire | I11: Dragon | J11: Mega | K11: Non available | L11: 0004A0 | M11: 0006A0 | N11: Mega | O11: Megastone | P11: 634 | Q11: 78 | R11: 130 | S11: 111 | T11: 130 | U11: 85 | V11: 100
A12: 6 | B12: Charizard (Mega Charizard Y) | C12: 0006N0 | D12: 0.85 | E12: 0.15 | F12: Dragon | G12: Kanto | H12: Fire | I12: Flying | J12: Mega | K12: Non available | L12: 0004A0 | M12: 0006A0 | N12: Mega | O12: Megastone | P12: 634 | Q12: 78 | R12: 104 | S12: 78 | T12: 159 | U12: 115 | V12: 100
A13: 7 | B13: Squirtle | C13: 0007A0 | D13: 0.85 | E13: 0.15 | F13: Water 1 | G13: Kanto | H13: Water | I13: - | J13: Starter | K13: Rare | L13: 0007A0 | M13: - | N13: Basic | O13: - | P13: 314 | Q13: 44 | R13: 48 | S13: 65 | T13: 50 | U13: 64 | V13: 43
A14: 8 | B14: Wartortle | C14: 0008A0 | D14: 0.85 | E14: 0.15 | F14: Water 1 | G14: Kanto | H14: Water | I14: - | J14: Starter | K14: Rare | L14: 0007A0 | M14: 0007A0 | N14: Middle | O14: Experience | P14: 405 | Q14: 59 | R14: 63 | S14: 80 | T14: 65 | U14: 80 | V14: 58
A15: 9 | B15: Blastoise | C15: 0009A0 | D15: 0.85 | E15: 0.15 | F15: Water 1 | G15: Kanto | H15: Water | I15: - | J15: Starter | K15: Rare | L15: 0007A0 | M15: 0008A0 | N15: Final | O15: Experience | P15: 530 | Q15: 79 | R15: 83 | S15: 100 | T15: 85 | U15: 105 | V15: 78
... A114: 80 | B114: Slowbro (Mega Slowbro) | C114: 0080M0 | D114: 0.5 | E114: 0.5 | F114: Water 1 | G114: Kanto | H114: Water | I114: Psychic | J114: Mega | K114: Non available | L114: 0079A0 | M114: 0080A0 | N114: Mega | O114: Megastone | P114: 590 | Q114: 95 | R114: 75 | S114: 180 | T114: 130 | U114: 80 | V114: 30
A115: 81 | B115: Magnemite | C115: 0081A0 | D115: - | E115: - | F115: Mineral | G115: Kanto | H115: Electric | I115: Steel | J115: Basic | K115: Common | L115: 0081A0 | M115: - | N115: Basic | O115: - | P115: 325 | Q115: 25 | R115: 35 | S115: 70 | T115: 95 | U115: 55 | V115: 45
A116: 82 | B116: Magneton | C116: 0082A0 | D116: - | E116: - | F116: Mineral | G116: Kanto | H116: Electric | I116: Steel | J116: Basic | K116: Common | L116: 0081A0 | M116: 0081A0 | N116: Middle | O116: Experience | P116: 465 | Q116: 50 | R116: 60 | S116: 95 | T116: 120 | U116: 70 | V116: 70
A117: 83 | B117: Farfetch'd | C117: 0083A0 | D117: 0.5 | E117: 0.5 | F117: Flying | G117: Kanto | H117: Flying | I117: Normal | J117: Basic | K117: Uncommon | L117: 0083A0 | M117: - | N117: Final | O117: - | P117: 377 | Q117: 52 | R117: 90 | S117: 55 | T117: 58 | U117: 62 | V117: 60
A118: 83 | B118: Farfetch'd (Galarian Form) | C118: 0083G0 | D118: 0.5 | E118: 0.5 | F118: Flying | G118: Galar | H118: Fighting | I118: - | J118: Basic | K118: Uncommon | L118: 0083A0 | M118: - | N118: Basic | O118: - | P118: 377 | Q118: 52 | R118: 95 | S118: 55 | T118: 58 | U118: 62 | V118: 55
A119: 84 | B119: Doduo | C119: 0084A0 | D119: 0.5 | E119: 0.5 | F119: Flying | G119: Kanto | H119: Flying | I119: Normal | J119: Basic | K119: Uncommon | L119: 0084A0 | M119: - | N119: Basic | O119: - | P119: 310 | Q119: 35 | R119: 85 | S119: 45 | T119: 35 | U119: 35 | V119: 75
A120: 85 | B120: Dodrio | C120: 0085A0 | D120: 0.5 | E120: 0.5 | F120: Flying | G120: Kanto | H120: Flying | I120: Normal | J120: Basic | K120: Uncommon | L120: 0084A0 | M120: 0084A0 | N120: Final | O120: Experience | P120: 470 | Q120: 60 | R120: 110 | S120: 70 | T120: 60 | U120: 60 | V120: 110
A121: 86 | B121: Seel | C121: 0086A0 | D121: 0.5 | E121: 0.5 | F121: Water 3 | G121: Kanto | H121: Water | I121: - | J121: Basic | K121: Uncommon | L121: 0086A0 | M121: - | N121: Basic | O121: - | P121: 325 | Q121: 65 | R121: 45 | S121: 55 | T121: 45 | U121: 70 | V121: 45
A122: 87 | B122: Dewgong | C122: 0087A0 | D122: 0.5 | E122: 0.5 | F122: Water 3 | G122: Kanto | H122: Water | I122: Ice | J122: Basic | K122: Uncommon | L122: 0086A0 | M122: 0086A0 | N122: Final | O122: Experience | P122: 475 | Q122: 90 | R122: 70 | S122: 80 | T122: 70 | U122: 95 | V122: 70
A123: 88 | B123: Grimer | C123: 0088A0 | D123: 0.5 | E123: 0.5 | F123: Amorphous | G123: Kanto | H123: Poison | I123: - | J123: Basic | K123: Uncommon | L123: 0088A0 | M123: - | N123: Basic | O123: - | P123: 325 | Q123: 80 | R123: 80 | S123: 50 | T123: 40 | U123: 50 | V123: 25
A124: 88 | B124: Grimer (Alolan Form) | C124: 0088L0 | D124: 0.5 | E124: 0.5 | F124: Amorphous | G124: Alola | H124: Poison | I124: Dark | J124: Basic | K124: Uncommon | L124: 0088A0 | M124: - | N124: Basic | O124: - | P124: 325 | Q124: 80 | R124: 80 | S124: 50 | T124: 40 | U124: 50 | V124: 25
A125: 89 | B125: Muk | C125: 0089A0 | D125: 0.5 | E125: 0.5 | F125: Amorphous | G125: Kanto | H125: Poison | I125: - | J125: Basic | K125: Uncommon | L125: 0088A0 | M125: 0088A0 | N125: Final | O125: Experience | P125: 500 | Q125: 105 | R125: 105 | S125: 75 | T125: 65 | U125: 100 | V125: 50
A126: 89 | B126: Muk (Alolan Form) | C126: 0089L0 | D126: 0.5 | E126: 0.5 | F126: Amorphous | G126: Alola | H126: Poison | I126: Dark | J126: Basic | K126: Uncommon | L126: 0088A0 | M126: 0088L0 | N126: Final | O126: Experience | P126: 500 | Q126: 105 | R126: 105 | S126: 75 | T126: 65 | U126: 100 | V126: 50
A127: 90 | B127: Shellder | C127: 0090A0 | D127: 0.5 | E127: 0.5 | F127: Water 3 | G127: Kanto | H127: Water | I127: - | J127: Basic | K127: Uncommon | L127: 0090A0 | M127: - | N127: Basic | O127: - | P127: 305 | Q127: 30 | R127: 65 | S127: 100 | T127: 45 | U127: 25 | V127: 40
A128: 91 | B128: Cloyster | C128: 0091A0 | D128: 0.5 | E128: 0.5 | F128: Water 2 | G128: Kanto | H128: Water | I128: Ice | J128: Basic | K128: Uncommon | L128: 0090A0 | M128: 0090A0 | N128: Final | O128: Stone | P128: 525 | Q128: 50 | R128: 95 | S128: 180 | T128: 85 | U128: 45 | V128: 70
... A137: 99 | B137: Kingler | C137: 0099A0 | D137: 0.5 | E137: 0.5 | F137: Water 3 | G137: Kanto | H137: Water | I137: - | J137: Basic | K137: Common | L137: 0098A0 | M137: 0098A0 | N137: Final | O137: Experience | P137: 475 | Q137: 55 | R137: 130 | S137: 115 | T137: 50 | U137: 50 | V137: 75
A138: 100 | B138: Voltorb | C138: 0100A0 | D138: - | E138: - | F138: Mineral | G138: Kanto | H138: Electric | I138: - | J138: Basic | K138: Common | L138: 0100A0 | M138: - | N138: Basic | O138: - | P138: 330 | Q138: 40 | R138: 30 | S138: 50 | T138: 55 | U138: 55 | V138: 100
A139: 100 | B139: Voltorb (Hisuian Voltorb) | C139: 0100H0 | D139: 0.5 | E139: 0.5 | F139: Mineral | G139: Hisui | H139: Electric | I139: Grass | J139: Basic | K139: Common | L139: 0100A0 | M139: - | N139: Basic | O139: - | P139: 330 | Q139: 40 | R139: 30 | S139: 50 | T139: 55 | U139: 55 | V139: 100
A140: 101 | B140: Electrode | C140: 0101A0 | D140: - | E140: - | F140: Mineral | G140: Kanto | H140: Electric | I140: - | J140: Basic | K140: Common | L140: 0100A0 | M140: 0100A0 | N140: Final | O140: Experience | P140: 490 | Q140: 60 | R140: 50 | S140: 70 | T140: 80 | U140: 80 | V140: 150
A141: 101 | B141: Electrode (Hisuian Electrode) | C141: 0101H0 | D141: 0.5 | E141: 0.5 | F141: Mineral | G141: Hisui | H141: Electric | I141: Gr | J141: Basic | K141: Common | L141: 0100A0 | M141: 0100H0 | N141: Final | O141: Experience | P141: 490 | Q141: 60 | R141: 50 | S141: 70 | T141: 80 | U141: 80 | V141: 150
A142: 102 | B142: Exeggcute | C142: 0102A0 | D142: 0.5 | E142: 0.5 | F142: Grass | G142: Kanto | H142: Grass | I142: Psychic | J142: Basic | K142: Uncommon | L142: 0102A0 | M142: - | N142: Basic | O142: - | P142: 325 | Q142: 60 | R142: 40 | S142: 80 | T142: 60 | U142: 45 | V142: 40
A143: 103 | B143: Exeggutor | C143: 0103A0 | D143: 0.5 | E143: 0.5 | F143: Grass | G143: Kanto | H143: Grass | I143: Psychic | J143: Basic | K143: Uncommon | L143: 0102A0 | M143: 0102A0 | N143: Final | O143: Stone | P143: 530 | Q143: 95 | R143: 95 | S143: 85 | T143: 125 | U143: 75 | V143: 55
A144: 103 | B144: Exeggutor (Alolan Form) | C144: 0103L0 | D144: 0.5 | E144: 0.5 | F144: Grass | G144: Alola | H144: Grass | I144: Dragon | J144: Basic | K144: Uncommon | L144: 0102A0 | M144: 0102A0 | N144: Final | O144: Stone | P144: 530 | Q144: 95 | R144: 105 | S144: 85 | T144: 125 | U144: 75 | V144: 45
A145: 104 | B145: Cubone | C145: 0104A0 | D145: 0.5 | E145: 0.5 | F145: Monster | G145: Kanto | H145: Ground | I145: - | J145: Basic | K145: Uncommon | L145: 0104A0 | M145: - | N145: Basic | O145: - | P145: 320 | Q145: 50 | R145: 50 | S145: 95 | T145: 40 | U145: 50 | V145: 35
A146: 105 | B146: Marowak | C146: 0105A0 | D146: 0.5 | E146: 0.5 | F146: Monster | G146: Kanto | H146: Ground | I146: - | J146: Basic | K146: Uncommon | L146: 0104A0 | M146: 0104A0 | N146: Final | O146: Experience | P146: 425 | Q146: 60 | R146: 80 | S146: 110 | T146: 50 | U146: 80 | V146: 45
A147: 105 | B147: Marowak (Alolan Form) | C147: 0105L0 | D147: 0.5 | E147: 0.5 | F147: Monster | G147: Alola | H147: Fire | I147: Ghost | J147: Basic | K147: Uncommon | L147: 0104A0 | M147: 0104A0 | N147: Final | O147: Experience | P147: 425 | Q147: 60 | R147: 80 | S147: 110 | T147: 50 | U147: 80 | V147: 45
A148: 106 | B148: Hitmonlee | C148: 0106A0 | D148: 1 | E148: 0 | F148: Human-Like | G148: Kanto | H148: Fighting | I148: - | J148: Basic | K148: Rare | L148: 0236A0 | M148: 0236A0 | N148: Final | O148: Experience | P148: 455 | Q148: 50 | R148: 120 | S148: 53 | T148: 35 | U148: 110 | V148: 87
A149: 107 | B149: Hitmonchan | C149: 0107A0 | D149: 1 | E149: 0 | F149: Human-Like | G149: Kanto | H149: Fighting | I149: - | J149: Basic | K149: Rare | L149: 0236A0 | M149: 0236A0 | N149: Final | O149: Experience | P149: 455 | Q149: 50 | R149: 105 | S149: 79 | T149: 35 | U149: 110 | V149: 76
A150: 108 | B150: Lickitung | C150: 0108A0 | D150: 0.5 | E150: 0.5 | F150: Monster | G150: Kanto | H150: Normal | I150: - | J150: Basic | K150: Rare | L150: 0108A0 | M150: - | N150: Basic | O150: - | P150: 385 | Q150: 90 | R150: 55 | S150: 75 | T150: 60 | U150: 75 | V150: 30
A151: 109 | B151: Koffing | C151: 0109A0 | D151: 0.5 | E151: 0.5 | F151: Amorphous | G151: Kanto | H151: Poison | I151: - | J151: Basic | K151: Uncommon | L151: 0109A0 | M151: - | N151: Basic | O151: - | P151: 340 | Q151: 40 | R151: 65 | S151: 95 | T151: 60 | U151: 45 | V151: 35
A152: 110 | B152: Weezing | C152: 0110A0 | D152: 0.5 | E152: 0.5 | F152: Amorphous | G152: Kanto | H152: Poison | I152: - | J152: Basic | K152: Uncommon | L152: 0109A0 | M152: 0109A0 | N152: Final | O152: Experience | P152: 490 | Q152: 65 | R152: 90 | S152: 120 | T152: 85 | U152: 70 | V152: 60
... A163: 119 | B163: Seaking | C163: 0119A0 | D163: 0.5 | E163: 0.5 | F163: Water 2 | G163: Kanto | H163: Water | I163: - | J163: Basic | K163: Uncommon | L163: 0118A0 | M163: 0118A0 | N163: Final | O163: Experience | P163: 450 | Q163: 80 | R163: 92 | S163: 65 | T163: 65 | U163: 80 | V163: 68
A164: 120 | B164: Staryu | C164: 0120A0 | D164: - | E164: - | F164: Water 3 | G164: Kanto | H164: Water | I164: - | J164: Basic | K164: Uncommon | L164: 0120A0 | M164: - | N164: Basic | O164: - | P164: 340 | Q164: 30 | R164: 45 | S164: 55 | T164: 70 | U164: 55 | V164: 85
A165: 121 | B165: Starmie | C165: 0121A0 | D165: - | E165: - | F165: Water 3 | G165: Kanto | H165: Water | I165: Psychic | J165: Basic | K165: Uncommon | L165: 0120A0 | M165: 0120A0 | N165: Final | O165: Stone | P165: 520 | Q165: 60 | R165: 75 | S165: 85 | T165: 100 | U165: 85 | V165: 115
A166: 122 | B166: Mr. Mime | C166: 0122A0 | D166: 0.5 | E166: 0.5 | F166: Human-Like | G166: Kanto | H166: Psychic | I166: Fairy | J166: Basic | K166: Rare | L166: 0439A0 | M166: 0439A0 | N166: Final | O166: Experience | P166: 460 | Q166: 40 | R166: 45 | S166: 65 | T166: 100 | U166: 120 | V166: 90
A167: 122 | B167: Mr. Mime (Galarian Form) | C167: 0122G0 | D167: 0.5 | E167: 0.5 | F167: Human-Like | G167: Galar | H167: Psychic | I167: Fairy | J167: Basic | K167: Rare | L167: 0439A0 | M167: 0439A0 | N167: Middle | O167: Experience | P167: 460 | Q167: 50 | R167: 65 | S167: 65 | T167: 90 | U167: 90 | V167: 100
A168: 123 | B168: Scyther | C168: 0123A0 | D168: 0.5 | E168: 0.5 | F168: Bug | G168: Kanto | H168: Bug | I168: Flying | J168: Basic | K168: Rare | L168: 0123A0 | M168: - | N168: Basic | O168: - | P168: 500 | Q168: 70 | R168: 110 | S168: 80 | T168: 55 | U168: 80 | V168: 105
A169: 124 | B169: Jynx | C169: 0124A0 | D169: 0 | E169: 1 | F169: Human-Like | G169: Kanto | H169: Ice | I169: Psychic | J169: Basic | K169: Rare | L169: 0238A0 | M169: 0238A0 | N169: Final | O169: Experience | P169: 455 | Q169: 65 | R169: 50 | S169: 35 | T169: 115 | U169: 95 | V169: 95
A170: 125 | B170: Electabuzz | C170: 0125A0 | D170: 0.75 | E170: 0.25 | F170: Human-Like | G170: Kanto | H170: Electric | I170: - | J170: Basic | K170: Rare | L170: 0239A0 | M170: 0239A0 | N170: Middle | O170: Experience | P170: 490 | Q170: 65 | R170: 83 | S170: 57 | T170: 95 | U170: 85 | V170: 105
A171: 126 | B171: Magmar | C171: 0126A0 | D171: 0.75 | E171: 0.25 | F171: Human-Like | G171: Kanto | H171: Fire | I171: - | J171: Basic | K171: Rare | L171: 0240A0 | M171: 0240A0 | N171: Middle | O171: Experience | P171: 495 | Q171: 65 | R171: 95 | S171: 57 | T171: 100 | U171: 85 | V171: 93
A172: 127 | B172: Pinsir | C172: 0127A0 | D172: 0.5 | E172: 0.5 | F172: Bug | G172: Kanto | H172: Bug | I172: - | J172: Basic | K172: Rare | L172: 0127A0 | M172: - | N172: Final | O172: - | P172: 500 | Q172: 65 | R172: 125 | S172: 100 | T172: 55 | U172: 70 | V172: 85
A173: 127 | B173: Pinsir (Mega Pinsir) | C173: 0127M0 | D173: 0.5 | E173: 0.5 | F173: Bug | G173: Kanto | H173: Bug | I173: Flying | J173: Mega | K173: Non available | L173: 0127A0 | M173: 0127A0 | N173: Mega | O173: Megastone | P173: 600 | Q173: 65 | R173: 155 | S173: 120 | T173: 65 | U173: 90 | V173: 105
A174: 128 | B174: Tauros | C174: 0128A0 | D174: 1 | E174: 0 | F174: Field | G174: Kanto | H174: Normal | I174: - | J174: Basic | K174: Rare | L174: 0128A0 | M174: - | N174: Final | O174: - | P174: 490 | Q174: 75 | R174: 100 | S174: 95 | T174: 40 | U174: 70 | V174: 110
A175: 128 | B175: Tauros (Combat Breed) | C175: 0128P0 | D175: 1 | E175: 0 | F175: Field | G175: Paldea | H175: Fighting | I175: - | J175: Basic | K175: Rare | L175: 0128A0 | M175: - | N175: Final | O175: - | P175: 490 | Q175: 75 | R175: 110 | S175: 105 | T175: 30 | U175: 70 | V175: 100
A176: 128 | B176: Tauros (Aqua Breed) | C176: 0128P1 | D176: 1 | E176: 0 | F176: Field | G176: Paldea | H176: Fighting | I176: Water | J176: Basic | K176: Rare | L176: 0128A0 | M176: - | N176: Final | O176: - | P176: 490 | Q176: 75 | R176: 110 | S176: 105 | T176: 30 | U176: 70 | V176: 100
A177: 128 | B177: Tauros (Blaze Breed) | C177: 0128P2 | D177: 1 | E177: 0 | F177: Field | G177: Paldea | H177: Fighting | I177: Fire | J177: Basic | K177: Rare | L177: 0128A0 | M177: - | N177: Final | O177: - | P177: 490 | Q177: 75 | R177: 110 | S177: 105 | T177: 30 | U177: 70 | V177: 100
... A181: 131 | B181: Lapras | C181: 0131A0 | D181: 0.5 | E181: 0.5 | F181: Water 3 | G181: Kanto | H181: Water | I181: Ice | J181: Basic | K181: Rare | L181: 0131A0 | M181: - | N181: Final | O181: - | P181: 535 | Q181: 130 | R181: 85 | S181: 80 | T181: 85 | U181: 95 | V181: 60
A182: 132 | B182: Ditto | C182: 0132A0 | D182: - | E182: - | F182: Ditto | G182: Kanto | H182: Normal | I182: - | J182: Basic | K182: Rare | L182: 0132A0 | M182: - | N182: Final | O182: - | P182: 288 | Q182: 48 | R182: 48 | S182: 48 | T182: 48 | U182: 48 | V182: 48
A183: 133 | B183: Eevee | C183: 0133A0 | D183: 0.85 | E183: 0.15 | F183: Field | G183: Kanto | H183: Normal | I183: - | J183: Basic | K183: Uncommon | L183: 0133A0 | M183: - | N183: Basic | O183: - | P183: 325 | Q183: 55 | R183: 55 | S183: 50 | T183: 45 | U183: 65 | V183: 55
A184: 133 | B184: Eevee (Partner Eevee) | C184: 0133B0 | D184: 0.85 | E184: 0.15 | F184: Field | G184: Kanto | H184: Normal | I184: - | J184: Special | K184: Uncommon | L184: 0133A0 | M184: 0133A0 | N184: Special | O184: Gift | P184: 435 | Q184: 65 | R184: 75 | S184: 70 | T184: 65 | U184: 85 | V184: 75
A185: 134 | B185: Vaporeon | C185: 0134A0 | D185: 0.85 | E185: 0.15 | F185: Field | G185: Kanto | H185: Water | I185: - | J185: Basic | K185: Uncommon | L185: 0133A0 | M185: 0133A0 | N185: Final | O185: Stone | P185: 525 | Q185: 130 | R185: 65 | S185: 60 | T185: 110 | U185: 95 | V185: 65
A186: 135 | B186: Jolteon | C186: 0135A0 | D186: 0.85 | E186: 0.15 | F186: Field | G186: Kanto | H186: Electric | I186: - | J186: Basic | K186: Uncommon | L186: 0133A0 | M186: 0133A0 | N186: Final | O186: Stone | P186: 525 | Q186: 65 | R186: 65 | S186: 60 | T186: 110 | U186: 95 | V186: 130
A187: 136 | B187: Flareon | C187: 0136A0 | D187: 0.85 | E187: 0.15 | F187: Field | G187: Kanto | H187: Fire | I187: - | J187: Basic | K187: Uncommon | L187: 0133A0 | M187: 0133A0 | N187: Final | O187: Stone | P187: 525 | Q187: 65 | R187: 130 | S187: 60 | T187: 95 | U187: 110 | V187: 65
A188: 137 | B188: Porygon | C188: 0137A0 | D188: - | E188: - | F188: Mineral | G188: Kanto | H188: Normal | I188: - | J188: Basic | K188: Rare | L188: 0137A0 | M188: - | N188: Basic | O188: - | P188: 395 | Q188: 65 | R188: 60 | S188: 70 | T188: 85 | U188: 75 | V188: 40
A189: 138 | B189: Omanyte | C189: 0138A0 | D189: 0.85 | E189: 0.15 | F189: Water 2 | G189: Kanto | H189: Water | I189: Rock | J189: Basic | K189: Rare | L189: 0138A0 | M189: - | N189: Basic | O189: - | P189: 355 | Q189: 35 | R189: 40 | S189: 100 | T189: 90 | U189: 55 | V189: 35
A190: 139 | B190: Omastar | C190: 0139A0 | D190: 0.85 | E190: 0.15 | F190: Water 2 | G190: Kanto | H190: Water | I190: Rock | J190: Basic | K190: Rare | L190: 0138A0 | M190: 0138A0 | N190: Final | O190: Experience | P190: 495 | Q190: 70 | R190: 60 | S190: 125 | T190: 115 | U190: 70 | V190: 55
A191: 140 | B191: Kabuto | C191: 0140A0 | D191: 0.85 | E191: 0.15 | F191: Water 2 | G191: Kanto | H191: Rock | I191: Water | J191: Basic | K191: Rare | L191: 0140A0 | M191: - | N191: Basic | O191: - | P191: 355 | Q191: 30 | R191: 80 | S191: 90 | T191: 55 | U191: 45 | V191: 55
A192: 141 | B192: Kabutops | C192: 0141A0 | D192: 0.85 | E192: 0.15 | F192: Water 2 | G192: Kanto | H192: Rock | I192: Water | J192: Basic | K192: Rare | L192: 0140A0 | M192: 0140A0 | N192: Final | O192: Experience | P192: 495 | Q192: 60 | R192: 115 | S192: 105 | T192: 65 | U192: 70 | V192: 80
A193: 142 | B193: Aerodactyl | C193: 0142A0 | D193: 0.85 | E193: 0.15 | F193: Flying | G193: Kanto | H193: Rock | I193: Flying | J193: Basic | K193: Rare | L193: 0142A0 | M193: - | N193: Final | O193: - | P193: 515 | Q193: 80 | R193: 105 | S193: 65 | T193: 60 | U193: 75 | V193: 130
A194: 142 | B194: Aerodactyl (Mega Aerodactyl) | C194: 0142M0 | D194: 0.85 | E194: 0.15 | F194: Flying | G194: Kanto | H194: Rock | I194: Flying | J194: Mega | K194: Non available | L194: 0142A0 | M194: 0142A0 | N194: Mega | O194: Megastone | P194: 615 | Q194: 80 | R194: 135 | S194: 85 | T194: 70 | U194: 95 | V194: 150
A195: 143 | B195: Snorlax | C195: 0143A0 | D195: 0.85 | E195: 0.15 | F195: Monster | G195: Kanto | H195: Normal | I195: - | J195: Basic | K195: Rare | L195: 0446A0 | M195: 0446A0 | N195: Final | O195: Experience | P195: 540 | Q195: 160 | R195: 110 | S195: 65 | T195: 65 | U195: 110 | V195: 30
A196: 144 | B196: Articuno | C196: 0144A0 | D196: - | E196: - | F196: Undiscovered | G196: Kanto | H196: Ice | I196: Flying | J196: Legendary | K196: Legendary | L196: 0144A0 | M196: - | N196: Final | O196: - | P196: 580 | Q196: 90 | R196: 85 | S196: 100 | T196: 95 | U196: 125 | V196: 85
A197: 144 | B197: Articuno (Galarian Form) | C197: 0144G0 | D197: - | E197: - | F197: Undiscovered | G197: Galar | H197: Psychic | I197: Flying | J197: Legendary | K197: Legendary | L197: 0144A0 | M197: - | N197: Final | O197: - | P197: 580 | Q197: 90 | R197: 85 | S197: 85 | T197: 125 | U197: 100 | V197: 95
A198: 145 | B198: Zapdos | C198: 0145A0 | D198: - | E198: - | F198: Undiscovered | G198: Kanto | H198: Electric | I198: Flying | J198: Legendary | K198: Legendary | L198: 0145A0 | M198: - | N198: Final | O198: - | P198: 580 | Q198: 90 | R198: 90 | S198: 85 | T198: 125 | U198: 90 | V198: 100
A199: 145 | B199: Zapdos (Galarian Form) | C199: 0145G0 | D199: - | E199: - | F199: Undiscovered | G199: Galar | H199: Fighting | I199: Flying | J199: Legendary | K199: Legendary | L199: 0145A0 | M199: - | N199: Final | O199: - | P199: 580 | Q199: 90 | R199: 125 | S199: 90 | T199: 85 | U199: 90 | V199: 100
A200: 146 | B200: Moltres | C200: 0146A0 | D200: - | E200: - | F200: Undiscovered | G200: Kanto | H200: Fire | I200: Flying | J200: Legendary | K200: Legendary | L200: 0146A0 | M200: - | N200: Final | O200: - | P200: 580 | Q200: 90 | R200: 100 | S200: 90 | T200: 125 | U200: 85 | V200: 90
A201: 146 | B201: Moltres (Galarian Form) | C201: 0146G0 | D201: - | E201: - | F201: Undiscovered | G201: Galar | H201: Dark | I201: Flying | J201: Legendary | K201: Legendary | L201: 0146A0 | M201: - | N201: Final | O201: - | P201: 580 | Q201: 90 | R201: 85 | S201: 90 | T201: 100 | U201: 125 | V201: 90
A202: 147 | B202: Dratini | C202: 0147A0 | D202: 0.5 | E202: 0.5 | F202: Dragon | G202: Kanto | H202: Dragon | I202: - | J202: Basic | K202: Rare | L202: 0147A0 | M202: - | N202: Basic | O202: - | P202: 300 | Q202: 41 | R202: 64 | S202: 45 | T202: 50 | U202: 50 | V202: 50
A203: 148 | B203: Dragonair | C203: 0148A0 | D203: 0.5 | E203: 0.5 | F203: Dragon | G203: Kanto | H203: Dragon | I203: - | J203: Basic | K203: Rare | L203: 0147A0 | M203: 0147A0 | N203: Middle | O203: Experience | P203: 420 | Q203: 61 | R203: 84 | S203: 65 | T203: 70 | U203: 70 | V203: 70
A204: 149 | B204: Dragonite | C204: 0149A0 | D204: 0.5 | E204: 0.5 | F204: Dragon | G204: Kanto | H204: Dragon | I204: Flying | J204: Basic | K204: Rare | L204: 0147A0 | M204: 0148A0 | N204: Final | O204: Experience | P204: 600 | Q204: 91 | R204: 134 | S204: 95 | T204: 100 | U204: 100 | V204: 80
A205: 150 | B205: Mewtwo | C205: 0150A0 | D205: - | E205: - | F205: Undiscovered | G205: Kanto | H205: Psychic | I205: - | J205: Legendary | K205: Legendary | L205: 0150A0 | M205: - | N205: Final | O205: - | P205: 680 | Q205: 106 | R205: 110 | S205: 90 | T205: 154 | U205: 90 | V205: 130
A206: 150 | B206: Mewtwo (Mega Mewtwo X) | C206: 0150M0 | D206: - | E206: - | F206: Undiscovered | G206: Kanto | H206: Psychic | I206: Fighting | J206: Mega | K206: Non available | L206: 0150A0 | M206: 0150A0 | N206: Mega | O206: Megastone | P206: 780 | Q206: 106 | R206: 190 | S206: 100 | T206: 154 | U206: 100 | V206: 130
A207: 150 | B207: Mewtwo (Mega Mewtwo Y) | C207: 0150N0 | D207: - | E207: - | F207: Undiscovered | G207: Kanto | H207: Psychic | I207: - | J207: Mega | K207: Non available | L207: 0150A0 | M207: 0150A0 | N207: Mega | O207: Megastone | P207: 780 | Q207: 106 | R207: 150 | S207: 70 | T207: 194 | U207: 120 | V207: 140
A208: 151 | B208: Mew | C208: 0151A0 | D208: - | E208: - | F208: Undiscovered | G208: Kanto | H208: Psychic | I208: - | J208: Legendary | K208: Legendary | L208: 0151A0 | M208: - | N208: Final | O208: - | P208: 600 | Q208: 100 | R208: 100 | S208: 100 | T208: 100 | U208: 100 | V208: 100
A209: 152 | B209: Chikorita | C209: 0152A0 | D209: 0.85 | E209: 0.15 | F209: Grass | G209: Johto | H209: Grass | I209: - | J209: Starter | K209: Rare | L209: 0152A0 | M209: - | N209: Basic | O209: - | P209: 318 | Q209: 45 | R209: 49 | S209: 65 | T209: 49 | U209: 65 | V209: 45
A210: 153 | B210: Bayleef | C210: 0153A0 | D210: 0.85 | E210: 0.15 | F210: Grass | G210: Johto | H210: Grass | I210: - | J210: Starter | K210: Rare | L210: 0152A0 | M210: 0152A0 | N210: Middle | O210: Experience | P210: 405 | Q210: 60 | R210: 62 | S210: 80 | T210: 63 | U210: 80 | V210: 60
A211: 154 | B211: Meganium | C211: 0154A0 | D211: 0.85 | E211: 0.15 | F211: Grass | G211: Johto | H211: Grass | I211: - | J211: Starter | K211: Rare | L211: 0152A0 | M211: 0153A0 | N211: Final | O211: Experience | P211: 525 | Q211: 80 | R211: 82 | S211: 100 | T211: 83 | U211: 100 | V211: 80
A212: 155 | B212: Cyndaquil | C212: 0155A0 | D212: 0.85 | E212: 0.15 | F212: Field | G212: Johto | H212: Fire | I212: - | J212: Starter | K212: Rare | L212: 0155A0 | M212: - | N212: Basic | O212: - | P212: 309 | Q212: 39 | R212: 52 | S212: 43 | T212: 60 | U212: 50 | V212: 65
A213: 156 | B213: Quilava | C213: 0156A0 | D213: 0.85 | E213: 0.15 | F213: Field | G213: Johto | H213: Fire | I213: - | J213: Starter | K213: Rare | L213: 0155A0 | M213: 0155A0 | N213: Middle | O213: Experience | P213: 405 | Q213: 58 | R213: 64 | S213: 58 | T213: 80 | U213: 65 | V213: 80
A214: 157 | B214: Typhlosion | C214: 0157A0 | D214: 0.85 | E214: 0.15 | F214: Field | G214: Johto | H214: Fire | I214: - | J214: Starter | K214: Rare | L214: 0155A0 | M214: 0156A0 | N214: Final | O214: Experience | P214: 534 | Q214: 78 | R214: 84 | S214: 78 | T214: 109 | U214: 85 | V214: 100
A215: 157 | B215: Typhlosion (Hisuian Typhlosion) | C215: 0157H0 | D215: 0.85 | E215: 0.15 | F215: Field | G215: Hisui | H215: Fire | I215: Ghost | J215: Starter | K215: Rare | L215: 0155A0 | M215: 0156A0 | N215: Final | O215: Experience | P215: 534 | Q215: 73 | R215: 84 | S215: 78 | T215: 119 | U215: 85 | V215: 95
A216: 158 | B216: Totodile | C216: 0158A0 | D216: 0.85 | E216: 0.15 | F216: Water 1 | G216: Johto | H216: Water | I216: - | J216: Starter | K216: Rare | L216: 0158A0 | M216: - | N216: Basic | O216: - | P216: 314 | Q216: 50 | R216: 65 | S216: 64 | T216: 44 | U216: 48 | V216: 43
A217: 159 | B217: Croconaw | C217: 0159A0 | D217: 0.85 | E217: 0.15 | F217: Water 1 | G217: Johto | H217: Water | I217: - | J217: Starter | K217: Rare | L217: 0158A0 | M217: 0158A0 | N217: Middle | O217: Experience | P217: 405 | Q217: 65 | R217: 80 | S217: 80 | T217: 59 | U217: 63 | V217: 58
A218: 160 | B218: Feraligatr | C218: 0160A0 | D218: 0.85 | E218: 0.15 | F218: Water 1 | G218: Johto | H218: Water | I218: - | J218: Starter | K218: Rare | L218: 0158A0 | M218: 0159A0 | N218: Final | O218: Experience | P218: 530 | Q218: 85 | R218: 105 | S218: 100 | T218: 79 | U218: 83 | V218: 78
A219: 161 | B219: Sentret | C219: 0161A0 | D219: 0.5 | E219: 0.5 | F219: Field | G219: Johto | H219: Normal | I219: - | J219: Basic | K219: Common | L219: 0161A0 | M219: - | N219: Basic | O219: - | P219: 215 | Q219: 35 | R219: 46 | S219: 34 | T219: 35 | U219: 45 | V219: 20
...

Sheet Hatch
A1: Basic | M1: Evolution | AC1: Original stats
A2: # | B2: Name | C2: Cod | D2: Male | E2: Female | F2: Egg | G2: Generation | H2: Type 1 | I2: Type 2 | J2: TAG | K2: Rarity | L2: Family | M2: Preevolution | N2: Stage | O2: Desgaste | P2: Method | Q2: edadMinima | R2: minStyle | S2: minIQ | T2: minKindness | U2: minStrength | V2: itemNecesario | W2: statSosten | X2: minSosten | Y2: percentSosten | Z2: horasSosten | AA2: Acción | AB2: Repetición | AC2: Total | AD2: HP | AE2: Attack | AF2: Defense | AG2: Sp. Atk | AH2: Sp. Def | AI2: Speed
A3: 1 | B3: Bulbasaur | C3: 0001A0 | D3: 0.85 | E3: 0.15 | F3: Grass | G3: Kanto | H3: Grass | I3: Poison | J3: Starter | K3: 4 | L3: 0001A0 | M3: - | N3: Kid | O3: 1.75 | P3: - | AC3: 318 | AD3: 45 | AE3: 49 | AF3: 49 | AG3: 65 | AH3: 65 | AI3: 45
A4: 2 | B4: Ivysaur | C4: 0002A0 | D4: 0.85 | E4: 0.15 | F4: Grass | G4: Kanto | H4: Grass | I4: Poison | J4: Starter | K4: 4 | L4: 0001A0 | M4: 0001A0 | N4: Teen | O4: 1.75 | P4: Experience | AC4: 405 | AD4: 60 | AE4: 62 | AF4: 63 | AG4: 80 | AH4: 80 | AI4: 60
A5: 3 | B5: Venusaur | C5: 0003A0 | D5: 0.85 | E5: 0.15 | F5: Grass | G5: Kanto | H5: Grass | I5: Poison | J5: Starter | K5: 4 | L5: 0001A0 | M5: 0002A0 | N5: Adult | O5: 1.75 | P5: Experience | AC5: 525 | AD5: 80 | AE5: 82 | AF5: 83 | AG5: 100 | AH5: 100 | AI5: 80
A6: 4 | B6: Charmander | C6: 0004A0 | D6: 0.85 | E6: 0.15 | F6: Dragon | G6: Kanto | H6: Fire | I6: - | J6: Starter | K6: 4 | L6: 0004A0 | M6: - | N6: Kid | O6: 1.75 | P6: - | AC6: 309 | AD6: 39 | AE6: 52 | AF6: 43 | AG6: 60 | AH6: 50 | AI6: 65
A7: 5 | B7: Charmeleon | C7: 0005A0 | D7: 0.85 | E7: 0.15 | F7: Dragon | G7: Kanto | H7: Fire | I7: - | J7: Starter | K7: 4 | L7: 0004A0 | M7: 0004A0 | N7: Teen | O7: 1.75 | P7: Experience | AC7: 405 | AD7: 58 | AE7: 64 | AF7: 58 | AG7: 80 | AH7: 65 | AI7: 80
A8: 6 | B8: Charizard | C8: 0006A0 | D8: 0.85 | E8: 0.15 | F8: Dragon | G8: Kanto | H8: Fire | I8: Flying | J8: Starter | K8: 4 | L8: 0004A0 | M8: 0005A0 | N8: Adult | O8: 1.75 | P8: Experience | AC8: 534 | AD8: 78 | AE8: 84 | AF8: 78 | AG8: 109 | AH8: 85 | AI8: 100
A9: 7 | B9: Squirtle | C9: 0007A0 | D9: 0.85 | E9: 0.15 | F9: Water 1 | G9: Kanto | H9: Water | I9: - | J9: Starter | K9: 4 | L9: 0007A0 | M9: - | N9: Kid | O9: 1.75 | P9: - | AC9: 314 | AD9: 44 | AE9: 48 | AF9: 65 | AG9: 50 | AH9: 64 | AI9: 43
A10: 8 | B10: Wartortle | C10: 0008A0 | D10: 0.85 | E10: 0.15 | F10: Water 1 | G10: Kanto | H10: Water | I10: - | J10: Starter | K10: 4 | L10: 0007A0 | M10: 0007A0 | N10: Teen | O10: 1.75 | P10: Experience | AC10: 405 | AD10: 59 | AE10: 63 | AF10: 80 | AG10: 65 | AH10: 80 | AI10: 58
A11: 9 | B11: Blastoise | C11: 0009A0 | D11: 0.85 | E11: 0.15 | F11: Water 1 | G11: Kanto | H11: Water | I11: - | J11: Starter | K11: 4 | L11: 0007A0 | M11: 0008A0 | N11: Adult | O11: 1.75 | P11: Experience | AC11: 530 | AD11: 79 | AE11: 83 | AF11: 100 | AG11: 85 | AH11: 105 | AI11: 78
A12: 10 | B12: Caterpie | C12: 0010A0 | D12: 0.5 | E12: 0.5 | F12: Bug | G12: Kanto | H12: Bug | I12: - | J12: Basic | K12: 1 | L12: 0010A0 | M12: - | N12: Kid | O12: 1 | P12: - | AC12: 195 | AD12: 45 | AE12: 30 | AF12: 35 | AG12: 20 | AH12: 20 | AI12: 45
A13: 11 | B13: Metapod | C13: 0011A0 | D13: 0.5 | E13: 0.5 | F13: Bug | G13: Kanto | H13: Bug | I13: - | J13: Basic | K13: 1 | L13: 0010A0 | M13: 0010A0 | N13: Teen | O13: 1 | P13: Experience | AC13: 205 | AD13: 50 | AE13: 20 | AF13: 55 | AG13: 25 | AH13: 25 | AI13: 30
A14: 12 | B14: Butterfree | C14: 0012A0 | D14: 0.5 | E14: 0.5 | F14: Bug | G14: Kanto | H14: Bug | I14: Flying | J14: Basic | K14: 1 | L14: 0010A0 | M14: 0011A0 | N14: Adult | O14: 1 | P14: Experience | AC14: 395 | AD14: 60 | AE14: 45 | AF14: 50 | AG14: 90 | AH14: 80 | AI14: 70
... A28: 24 | B28: Arbok | C28: 0024A0 | D28: 0.5 | E28: 0.5 | F28: Field | G28: Kanto | H28: Poison | I28: - | J28: Basic | K28: 1 | L28: 0023A0 | M28: 0023A0 | N28: Adult | O28: 1 | P28: Experience | AC28: 448 | AD28: 60 | AE28: 95 | AF28: 69 | AG28: 65 | AH28: 79 | AI28: 80
A29: 25 | B29: Pikachu | C29: 0025A0 | D29: 0.5 | E29: 0.5 | F29: Fairy | G29: Kanto | H29: Electric | I29: - | J29: Basic | K29: 2 | L29: 0172A0 | M29: 0172A0 | N29: Kid | O29: 1.25 | P29: Experience | Q29: 1 | W29: felicidad | Y29: 70 | Z29: 6 | AC29: 320 | AD29: 35 | AE29: 55 | AF29: 40 | AG29: 50 | AH29: 50 | AI29: 90
A30: 26 | B30: Raichu | C30: 0026A0 | D30: 0.5 | E30: 0.5 | F30: Fairy | G30: Kanto | H30: Electric | I30: - | J30: Basic | K30: 2 | L30: 0172A0 | M30: 0025A0 | N30: Adult | O30: 1.25 | P30: Stone | Q30: 2 | V30: piedra_trueno | AC30: 485 | AD30: 60 | AE30: 90 | AF30: 55 | AG30: 90 | AH30: 80 | AI30: 110
A31: 26 | B31: Raichu (Alolan Form) | C31: 0026L0 | D31: 0.5 | E31: 0.5 | F31: Fairy | G31: Alola | H31: Electric | I31: Psychic | J31: Basic | K31: 2 | L31: 0172A0 | M31: 0025A0 | N31: Adult | O31: 1.25 | P31: Stone | Q31: 2 | R31: 80 | AC31: 485 | AD31: 60 | AE31: 85 | AF31: 50 | AG31: 95 | AH31: 85 | AI31: 110
A32: 27 | B32: Sandshrew | C32: 0027A0 | D32: 0.5 | E32: 0.5 | F32: Field | G32: Kanto | H32: Ground | I32: - | J32: Basic | K32: 2 | L32: 0027A0 | M32: - | N32: Kid | O32: 1.25 | P32: - | AC32: 300 | AD32: 50 | AE32: 75 | AF32: 85 | AG32: 20 | AH32: 30 | AI32: 40
A33: 27 | B33: Sandshrew (Alolan Form) | C33: 0027L0 | D33: 0.5 | E33: 0.5 | F33: Field | G33: Alola | H33: Ice | I33: Steel | J33: Basic | K33: 2 | L33: 0027A0 | M33: - | N33: Kid | O33: 1.25 | P33: - | AC33: 300 | AD33: 50 | AE33: 75 | AF33: 90 | AG33: 10 | AH33: 35 | AI33: 40
A34: 28 | B34: Sandslash | C34: 0028A0 | D34: 0.5 | E34: 0.5 | F34: Field | G34: Kanto | H34: Ground | I34: - | J34: Basic | K34: 2 | L34: 0027A0 | M34: 0027A0 | N34: Adult | O34: 1.25 | P34: Experience | AC34: 450 | AD34: 75 | AE34: 100 | AF34: 110 | AG34: 45 | AH34: 55 | AI34: 65
A35: 28 | B35: Sandslash (Alolan Form) | C35: 0028L0 | D35: 0.5 | E35: 0.5 | F35: Field | G35: Alola | H35: Ice | I35: Steel | J35: Basic | K35: 2 | L35: 0027A0 | M35: 0027L0 | N35: Adult | O35: 1.25 | P35: Experience | AC35: 450 | AD35: 75 | AE35: 100 | AF35: 120 | AG35: 25 | AH35: 65 | AI35: 65
A36: 29 | B36: Nidoran♀ | C36: 0029A0 | D36: 0 | E36: 1 | F36: Field | G36: Kanto | H36: Poison | I36: - | J36: Basic | K36: 1 | L36: 0029A0 | M36: - | N36: Kid | O36: 1 | P36: - | AC36: 275 | AD36: 55 | AE36: 47 | AF36: 52 | AG36: 40 | AH36: 40 | AI36: 41
A37: 30 | B37: Nidorina | C37: 0030A0 | D37: 0 | E37: 1 | F37: Undiscovered | G37: Kanto | H37: Poison | I37: - | J37: Basic | K37: 1 | L37: 0029A0 | M37: 0029A0 | N37: Teen | O37: 1 | P37: Experience | AC37: 365 | AD37: 70 | AE37: 62 | AF37: 67 | AG37: 55 | AH37: 55 | AI37: 56
A38: 31 | B38: Nidoqueen | C38: 0031A0 | D38: 0 | E38: 1 | F38: Undiscovered | G38: Kanto | H38: Poison | I38: Ground | J38: Basic | K38: 1 | L38: 0029A0 | M38: 0030A0 | N38: Adult | O38: 1 | P38: Stone | AC38: 505 | AD38: 90 | AE38: 92 | AF38: 87 | AG38: 75 | AH38: 85 | AI38: 76
A39: 32 | B39: Nidoran♂ | C39: 0032A0 | D39: 1 | E39: 0 | F39: Field | G39: Kanto | H39: Poison | I39: - | J39: Basic | K39: 1 | L39: 0032A0 | M39: - | N39: Kid | O39: 1 | P39: - | AC39: 273 | AD39: 46 | AE39: 57 | AF39: 40 | AG39: 40 | AH39: 40 | AI39: 50
A40: 33 | B40: Nidorino | C40: 0033A0 | D40: 1 | E40: 0 | F40: Field | G40: Kanto | H40: Poison | I40: - | J40: Basic | K40: 1 | L40: 0032A0 | M40: 0032A0 | N40: Teen | O40: 1 | P40: Experience | AC40: 365 | AD40: 61 | AE40: 72 | AF40: 57 | AG40: 55 | AH40: 55 | AI40: 65
A41: 34 | B41: Nidoking | C41: 0034A0 | D41: 1 | E41: 0 | F41: Field | G41: Kanto | H41: Poison | I41: Ground | J41: Basic | K41: 1 | L41: 0032A0 | M41: 0033A0 | N41: Adult | O41: 1 | P41: Stone | AC41: 505 | AD41: 81 | AE41: 102 | AF41: 77 | AG41: 85 | AH41: 75 | AI41: 85
A42: 35 | B42: Clefairy | C42: 0035A0 | D42: 0.25 | E42: 0.75 | F42: Fairy | G42: Kanto | H42: Fairy | I42: - | J42: Basic | K42: 2 | L42: 0173A0 | M42: 0173A0 | N42: Kid | O42: 1.25 | P42: Experience | Q42: 1 | W42: felicidad | Y42: 70 | Z42: 6 | AC42: 323 | AD42: 70 | AE42: 45 | AF42: 48 | AG42: 60 | AH42: 65 | AI42: 35
A43: 36 | B43: Clefable | C43: 0036A0 | D43: 0.25 | E43: 0.75 | F43: Fairy | G43: Kanto | H43: Fairy | I43: - | J43: Basic | K43: 2 | L43: 0173A0 | M43: 0035A0 | N43: Adult | O43: 1.25 | P43: Stone | Q43: 2 | V43: piedra_lunar | AC43: 483 | AD43: 95 | AE43: 70 | AF43: 73 | AG43: 95 | AH43: 90 | AI43: 60
A44: 37 | B44: Vulpix | C44: 0037A0 | D44: 0.25 | E44: 0.75 | F44: Field | G44: Kanto | H44: Fire | I44: - | J44: Basic | K44: 2 | L44: 0037A0 | M44: - | N44: Kid | O44: 1.25 | P44: - | AC44: 299 | AD44: 38 | AE44: 41 | AF44: 40 | AG44: 50 | AH44: 65 | AI44: 65
A45: 37 | B45: Vulpix (Alolan Form) | C45: 0037L0 | D45: 0.25 | E45: 0.75 | F45: Field | G45: Alola | H45: Ice | I45: - | J45: Basic | K45: 2 | L45: 0037A0 | M45: - | N45: Kid | O45: 1.25 | P45: - | AC45: 299 | AD45: 38 | AE45: 41 | AF45: 40 | AG45: 50 | AH45: 65 | AI45: 65
A46: 38 | B46: Ninetales | C46: 0038A0 | D46: 0.25 | E46: 0.75 | F46: Field | G46: Kanto | H46: Fire | I46: - | J46: Basic | K46: 2 | L46: 0037A0 | M46: 0037A0 | N46: Adult | O46: 1.25 | P46: Stone | AC46: 505 | AD46: 73 | AE46: 76 | AF46: 75 | AG46: 81 | AH46: 100 | AI46: 100
A47: 38 | B47: Ninetales (Alolan Form) | C47: 0038L0 | D47: 0.25 | E47: 0.75 | F47: Field | G47: Alola | H47: Ice | I47: Fairy | J47: Basic | K47: 2 | L47: 0037A0 | M47: 0037L0 | N47: Adult | O47: 1.25 | P47: Stone | AC47: 505 | AD47: 73 | AE47: 67 | AF47: 75 | AG47: 81 | AH47: 100 | AI47: 109
A48: 39 | B48: Jigglypuff | C48: 0039A0 | D48: 0.25 | E48: 0.75 | F48: Fairy | G48: Kanto | H48: Fairy | I48: Normal | J48: Basic | K48: 2 | L48: 0174A0 | M48: 0174A0 | N48: Kid | O48: 1.25 | P48: Experience | Q48: 1 | W48: felicidad | Y48: 70 | Z48: 6 | AC48: 270 | AD48: 115 | AE48: 45 | AF48: 20 | AG48: 45 | AH48: 25 | AI48: 20
A49: 40 | B49: Wigglytuff | C49: 0040A0 | D49: 0.25 | E49: 0.75 | F49: Fairy | G49: Kanto | H49: Fairy | I49: Normal | J49: Basic | K49: 2 | L49: 0174A0 | M49: 0039A0 | N49: Adult | O49: 1.25 | P49: Stone | Q49: 2 | V49: piedra_lunar | AC49: 435 | AD49: 140 | AE49: 70 | AF49: 45 | AG49: 85 | AH49: 50 | AI49: 45
A50: 41 | B50: Zubat | C50: 0041A0 | D50: 0.5 | E50: 0.5 | F50: Flying | G50: Kanto | H50: Poison | I50: Flying | J50: Basic | K50: 1 | L50: 0041A0 | M50: - | N50: Kid | O50: 1 | P50: - | AC50: 245 | AD50: 40 | AE50: 45 | AF50: 35 | AG50: 30 | AH50: 40 | AI50: 55
A51: 42 | B51: Golbat | C51: 0042A0 | D51: 0.5 | E51: 0.5 | F51: Flying | G51: Kanto | H51: Poison | I51: Flying | J51: Basic | K51: 1 | L51: 0041A0 | M51: 0041A0 | N51: Teen | O51: 1 | P51: Experience | AC51: 455 | AD51: 75 | AE51: 80 | AF51: 70 | AG51: 65 | AH51: 75 | AI51: 90
A52: 43 | B52: Oddish | C52: 0043A0 | D52: 0.5 | E52: 0.5 | F52: Grass | G52: Kanto | H52: Grass | I52: Poison | J52: Basic | K52: 1 | L52: 0043A0 | M52: - | N52: Kid | O52: 1 | P52: - | AC52: 320 | AD52: 45 | AE52: 50 | AF52: 55 | AG52: 75 | AH52: 65 | AI52: 30
A53: 44 | B53: Gloom | C53: 0044A0 | D53: 0.5 | E53: 0.5 | F53: Grass | G53: Kanto | H53: Grass | I53: Poison | J53: Basic | K53: 1 | L53: 0043A0 | M53: 0043A0 | N53: Teen | O53: 1 | P53: Experience | AC53: 395 | AD53: 60 | AE53: 65 | AF53: 70 | AG53: 85 | AH53: 75 | AI53: 40
A54: 45 | B54: Vileplume | C54: 0045A0 | D54: 0.5 | E54: 0.5 | F54: Grass | G54: Kanto | H54: Grass | I54: Poison | J54: Basic | K54: 1 | L54: 0043A0 | M54: 0044A0 | N54: Adult | O54: 1 | P54: Stone | AC54: 490 | AD54: 75 | AE54: 80 | AF54: 85 | AG54: 110 | AH54: 90 | AI54: 50
A55: 46 | B55: Paras | C55: 0046A0 | D55: 0.5 | E55: 0.5 | F55: Bug | G55: Kanto | H55: Bug | I55: Grass | J55: Basic | K55: 1 | L55: 0046A0 | M55: - | N55: Kid | O55: 1 | P55: - | AC55: 285 | AD55: 35 | AE55: 70 | AF55: 55 | AG55: 45 | AH55: 55 | AI55: 25
A56: 47 | B56: Parasect | C56: 0047A0 | D56: 0.5 | E56: 0.5 | F56: Bug | G56: Kanto | H56: Bug | I56: Grass | J56: Basic | K56: 1 | L56: 0046A0 | M56: 0046A0 | N56: Adult | O56: 1 | P56: Experience | AC56: 405 | AD56: 60 | AE56: 95 | AF56: 80 | AG56: 60 | AH56: 80 | AI56: 30
A57: 48 | B57: Venonat | C57: 0048A0 | D57: 0.5 | E57: 0.5 | F57: Bug | G57: Kanto | H57: Bug | I57: Poison | J57: Basic | K57: 1 | L57: 0048A0 | M57: - | N57: Kid | O57: 1 | P57: - | AC57: 305 | AD57: 60 | AE57: 55 | AF57: 50 | AG57: 40 | AH57: 55 | AI57: 45
A58: 49 | B58: Venomoth | C58: 0049A0 | D58: 0.5 | E58: 0.5 | F58: Bug | G58: Kanto | H58: Bug | I58: Poison | J58: Basic | K58: 1 | L58: 0048A0 | M58: 0048A0 | N58: Adult | O58: 1 | P58: Experience | AC58: 450 | AD58: 70 | AE58: 65 | AF58: 60 | AG58: 90 | AH58: 75 | AI58: 90
A59: 50 | B59: Diglett | C59: 0050A0 | D59: 0.5 | E59: 0.5 | F59: Field | G59: Kanto | H59: Ground | I59: - | J59: Basic | K59: 2 | L59: 0050A0 | M59: - | N59: Kid | O59: 1.25 | P59: - | AC59: 265 | AD59: 10 | AE59: 55 | AF59: 25 | AG59: 35 | AH59: 45 | AI59: 95
A60: 50 | B60: Diglett (Alolan Form) | C60: 0050L0 | D60: 0.5 | E60: 0.5 | F60: Field | G60: Alola | H60: Ground | I60: Steel | J60: Basic | K60: 2 | L60: 0050A0 | M60: - | N60: Kid | O60: 1.25 | P60: - | AC60: 265 | AD60: 10 | AE60: 55 | AF60: 30 | AG60: 35 | AH60: 45 | AI60: 90
A61: 51 | B61: Dugtrio | C61: 0051A0 | D61: 0.5 | E61: 0.5 | F61: Field | G61: Kanto | H61: Ground | I61: - | J61: Basic | K61: 2 | L61: 0050A0 | M61: 0050A0 | N61: Adult | O61: 1.25 | P61: Experience | AC61: 425 | AD61: 35 | AE61: 100 | AF61: 50 | AG61: 50 | AH61: 70 | AI61: 120
... A104: 80 | B104: Slowbro (Galarian Form) | C104: 0080G0 | D104: 0.5 | E104: 0.5 | F104: Water 1 | G104: Galar | H104: Poison | I104: Psychic | J104: Basic | K104: 2 | L104: 0079A0 | M104: 0079G0 | N104: Adult | O104: 1.25 | P104: Gift | AC104: 490 | AD104: 95 | AE104: 100 | AF104: 95 | AG104: 100 | AH104: 70 | AI104: 30
A105: 81 | B105: Magnemite | C105: 0081A0 | D105: - | E105: - | F105: Mineral | G105: Kanto | H105: Electric | I105: Steel | J105: Basic | K105: 1 | L105: 0081A0 | M105: - | N105: Kid | O105: 1 | P105: - | AC105: 325 | AD105: 25 | AE105: 35 | AF105: 70 | AG105: 95 | AH105: 55 | AI105: 45
A106: 82 | B106: Magneton | C106: 0082A0 | D106: - | E106: - | F106: Mineral | G106: Kanto | H106: Electric | I106: Steel | J106: Basic | K106: 1 | L106: 0081A0 | M106: 0081A0 | N106: Teen | O106: 1 | P106: Experience | AC106: 465 | AD106: 50 | AE106: 60 | AF106: 95 | AG106: 120 | AH106: 70 | AI106: 70
A107: 83 | B107: Farfetch'd | C107: 0083A0 | D107: 0.5 | E107: 0.5 | F107: Flying | G107: Kanto | H107: Flying | I107: Normal | J107: Basic | K107: 2 | L107: 0083A0 | M107: - | N107: Adult | O107: 1.25 | P107: - | AC107: 377 | AD107: 52 | AE107: 90 | AF107: 55 | AG107: 58 | AH107: 62 | AI107: 60
A108: 83 | B108: Farfetch'd (Galarian Form) | C108: 0083G0 | D108: 0.5 | E108: 0.5 | F108: Flying | G108: Galar | H108: Fighting | I108: - | J108: Basic | K108: 2 | L108: 0083A0 | M108: - | N108: Kid | O108: 1.25 | P108: - | AC108: 377 | AD108: 52 | AE108: 95 | AF108: 55 | AG108: 58 | AH108: 62 | AI108: 55
A109: 84 | B109: Doduo | C109: 0084A0 | D109: 0.5 | E109: 0.5 | F109: Flying | G109: Kanto | H109: Flying | I109: Normal | J109: Basic | K109: 2 | L109: 0084A0 | M109: - | N109: Kid | O109: 1.25 | P109: - | AC109: 310 | AD109: 35 | AE109: 85 | AF109: 45 | AG109: 35 | AH109: 35 | AI109: 75
A110: 85 | B110: Dodrio | C110: 0085A0 | D110: 0.5 | E110: 0.5 | F110: Flying | G110: Kanto | H110: Flying | I110: Normal | J110: Basic | K110: 2 | L110: 0084A0 | M110: 0084A0 | N110: Adult | O110: 1.25 | P110: Experience | AC110: 470 | AD110: 60 | AE110: 110 | AF110: 70 | AG110: 60 | AH110: 60 | AI110: 110
A111: 86 | B111: Seel | C111: 0086A0 | D111: 0.5 | E111: 0.5 | F111: Water 3 | G111: Kanto | H111: Water | I111: - | J111: Basic | K111: 2 | L111: 0086A0 | M111: - | N111: Kid | O111: 1.25 | P111: - | AC111: 325 | AD111: 65 | AE111: 45 | AF111: 55 | AG111: 45 | AH111: 70 | AI111: 45
A112: 87 | B112: Dewgong | C112: 0087A0 | D112: 0.5 | E112: 0.5 | F112: Water 3 | G112: Kanto | H112: Water | I112: Ice | J112: Basic | K112: 2 | L112: 0086A0 | M112: 0086A0 | N112: Adult | O112: 1.25 | P112: Experience | AC112: 475 | AD112: 90 | AE112: 70 | AF112: 80 | AG112: 70 | AH112: 95 | AI112: 70
A113: 88 | B113: Grimer | C113: 0088A0 | D113: 0.5 | E113: 0.5 | F113: Amorphous | G113: Kanto | H113: Poison | I113: - | J113: Basic | K113: 2 | L113: 0088A0 | M113: - | N113: Kid | O113: 1.25 | P113: - | AC113: 325 | AD113: 80 | AE113: 80 | AF113: 50 | AG113: 40 | AH113: 50 | AI113: 25
A114: 88 | B114: Grimer (Alolan Form) | C114: 0088L0 | D114: 0.5 | E114: 0.5 | F114: Amorphous | G114: Alola | H114: Poison | I114: Dark | J114: Basic | K114: 2 | L114: 0088A0 | M114: - | N114: Kid | O114: 1.25 | P114: - | AC114: 325 | AD114: 80 | AE114: 80 | AF114: 50 | AG114: 40 | AH114: 50 | AI114: 25
A115: 89 | B115: Muk | C115: 0089A0 | D115: 0.5 | E115: 0.5 | F115: Amorphous | G115: Kanto | H115: Poison | I115: - | J115: Basic | K115: 2 | L115: 0088A0 | M115: 0088A0 | N115: Adult | O115: 1.25 | P115: Experience | AC115: 500 | AD115: 105 | AE115: 105 | AF115: 75 | AG115: 65 | AH115: 100 | AI115: 50
A116: 89 | B116: Muk (Alolan Form) | C116: 0089L0 | D116: 0.5 | E116: 0.5 | F116: Amorphous | G116: Alola | H116: Poison | I116: Dark | J116: Basic | K116: 2 | L116: 0088A0 | M116: 0088L0 | N116: Adult | O116: 1.25 | P116: Experience | AC116: 500 | AD116: 105 | AE116: 105 | AF116: 75 | AG116: 65 | AH116: 100 | AI116: 50
A117: 90 | B117: Shellder | C117: 0090A0 | D117: 0.5 | E117: 0.5 | F117: Water 3 | G117: Kanto | H117: Water | I117: - | J117: Basic | K117: 2 | L117: 0090A0 | M117: - | N117: Kid | O117: 1.25 | P117: - | AC117: 305 | AD117: 30 | AE117: 65 | AF117: 100 | AG117: 45 | AH117: 25 | AI117: 40
A118: 91 | B118: Cloyster | C118: 0091A0 | D118: 0.5 | E118: 0.5 | F118: Water 2 | G118: Kanto | H118: Water | I118: Ice | J118: Basic | K118: 2 | L118: 0090A0 | M118: 0090A0 | N118: Adult | O118: 1.25 | P118: Stone | AC118: 525 | AD118: 50 | AE118: 95 | AF118: 180 | AG118: 85 | AH118: 45 | AI118: 70
... A126: 99 | B126: Kingler | C126: 0099A0 | D126: 0.5 | E126: 0.5 | F126: Water 3 | G126: Kanto | H126: Water | I126: - | J126: Basic | K126: 1 | L126: 0098A0 | M126: 0098A0 | N126: Adult | O126: 1 | P126: Experience | AC126: 475 | AD126: 55 | AE126: 130 | AF126: 115 | AG126: 50 | AH126: 50 | AI126: 75
A127: 100 | B127: Voltorb | C127: 0100A0 | D127: - | E127: - | F127: Mineral | G127: Kanto | H127: Electric | I127: - | J127: Basic | K127: 1 | L127: 0100A0 | M127: - | N127: Kid | O127: 1 | P127: - | AC127: 330 | AD127: 40 | AE127: 30 | AF127: 50 | AG127: 55 | AH127: 55 | AI127: 100
A128: 100 | B128: Voltorb (Hisuian Voltorb) | C128: 0100H0 | D128: 0.5 | E128: 0.5 | F128: Mineral | G128: Hisui | H128: Electric | I128: Grass | J128: Basic | K128: 1 | L128: 0100A0 | M128: - | N128: Kid | O128: 1 | P128: - | AC128: 330 | AD128: 40 | AE128: 30 | AF128: 50 | AG128: 55 | AH128: 55 | AI128: 100
A129: 101 | B129: Electrode | C129: 0101A0 | D129: - | E129: - | F129: Mineral | G129: Kanto | H129: Electric | I129: - | J129: Basic | K129: 1 | L129: 0100A0 | M129: 0100A0 | N129: Adult | O129: 1 | P129: Experience | AC129: 490 | AD129: 60 | AE129: 50 | AF129: 70 | AG129: 80 | AH129: 80 | AI129: 150
A130: 101 | B130: Electrode (Hisuian Electrode) | C130: 0101H0 | D130: 0.5 | E130: 0.5 | F130: Mineral | G130: Hisui | H130: Electric | I130: Gr | J130: Basic | K130: 1 | L130: 0100A0 | M130: 0100H0 | N130: Adult | O130: 1 | P130: Experience | AC130: 490 | AD130: 60 | AE130: 50 | AF130: 70 | AG130: 80 | AH130: 80 | AI130: 150
A131: 102 | B131: Exeggcute | C131: 0102A0 | D131: 0.5 | E131: 0.5 | F131: Grass | G131: Kanto | H131: Grass | I131: Psychic | J131: Basic | K131: 2 | L131: 0102A0 | M131: - | N131: Kid | O131: 1.25 | P131: - | AC131: 325 | AD131: 60 | AE131: 40 | AF131: 80 | AG131: 60 | AH131: 45 | AI131: 40
A132: 103 | B132: Exeggutor | C132: 0103A0 | D132: 0.5 | E132: 0.5 | F132: Grass | G132: Kanto | H132: Grass | I132: Psychic | J132: Basic | K132: 2 | L132: 0102A0 | M132: 0102A0 | N132: Adult | O132: 1.25 | P132: Stone | AC132: 530 | AD132: 95 | AE132: 95 | AF132: 85 | AG132: 125 | AH132: 75 | AI132: 55
A133: 103 | B133: Exeggutor (Alolan Form) | C133: 0103L0 | D133: 0.5 | E133: 0.5 | F133: Grass | G133: Alola | H133: Grass | I133: Dragon | J133: Basic | K133: 2 | L133: 0102A0 | M133: 0102A0 | N133: Adult | O133: 1.25 | P133: Stone | AC133: 530 | AD133: 95 | AE133: 105 | AF133: 85 | AG133: 125 | AH133: 75 | AI133: 45
A134: 104 | B134: Cubone | C134: 0104A0 | D134: 0.5 | E134: 0.5 | F134: Monster | G134: Kanto | H134: Ground | I134: - | J134: Basic | K134: 2 | L134: 0104A0 | M134: - | N134: Kid | O134: 1.25 | P134: - | AC134: 320 | AD134: 50 | AE134: 50 | AF134: 95 | AG134: 40 | AH134: 50 | AI134: 35
A135: 105 | B135: Marowak | C135: 0105A0 | D135: 0.5 | E135: 0.5 | F135: Monster | G135: Kanto | H135: Ground | I135: - | J135: Basic | K135: 2 | L135: 0104A0 | M135: 0104A0 | N135: Adult | O135: 1.25 | P135: Experience | AC135: 425 | AD135: 60 | AE135: 80 | AF135: 110 | AG135: 50 | AH135: 80 | AI135: 45
A136: 105 | B136: Marowak (Alolan Form) | C136: 0105L0 | D136: 0.5 | E136: 0.5 | F136: Monster | G136: Alola | H136: Fire | I136: Ghost | J136: Basic | K136: 2 | L136: 0104A0 | M136: 0104A0 | N136: Adult | O136: 1.25 | P136: Experience | AC136: 425 | AD136: 60 | AE136: 80 | AF136: 110 | AG136: 50 | AH136: 80 | AI136: 45
A137: 106 | B137: Hitmonlee | C137: 0106A0 | D137: 1 | E137: 0 | F137: Human-Like | G137: Kanto | H137: Fighting | I137: - | J137: Basic | K137: 3 | L137: 0236A0 | M137: 0236A0 | N137: Adult | O137: 1.5 | P137: Experience | Q137: 2 | R137: 30 | U137: 70 | AC137: 455 | AD137: 50 | AE137: 120 | AF137: 53 | AG137: 35 | AH137: 110 | AI137: 87
A138: 107 | B138: Hitmonchan | C138: 0107A0 | D138: 1 | E138: 0 | F138: Human-Like | G138: Kanto | H138: Fighting | I138: - | J138: Basic | K138: 3 | L138: 0236A0 | M138: 0236A0 | N138: Adult | O138: 1.5 | P138: Experience | Q138: 2 | R138: 70 | U138: 30 | AC138: 455 | AD138: 50 | AE138: 105 | AF138: 79 | AG138: 35 | AH138: 110 | AI138: 76
A139: 108 | B139: Lickitung | C139: 0108A0 | D139: 0.5 | E139: 0.5 | F139: Monster | G139: Kanto | H139: Normal | I139: - | J139: Basic | K139: 3 | L139: 0108A0 | M139: - | N139: Kid | O139: 1.5 | P139: - | AC139: 385 | AD139: 90 | AE139: 55 | AF139: 75 | AG139: 60 | AH139: 75 | AI139: 30
A140: 109 | B140: Koffing | C140: 0109A0 | D140: 0.5 | E140: 0.5 | F140: Amorphous | G140: Kanto | H140: Poison | I140: - | J140: Basic | K140: 2 | L140: 0109A0 | M140: - | N140: Kid | O140: 1.25 | P140: - | AC140: 340 | AD140: 40 | AE140: 65 | AF140: 95 | AG140: 60 | AH140: 45 | AI140: 35
A141: 110 | B141: Weezing | C141: 0110A0 | D141: 0.5 | E141: 0.5 | F141: Amorphous | G141: Kanto | H141: Poison | I141: - | J141: Basic | K141: 2 | L141: 0109A0 | M141: 0109A0 | N141: Adult | O141: 1.25 | P141: Experience | AC141: 490 | AD141: 65 | AE141: 90 | AF141: 120 | AG141: 85 | AH141: 70 | AI141: 60
A142: 110 | B142: Weezing (Galarian Form) | C142: 0110G0 | D142: 0.5 | E142: 0.5 | F142: Amorphous | G142: Galar | H142: Poison | I142: Fairy | J142: Basic | K142: 2 | L142: 0109A0 | M142: 0109A0 | N142: Adult | O142: 1.25 | P142: Experience | AC142: 490 | AD142: 65 | AE142: 90 | AF142: 120 | AG142: 85 | AH142: 70 | AI142: 60
A143: 111 | B143: Rhyhorn | C143: 0111A0 | D143: 0.5 | E143: 0.5 | F143: Field | G143: Kanto | H143: Ground | I143: Rock | J143: Basic | K143: 2 | L143: 0111A0 | M143: - | N143: Kid | O143: 1.25 | P143: - | AC143: 345 | AD143: 80 | AE143: 85 | AF143: 95 | AG143: 30 | AH143: 30 | AI143: 25
A144: 112 | B144: Rhydon | C144: 0112A0 | D144: 0.5 | E144: 0.5 | F144: Field | G144: Kanto | H144: Ground | I144: Rock | J144: Basic | K144: 2 | L144: 0111A0 | M144: 0111A0 | N144: Teen | O144: 1.25 | P144: Experience | AC144: 485 | AD144: 105 | AE144: 130 | AF144: 120 | AG144: 45 | AH144: 45 | AI144: 40
A145: 113 | B145: Chansey | C145: 0113A0 | D145: 0 | E145: 1 | F145: Fairy | G145: Kanto | H145: Normal | I145: - | J145: Basic | K145: 3 | L145: 0440A0 | M145: 0440A0 | N145: Kid | O145: 1.5 | P145: Experience | Q145: 1 | T145: 80 | W145: felicidad | Y145: 70 | Z145: 6 | AC145: 450 | AD145: 250 | AE145: 5 | AF145: 5 | AG145: 35 | AH145: 105 | AI145: 50
A146: 114 | B146: Tangela | C146: 0114A0 | D146: 0.5 | E146: 0.5 | F146: Grass | G146: Kanto | H146: Grass | I146: - | J146: Basic | K146: 2 | L146: 0114A0 | M146: - | N146: Kid | O146: 1.25 | P146: - | AC146: 435 | AD146: 65 | AE146: 55 | AF146: 115 | AG146: 100 | AH146: 40 | AI146: 60
A147: 115 | B147: Kangaskhan | C147: 0115A0 | D147: 0 | E147: 1 | F147: Monster | G147: Kanto | H147: Normal | I147: - | J147: Basic | K147: 3 | L147: 0115A0 | M147: - | N147: Adult | O147: 1.5 | P147: - | AC147: 490 | AD147: 105 | AE147: 95 | AF147: 80 | AG147: 40 | AH147: 80 | AI147: 90
A148: 116 | B148: Horsea | C148: 0116A0 | D148: 0.5 | E148: 0.5 | F148: Dragon | G148: Kanto | H148: Water | I148: - | J148: Basic | K148: 2 | L148: 0116A0 | M148: - | N148: Kid | O148: 1.25 | P148: - | AC148: 295 | AD148: 30 | AE148: 40 | AF148: 70 | AG148: 70 | AH148: 25 | AI148: 60
A149: 117 | B149: Seadra | C149: 0117A0 | D149: 0.5 | E149: 0.5 | F149: Dragon | G149: Kanto | H149: Water | I149: - | J149: Basic | K149: 2 | L149: 0116A0 | M149: 0116A0 | N149: Teen | O149: 1.25 | P149: Experience | AC149: 440 | AD149: 55 | AE149: 65 | AF149: 95 | AG149: 95 | AH149: 45 | AI149: 85
A150: 118 | B150: Goldeen | C150: 0118A0 | D150: 0.5 | E150: 0.5 | F150: Water 2 | G150: Kanto | H150: Water | I150: - | J150: Basic | K150: 2 | L150: 0118A0 | M150: - | N150: Kid | O150: 1.25 | P150: - | AC150: 320 | AD150: 45 | AE150: 67 | AF150: 60 | AG150: 35 | AH150: 50 | AI150: 63
A151: 119 | B151: Seaking | C151: 0119A0 | D151: 0.5 | E151: 0.5 | F151: Water 2 | G151: Kanto | H151: Water | I151: - | J151: Basic | K151: 2 | L151: 0118A0 | M151: 0118A0 | N151: Adult | O151: 1.25 | P151: Experience | AC151: 450 | AD151: 80 | AE151: 92 | AF151: 65 | AG151: 65 | AH151: 80 | AI151: 68
A152: 120 | B152: Staryu | C152: 0120A0 | D152: - | E152: - | F152: Water 3 | G152: Kanto | H152: Water | I152: - | J152: Basic | K152: 2 | L152: 0120A0 | M152: - | N152: Kid | O152: 1.25 | P152: - | AC152: 340 | AD152: 30 | AE152: 45 | AF152: 55 | AG152: 70 | AH152: 55 | AI152: 85
A153: 121 | B153: Starmie | C153: 0121A0 | D153: - | E153: - | F153: Water 3 | G153: Kanto | H153: Water | I153: Psychic | J153: Basic | K153: 2 | L153: 0120A0 | M153: 0120A0 | N153: Adult | O153: 1.25 | P153: Stone | AC153: 520 | AD153: 60 | AE153: 75 | AF153: 85 | AG153: 100 | AH153: 85 | AI153: 115
A154: 122 | B154: Mr. Mime | C154: 0122A0 | D154: 0.5 | E154: 0.5 | F154: Human-Like | G154: Kanto | H154: Psychic | I154: Fairy | J154: Basic | K154: 3 | L154: 0439A0 | M154: 0439A0 | N154: Adult | O154: 1.5 | P154: Experience | Q154: 2 | S154: 50 | W154: felicidad | Y154: 70 | Z154: 6 | AC154: 460 | AD154: 40 | AE154: 45 | AF154: 65 | AG154: 100 | AH154: 120 | AI154: 90
A155: 122 | B155: Mr. Mime (Galarian Form) | C155: 0122G0 | D155: 0.5 | E155: 0.5 | F155: Human-Like | G155: Galar | H155: Psychic | I155: Fairy | J155: Basic | K155: 3 | L155: 0439A0 | M155: 0439A0 | N155: Kid | O155: 1.5 | P155: Experience | AC155: 460 | AD155: 50 | AE155: 65 | AF155: 65 | AG155: 90 | AH155: 90 | AI155: 100
A156: 123 | B156: Scyther | C156: 0123A0 | D156: 0.5 | E156: 0.5 | F156: Bug | G156: Kanto | H156: Bug | I156: Flying | J156: Basic | K156: 3 | L156: 0123A0 | M156: - | N156: Kid | O156: 1.5 | P156: - | AC156: 500 | AD156: 70 | AE156: 110 | AF156: 80 | AG156: 55 | AH156: 80 | AI156: 105
A157: 124 | B157: Jynx | C157: 0124A0 | D157: 0 | E157: 1 | F157: Human-Like | G157: Kanto | H157: Ice | I157: Psychic | J157: Basic | K157: 3 | L157: 0238A0 | M157: 0238A0 | N157: Adult | O157: 1.5 | P157: Experience | Q157: 2 | S157: 50 | W157: felicidad | Y157: 70 | Z157: 6 | AC157: 455 | AD157: 65 | AE157: 50 | AF157: 35 | AG157: 115 | AH157: 95 | AI157: 95
A158: 125 | B158: Electabuzz | C158: 0125A0 | D158: 0.75 | E158: 0.25 | F158: Human-Like | G158: Kanto | H158: Electric | I158: - | J158: Basic | K158: 3 | L158: 0239A0 | M158: 0239A0 | N158: Kid | O158: 1.5 | P158: Experience | Q158: 1 | U158: 50 | W158: felicidad | Y158: 70 | Z158: 6 | AC158: 490 | AD158: 65 | AE158: 83 | AF158: 57 | AG158: 95 | AH158: 85 | AI158: 105
A159: 126 | B159: Magmar | C159: 0126A0 | D159: 0.75 | E159: 0.25 | F159: Human-Like | G159: Kanto | H159: Fire | I159: - | J159: Basic | K159: 3 | L159: 0240A0 | M159: 0240A0 | N159: Kid | O159: 1.5 | P159: Experience | Q159: 1 | R159: 50 | W159: felicidad | Y159: 70 | Z159: 6 | AC159: 495 | AD159: 65 | AE159: 95 | AF159: 57 | AG159: 100 | AH159: 85 | AI159: 93
A160: 127 | B160: Pinsir | C160: 0127A0 | D160: 0.5 | E160: 0.5 | F160: Bug | G160: Kanto | H160: Bug | I160: - | J160: Basic | K160: 3 | L160: 0127A0 | M160: - | N160: Adult | O160: 1.5 | P160: - | AC160: 500 | AD160: 65 | AE160: 125 | AF160: 100 | AG160: 55 | AH160: 70 | AI160: 85
A161: 128 | B161: Tauros | C161: 0128A0 | D161: 1 | E161: 0 | F161: Field | G161: Kanto | H161: Normal | I161: - | J161: Basic | K161: 3 | L161: 0128A0 | M161: - | N161: Adult | O161: 1.5 | P161: - | AC161: 490 | AD161: 75 | AE161: 100 | AF161: 95 | AG161: 40 | AH161: 70 | AI161: 110
A162: 128 | B162: Tauros (Combat Breed) | C162: 0128P0 | D162: 1 | E162: 0 | F162: Field | G162: Paldea | H162: Fighting | I162: - | J162: Basic | K162: 3 | L162: 0128A0 | M162: - | N162: Adult | O162: 1.5 | P162: - | AC162: 490 | AD162: 75 | AE162: 110 | AF162: 105 | AG162: 30 | AH162: 70 | AI162: 100
...

Sheet Hoja3
A2: tiempo | B2: hambre
A3: stats | B3: felicidad
A4: objeto | B4: energía
A5: acción | B5: higiene
A6: caos
C8: edadMinima | D8: minHambre | E8: minFelicidad | F8: minEnergia | G8: minHigiene | H8: minStyle | I8: minIQ | J8: minKindness | K8: minStrength

Sheet LP Cost x Team
A1: LP Cost | B1: (Varios elementos)
A2: Stage | B2: (Varios elementos)
C4: Valores
A5: # | B5: Trainer | C5: Suma de LP Cost | D5: Suma de Overall
A6: 1 | B6: Red | C6: 26 | D6: 155
A7: 2 | B7: Blue | C7: 25 | D7: 158
A8: 3 | B8: Leaf | C8: 24 | D8: 153
A9: 4 | B9: Ethan | C9: 24 | D9: 147
A10: 5 | B10: Kris | C10: 23 | D10: 154
A11: 6 | B11: Lyra | C11: 23 | D11: 150
A12: 7 | B12: Silver | C12: 24 | D12: 151
A13: 8 | B13: Brendan | C13: 22 | D13: 141
A14: 9 | B14: May | C14: 22 | D14: 141
A15: 10 | B15: Wally | C15: 22 | D15: 145
A16: 11 | B16: Barry | C16: 24 | D16: 150
A17: 12 | B17: Lucas | C17: 23 | D17: 146
... A40: 100 | B40: Jomi | C40: 25 | D40: 157

Sheet Pokedex
B3: =VLOOKUP(C3,'Pokemon Db'!A:AP,2,0) -> Charizard | C3: 6 | E3: =CONCATENATE("#",C3," - ",B3) -> #6 - Charizard
E10: =VLOOKUP(C3,'Pokemon Db'!A:AP,19,0) -> 534
E11: =VLOOKUP(E10,Habs!B:D,3,0) -> #N/A
E13: =VLOOKUP(C3,'Pokemon Db'!A:AL,22,0) -> 78 | F13: =VLOOKUP(C3,'Pokemon Db'!A:AP,21,0) -> 84
E14: =VLOOKUP(F13,Movimientos!A:C,3,0) -> #N/A
E15: =VLOOKUP(C3,'Pokemon Db'!A:AL,24,0) -> 85 | F15: =VLOOKUP(C3,'Pokemon Db'!A:AP,23,0) -> 109
E16: =VLOOKUP(F15,Movimientos!A:C,3,0) -> #N/A
E18: W| | I18: |R

Sheet Evolution
A1: # | B1: Name | C1: Cod | D1: Family | E1: Preevolution | F1: Method | G1: Exp | H1: Evolves into | I1: Method | J1: Exp | K1: Friend | L1: Gender | M1: Move | N1: Weather | O1: Time | P1: Hability | Q1: PKMN in team | R1: Stat | S1: Name
A2: 1 | B2: Bulbasaur | C2: 001A | D2: 001A | E2: - | F2: - | G2: - | H2: Ivysaur | I2: Experience | J2: 3 | S2: Bulbasaur
A3: 2 | B3: Ivysaur | C3: 002A | D3: 001A | E3: 001A | F3: Experience | G3: 3 | H3: Venusaur | I3: Experience | J3: 4 | S3: Ivysaur
A4: 3 | B4: Venusaur | C4: 003A | D4: 001A | E4: 002A | F4: Experience | G4: 4 | H4: - | I4: - | J4: - | S4: Venusaur
A5: 4 | B5: Charmander | C5: 004A | D5: 004A | E5: - | F5: - | G5: - | H5: Charmeleon | I5: Experience | J5: 3 | S5: Charmander
A6: 5 | B6: Charmeleon | C6: 005A | D6: 004A | E6: 004A | F6: Experience | G6: 3 | H6: Charizard | I6: Experience | J6: 4 | S6: Charmeleon
A7: 6 | B7: Charizard | C7: 006A | D7: 004A | E7: 005A | F7: Experience | G7: 4 | H7: - | I7: - | J7: - | S7: Charizard
A8: 7 | B8: Squirtle | C8: 007A | D8: 007A | E8: - | F8: - | G8: - | H8: Wartortle | I8: Experience | J8: 3 | S8: Squirtle
A9: 8 | B9: Wartortle | C9: 008A | D9: 007A | E9: 007A | F9: Experience | G9: 3 | H9: Blastoise | I9: Experience | J9: 4 | S9: Wartortle
A10: 9 | B10: Blastoise | C10: 009A | D10: 007A | E10: 008A | F10: Experience | G10: 4 | H10: - | I10: - | J10: - | S10: Blastoise
A11: 10 | B11: Caterpie | C11: 010A | D11: 010A | E11: - | F11: - | G11: - | H11: Metapod | I11: Experience | J11: 2 | S11: Caterpie
A12: 11 | B12: Metapod | C12: 011A | D12: 010A | E12: 010A | F12: Experience | G12: 2 | H12: Butterfree | I12: Experience | J12: 2 | S12: Metapod
A13: 12 | B13: Butterfree | C13: 012A | D13: 010A | E13: 011A | F13: Experience | G13: 2 | H13: - | I13: - | J13: - | S13: Butterfree
A14: 13 | B14: Weedle | C14: 013A | D14: 013A | E14: - | F14: - | G14: - | H14: Kakuna | I14: Experience | J14: 2 | S14: Weedle
A15: 14 | B15: Kakuna | C15: 014A | D15: 013A | E15: 013A | F15: Experience | G15: 2 | H15: Beedrill | I15: Experience | J15: 2 | S15: Kakuna
A16: 15 | B16: Beedrill | C16: 015A | D16: 013A | E16: 014A | F16: Experience | G16: 2 | H16: - | I16: - | J16: - | S16: Beedrill
A17: 16 | B17: Pidgey | C17: 016A | D17: 016A | E17: - | F17: - | G17: - | H17: Pidgeotto | I17: Experience | J17: 3 | S17: Pidgey
A18: 17 | B18: Pidgeotto | C18: 017A | D18: 016A | E18: 016A | F18: Experience | G18: 3 | H18: Pidgeot | I18: Experience | J18: 4 | S18: Pidgeotto
A19: 18 | B19: Pidgeot | C19: 018A | D19: 016A | E19: 017A | F19: Experience | G19: 4 | H19: - | I19: - | J19: - | S19: Pidgeot
A20: 19 | B20: Rattata | C20: 019A | D20: 019A | E20: - | F20: - | G20: - | H20: Raticate | I20: Experience | J20: 3 | S20: Rattata
A21: 20 | B21: Raticate | C21: 020A | D21: 019A | E21: 019A | F21: Experience | G21: 3 | H21: - | I21: - | J21: - | S21: Raticate
A22: 21 | B22: Spearow | C22: 021A | D22: 021A | E22: - | F22: - | G22: - | H22: Fearow | I22: Experience | J22: 3 | S22: Spearow
A23: 22 | B23: Fearow | C23: 022A | D23: 021A | E23: 021A | F23: Experience | G23: 3 | H23: - | I23: - | J23: - | S23: Fearow
A24: 23 | B24: Ekans | C24: 023A | D24: 023A | E24: - | F24: - | G24: - | H24: Arbok | I24: Experience | J24: 3 | S24: Ekans
A25: 24 | B25: Arbok | C25: 024A | D25: 023A | E25: 023A | F25: Experience | G25: 3 | H25: - | I25: - | J25: - | S25: Arbok
A26: 25 | B26: Pikachu (Partner Pikachu) | C26: 025B | D26: 172A | E26: - | F26: - | H26: - | I26: - | J26: - | S26: Pikachu (Partner Pikachu)
A27: 25 | B27: Pikachu | C27: 025A | D27: 172A | E27: 172A | F27: Experience | G27: 3 | H27: Raichu | I27: Stone | J27: - | K27: 30 | S27: Pikachu
A28: 26 | B28: Raichu | C28: 026A | D28: 172A | E28: 025A | F28: Stone | G28: - | H28: - | I28: - | J28: - | S28: Raichu
A29: 27 | B29: Sandshrew | C29: 027A | D29: 027A | E29: - | F29: - | G29: - | H29: Sandslash | I29: Experience | J29: 3 | S29: Sandshrew
A30: 28 | B30: Sandslash | C30: 028A | D30: 027A | E30: 027A | F30: Experience | G30: 3 | H30: - | I30: - | J30: - | S30: Sandslash
A31: 29 | B31: Nidoran♀ | C31: 029A | D31: 029A | E31: - | F31: - | G31: - | H31: Nidorina | I31: Experience | J31: 3 | S31: Nidoran♀
A32: 30 | B32: Nidorina | C32: 030A | D32: 029A | E32: 029A | F32: Experience | G32: 3 | H32: Nidoqueen | I32: Stone | J32: - | S32: Nidorina
A33: 31 | B33: Nidoqueen | C33: 031A | D33: 029A | E33: 030A | F33: Stone | G33: - | H33: - | I33: - | J33: - | S33: Nidoqueen
A34: 32 | B34: Nidoran♂ | C34: 032A | D34: 032A | E34: - | F34: - | G34: - | H34: Nidorino | I34: Experience | J34: 3 | S34: Nidoran♂
A35: 33 | B35: Nidorino | C35: 033A | D35: 032A | E35: 032A | F35: Experience | G35: 3 | H35: Nidoking | I35: Stone | J35: - | S35: Nidorino
A36: 34 | B36: Nidoking | C36: 034A | D36: 032A | E36: 033A | F36: Stone | G36: - | H36: - | I36: - | J36: - | S36: Nidoking
A37: 35 | B37: Clefairy | C37: 035A | D37: 173A | E37: 173A | F37: Experience | G37: 3 | H37: Clefable | I37: Stone | J37: - | K37: 30 | S37: Clefairy
A38: 36 | B38: Clefable | C38: 036A | D38: 173A | E38: 035A | F38: Stone | G38: - | H38: - | I38: - | J38: - | S38: Clefable
A39: 37 | B39: Vulpix | C39: 037A | D39: 037A | E39: - | F39: - | G39: - | H39: Ninetales | I39: Stone | J39: - | S39: Vulpix
A40: 38 | B40: Ninetales | C40: 038A | D40: 037A | E40: 037A | F40: Stone | G40: - | H40: - | I40: - | J40: - | S40: Ninetales
A41: 39 | B41: Jigglypuff | C41: 039A | D41: 174A | E41: 174A | F41: Experience | G41: 3 | H41: Wigglytuff | I41: Stone | J41: - | K41: 30 | S41: Jigglypuff
A42: 40 | B42: Wigglytuff | C42: 040A | D42: 174A | E42: 039A | F42: Stone | G42: - | H42: - | I42: - | J42: - | S42: Wigglytuff
A43: 41 | B43: Zubat | C43: 041A | D43: 041A | E43: - | F43: - | G43: - | H43: Golbat | I43: Experience | J43: 3 | S43: Zubat
A44: 42 | B44: Golbat | C44: 042A | D44: 041A | E44: 041A | F44: Experience | G44: 3 | H44: - | I44: - | J44: - | S44: Golbat
A45: 43 | B45: Oddish | C45: 043A | D45: 043A | E45: - | F45: - | G45: - | H45: Gloom | I45: Experience | J45: 3 | S45: Oddish
A46: 44 | B46: Gloom | C46: 044A | D46: 043A | E46: 043A | F46: Experience | G46: 3 | H46: Vileplume | I46: Stone | J46: - | S46: Gloom
A47: 45 | B47: Vileplume | C47: 045A | D47: 043A | E47: 044A | F47: Stone | G47: - | H47: - | I47: - | J47: - | S47: Vileplume
A48: 46 | B48: Paras | C48: 046A | D48: 046A | E48: - | F48: - | G48: - | H48: Parasect | I48: Experience | J48: 3 | S48: Paras
A49: 47 | B49: Parasect | C49: 047A | D49: 046A | E49: 046A | F49: Experience | G49: 3 | H49: - | I49: - | J49: - | S49: Parasect
A50: 48 | B50: Venonat | C50: 048A | D50: 048A | E50: - | F50: - | G50: - | H50: Venomoth | I50: Experience | J50: 4 | S50: Venonat
A51: 49 | B51: Venomoth | C51: 049A | D51: 048A | E51: 048A | F51: Experience | G51: 4 | H51: - | I51: - | J51: - | S51: Venomoth
A52: 50 | B52: Diglett | C52: 050A | D52: 050A | E52: - | F52: - | G52: - | H52: Dugtrio | I52: Experience | J52: 3 | S52: Diglett
A53: 51 | B53: Dugtrio | C53: 051A | D53: 050A | E53: 050A | F53: Experience | G53: 3 | H53: - | I53: - | J53: - | S53: Dugtrio
A54: 52 | B54: Meowth | C54: 052A | D54: 052A | E54: - | F54: - | G54: - | H54: Persian | I54: Experience | J54: 3 | S54: Meowth
A55: 53 | B55: Persian | C55: 053A | D55: 052A | E55: 052A | F55: Experience | G55: 3 | H55: - | I55: - | J55: - | S55: Persian
A56: 54 | B56: Psyduck | C56: 054A | D56: 054A | E56: - | F56: - | G56: - | H56: Golduck | I56: Experience | J56: 4 | S56: Psyduck
A57: 55 | B57: Golduck | C57: 055A | D57: 054A | E57: 054A | F57: Experience | G57: 4 | H57: - | I57: - | J57: - | S57: Golduck
A58: 56 | B58: Mankey | C58: 056A | D58: 056A | E58: - | F58: - | G58: - | H58: Primeape | I58: Experience | J58: 3 | S58: Mankey
A59: 57 | B59: Primeape | C59: 057A | D59: 056A | E59: 056A | F59: Experience | G59: 3 | H59: - | I59: - | J59: - | S59: Primeape
A60: 58 | B60: Growlithe | C60: 058A | D60: 058A | E60: - | F60: - | G60: - | H60: Arcanine | I60: Stone | J60: - | S60: Growlithe
A61: 59 | B61: Arcanine | C61: 059A | D61: 058A | E61: 058A | F61: Stone | G61: - | H61: - | I61: - | J61: - | S61: Arcanine
A62: 60 | B62: Poliwag | C62: 060A | D62: 060A | E62: - | F62: - | G62: - | H62: Poliwhirl | I62: Experience | J62: 3 | S62: Poliwag
A63: 61 | B63: Poliwhirl | C63: 061A | D63: 060A | E63: 060A | F63: Experience | G63: 3 | H63: Poliwrath | I63: Stone | J63: - | S63: Poliwhirl
A64: 62 | B64: Poliwrath | C64: 062A | D64: 060A | E64: 061A | F64: Stone | G64: - | H64: - | I64: - | J64: - | S64: Poliwrath
A65: 63 | B65: Abra | C65: 063A | D65: 063A | E65: - | F65: - | G65: - | H65: Kadabra | I65: Experience | J65: 3 | S65: Abra
A66: 64 | B66: Kadabra | C66: 064A | D66: 063A | E66: 063A | F66: Experience | G66: 3 | H66: Alakazam | I66: Experience | J66: 5 | S66: Kadabra
A67: 65 | B67: Alakazam | C67: 065A | D67: 063A | E67: 064A | F67: Experience | G67: 5 | H67: - | I67: - | J67: - | S67: Alakazam
A68: 66 | B68: Machop | C68: 066A | D68: 066A | E68: - | F68: - | G68: - | H68: Machoke | I68: Experience | J68: 3 | S68: Machop
A69: 67 | B69: Machoke | C69: 067A | D69: 066A | E69: 066A | F69: Experience | G69: 3 | H69: Machamp | I69: Experience | J69: 5 | S69: Machoke
A70: 68 | B70: Machamp | C70: 068A | D70: 066A | E70: 067A | F70: Experience | G70: 5 | H70: - | I70: - | J70: - | S70: Machamp
A71: 69 | B71: Bellsprout | C71: 069A | D71: 069A | E71: - | F71: - | G71: - | H71: Weepinbell | I71: Experience | J71: 3 | S71: Bellsprout
A72: 70 | B72: Weepinbell | C72: 070A | D72: 069A | E72: 069A | F72: Experience | G72: 3 | H72: Victreebel | I72: Stone | J72: - | S72: Weepinbell
A73: 71 | B73: Victreebel | C73: 071A | D73: 069A | E73: 070A | F73: Stone | G73: - | H73: - | I73: - | J73: - | S73: Victreebel
A74: 72 | B74: Tentacool | C74: 072A | D74: 072A | E74: - | F74: - | G74: - | H74: Tentacruel | I74: Experience | J74: 4 | S74: Tentacool
A75: 73 | B75: Tentacruel | C75: 073A | D75: 072A | E75: 072A | F75: Experience | G75: 4 | H75: - | I75: - | J75: - | S75: Tentacruel
A76: 74 | B76: Geodude | C76: 074A | D76: 074A | E76: - | F76: - | G76: - | H76: Graveler | I76: Experience | J76: 3 | S76: Geodude
A77: 75 | B77: Graveler | C77: 075A | D77: 074A | E77: 074A | F77: Experience | G77: 3 | H77: Golem | I77: Experience | J77: 5 | S77: Graveler
A78: 76 | B78: Golem | C78: 076A | D78: 074A | E78: 075A | F78: Experience | G78: 5 | H78: - | I78: - | J78: - | S78: Golem
A79: 77 | B79: Ponyta | C79: 077A | D79: 077A | E79: - | F79: - | G79: - | H79: Rapidash | I79: Experience | J79: 5 | S79: Ponyta
A80: 78 | B80: Rapidash | C80: 078A | D80: 077A | E80: 077A | F80: Experience | G80: 5 | H80: - | I80: - | J80: - | S80: Rapidash
A81: 79 | B81: Slowpoke | C81: 079A | D81: 079A | E81: - | F81: - | G81: - | H81: Slowbro | I81: Stone | J81: - | S81: Slowpoke
A82: 80 | B82: Slowbro | C82: 080A | D82: 079A | E82: 079A | F82: Stone | G82: - | H82: - | I82: - | J82: - | S82: Slowbro
A83: 81 | B83: Magnemite | C83: 081A | D83: 081A | E83: - | F83: - | G83: - | H83: Magneton | I83: Experience | J83: 4 | S83: Magnemite
A84: 82 | B84: Magneton | C84: 082A | D84: 081A | E84: 081A | F84: Experience | G84: 4 | H84: - | I84: - | J84: - | S84: Magneton
A85: 83 | B85: Farfetch'd | C85: 083A | D85: 083A | E85: - | F85: - | G85: - | H85: - | I85: - | J85: - | S85: Farfetch'd
A86: 84 | B86: Doduo | C86: 084A | D86: 084A | E86: - | F86: - | G86: - | H86: Dodrio | I86: Experience | J86: 4 | S86: Doduo
A87: 85 | B87: Dodrio | C87: 085A | D87: 084A | E87: 084A | F87: Experience | G87: 4 | H87: - | I87: - | J87: - | S87: Dodrio
A88: 86 | B88: Seel | C88: 086A | D88: 086A | E88: - | F88: - | G88: - | H88: Dewgong | I88: Experience | J88: 4 | S88: Seel
A89: 87 | B89: Dewgong | C89: 087A | D89: 086A | E89: 086A | F89: Experience | G89: 4 | H89: - | I89: - | J89: - | S89: Dewgong
A90: 88 | B90: Grimer | C90: 088A | D90: 088A | E90: - | F90: - | G90: - | H90: Muk | I90: Experience | J90: 4 | S90: Grimer
A91: 89 | B91: Muk | C91: 089A | D91: 088A | E91: 088A | F91: Experience | G91: 4 | H91: - | I91: - | J91: - | S91: Muk
A92: 90 | B92: Shellder | C92: 090A | D92: 090A | E92: - | F92: - | G92: - | H92: Cloyster | I92: Stone | J92: - | S92: Shellder
A93: 91 | B93: Cloyster | C93: 091A | D93: 090A | E93: 090A | F93: Stone | G93: - | H93: - | I93: - | J93: - | S93: Cloyster
A94: 92 | B94: Gastly | C94: 092A | D94: 092A | E94: - | F94: - | G94: - | H94: Haunter | I94: Experience | J94: 3 | S94: Gastly
A95: 93 | B95: Haunter | C95: 093A | D95: 092A | E95: 092A | F95: Experience | G95: 3 | H95: Gengar | I95: Experience | J95: 5 | S95: Haunter
A96: 94 | B96: Gengar | C96: 094A | D96: 092A | E96: 093A | F96: Experience | G96: 5 | H96: - | I96: - | J96: - | S96: Gengar
A97: 95 | B97: Onix | C97: 095A | D97: 095A | E97: - | F97: - | G97: - | H97: - | I97: - | J97: - | S97: Onix
A98: 96 | B98: Drowzee | C98: 096A | D98: 096A | E98: - | F98: - | G98: - | H98: Hypno | I98: Experience | J98: 3 | S98: Drowzee
A99: 97 | B99: Hypno | C99: 097A | D99: 096A | E99: 096A | F99: Experience | G99: 3 | H99: - | I99: - | J99: - | S99: Hypno
A100: 98 | B100: Krabby | C100: 098A | D100: 098A | E100: - | F100: - | G100: - | H100: Kingler | I100: Experience | J100: 3 | S100: Krabby
...

Sheet Habilidades
A1: Code | B1: Habilidad | C1: Tipo | D1: Descripción
A2: H100 | B2: ¡Al ring! | C2: T | D2: En un duelo, si tienes al usuario de la habilidad en el equipo, puedes decidir que Pokémon usará tu contrincante.
A3: H160 | B3: ¡Bingo! | C3: T | D3: Permite jugar al juego del casino sin necesidad de gastar dinero.
A4: H064 | B4: Aclimatación | C4: T | D4: En ruta terrestre, puedes tratar la casilla en la que has caído como si se tratase de una casilla de Encuentro Pokémon. 1 turno de recarga.
A5: H134 | B5: Agallas | C5: C | D5: Si sus PS llegan a la mitad, aumenta su Ataque en un nivel y su Velocidad en dos niveles.
A6: H015 | B6: Alas vendaval | C6: C | D6: Si el usuario utiliza un movimiento de tipo volador, siempre golpea primero.
A7: H127 | B7: Alborotador | C7: T | D7: El usuario de la habilidad solo puede evolucionar saliendo victorioso en un combate Pokémon.
A8: H035 | B8: Allanamiento | C8: T | D8: Cuándo un jugador rival juega una carta de evento, puedes activarla tu también. Recaga 2 turnos.
A9: H072 | B9: Amistoso | C9: T | D9: Si un Pokémon con esta habilidad está en el equipo, al finalizar un combate todos los participantes recuperan todos sus PS.
A10: H147 | B10: Anticipación | C10: T | D10: Si sacas un 6 durante una tirada de movimiento, el usuario de la habilidad evoluciona directamente.
A11: H145 | B11: Apagón | C11: T | D11: Un rival a tu elección perderá su siguiente turno (ignora habilidades u objetos que protejan al rival). No se puede aplicar al mismo rival dos veces seguidas. Recarga 2 turnos.
A12: H005 | B12: Arrojo | C12: C | D12: Aumenta en un nivel el Ataque y el Ataque Especial del usuario si se enfrenta a un Pokémon contra el que presenta debilidad de tipo.
... A174: H092 | B174: Zombie | C174: C | D174: Si el usuario recibe un golpe físico en combate, el Pokémon agresor pasa a estar somnoliento.

Sheet Moves
A1: Movimiento | B1: Tipo | C1: Descripción | D1: DMG | E1: BONUS | F1: CRITICAL | G1: 1HIT ACC. | H1: REPEAT | I1: MIN | J1: MAX | K1: STATUS | L1: P1 | M1: CONDITION | N1: P2 | O1: BATTLE | P1: P3 | Q1: PRIORITY | R1: P4 | S1: ATQ | T1: P5 | U1: SPD | V1: P6 | W1: DEF | X1: P7 | Y1: HEALFIX | Z1: HEALXCENT | AA1: DMGDEALT | AB1: DMGTKN | AC1: HEALSTAT | AD1: ATQ | AE1: P8 | AF1: SPD | AG1: P9 | AH1: DEF | AI1: P10 | AJ1: AUTOSTAT | AK1: P11
A2: A bocajarro | D2: Yes
A3: Absorbefuerza | D3: No
A4: Absorber | B4: Planta | C4: Heal +1HP | D4: Yes | F4: 0.1 | G4: 0.9 | AA4: 0.1
A5: Ácido | B5: Veneno | C5: <10% PSN | D5: Yes
A6: Acoso | D6: Yes
A7: Acróbata | D7: Yes
A8: Acua cola | B8: Agua | C8: - | D8: Yes | F8: 0.1 | G8: 0.9 | Q8: 0
A9: Acua jet | B9: Agua | C9: Priority +1 | D9: Yes | F9: 0.1 | G9: 0.9 | Q9: 1
A10: Adaptación | D10: Yes
A11: Aerochorro | D11: Yes
A12: Afilagarras | D12: No
A13: Agarre | B13: Normal | C13: TRAPPED | D13: Yes | F13: 0.2 | G13: 0.9 | M13: TRP | N13: 1
A14: Aguijón letal | B14: Bicho | C14: AL DERROTAR A UN ENEMIGO SUBE ATAQUE EN 2 NV | D14: Yes | F14: 0.1 | G14: 0.9 | Q14: 0
A15: Ala bis | B15: Volador | C15: Hit again if dice result = 5/6 (x2 max). No CRT | D15: Yes
A16: Ala de acero | D16: Yes
A17: Alboroto | D17: Yes
A18: Aligerar | B18: Acero | C18: No DMG. User speed +6. | D18: No | F18: 0.1 | G18: 1 | Q18: 0 | AF18: 6 | AG18: 1
A19: Alto voltaje | D19: Yes
A20: Alud | D20: Yes
A21: Amortiguador | B21: Normal | C21: No DMG. Heal +10HP | D21: No | F21: No | G21: 1 | Z21: 0.5
A22: Anulación | B22: Normal | C22: Foe can't use last move (only one move) | D22: No | F22: No | G22: 1
A23: Arañazo | B23: Normal | C23: - | D23: Yes | F23: 0.1 | G23: 0.9
A24: Arenas ardientes | B24: Tierra | C24: DMG. <50% foe BRN. | D24: Yes
A25: Aromaterapia | B25: Planta | C25: No DMG. Heal status all team | D25: No | F25: No | G25: 1 | AC25: ALL
A26: Arrumaco | D26: Yes
A27: Ascuas | B27: Fuego | C27: <10% BRN | D27: Yes | F27: 0.1 | G27: 0.9 | K27: BRN | L27: 0.1
A28: At. Arena | D28: Yes
A29: At. Rápido | B29: Normal | C29: Priority +1 | D29: Yes | F29: 0.1 | G29: 0.9 | Q29: 1
A30: Atadura | D30: Yes
A31: Ataque aéreo | B31: Volador | C31: Priority +1 | D31: Yes
A32: Ataque ala | B32: Volador | C32: - | D32: Yes
A33: Ataque furia | B33: Normal | C33: Hit again if dice result = 6 (x5 max). No CRT | D33: Yes | E33: 0.5 | F33: 0.1 | G33: 0.7
A34: Atracción | D34: No
A35: Aullido | D35: No
A36: Autodestrucción | B36: Normal | C36: El usuario explota y se debilita causando el x2 DMG al oponente. | D36: Yes | E36: 2 | F36: 0.1 | G36: 1 | AB36: 1
A37: Avalancha | B37: Roca | C37: <20% foe flinch | D37: Yes
A38: Batido | D38: No
A39: Beso amoroso | D39: No
A40: Beso drenaje | D40: Yes
A41: Beso dulce | D41: No
A42: Bilis | D42: Yes
A43: Bofetón Lodo | B43: Tierra | C43: - | D43: Yes
A44: Bola de hielo | D44: Yes
A45: Bola de polen | D45: Yes
A46: Bola sombra | B46: Fantasma | C46: prob bajar def | D46: Yes | F46: 0.1 | G46: 0.9 | W46: -1 | X46: 0.1
A47: Bola voltio | D47: Yes
A48: Bomba ácida | B48: Veneno | C48: DMG. Foe hability desactivated. | D48: Yes
A49: Bomba fango | B49: Tierra | C49: - | D49: Yes
A50: Bomba germen | D50: Yes
A51: Bomba imán | B51: Acero | C51: - | D51: Yes | F51: 0.1 | G51: 0.9 | Q51: 0
A52: Bomba lodo | B52: Veneno | C52: <20% PSN | D52: Yes
A53: Bostezo | D53: No
A54: Bote | D54: Yes
A55: Brillo mágico | D55: Yes
A56: Burbuja | B56: Agua | C56: SPD reduction 20% | D56: Yes | F56: 0.1 | G56: 0.9 | Q56: 0 | U56: -1 | V56: 0.2
A57: Cabeza de hierro | D57: Yes
A58: Cabezazo zen | B58: Psíquico | C58: <10% foe flinch | D58: Yes | F58: 0.1 | G58: 0.9 | M58: FNC | N58: 0.1
A59: Calcinación | D59: Yes
A60: Canon | D60: Yes
A61: Canto | B61: Normal | C61: No DMG. <60% SLP | D61: No | F61: No | G61: 0.6 | K61: SLP | L61: 0.6
A62: Canto helado | B62: Hielo | C62: Priority +1 | D62: Yes | F62: 0.1 | G62: 0.9 | Q62: 1
A63: Carámbano | B63: Hielo | C63: Hit again if dice result = 6 (x5 max). No CRT | D63: Yes | E63: 0.75 | F63: No | G63: 0.7 | Q63: 0
A64: Carantoña | B64: Hada | C64: HIGH CRT | D64: Yes | F64: 0.3 | G64: 0.8 | Q64: 0
A65: Carga dragón | D65: Yes
A66: Carga tóxica | B66: Veneno | C66: <10% PSN. If foe PSN damage x2 | D66: Yes
A67: Cascada | B67: Agua | C67: <20% foe flinch | D67: Yes | F67: 0.1 | G67: 0.9 | M67: FNC | N67: 0.2 | Q67: 0
A68: Chispa | B68: Eléctrico | C68: <20% PAR | D68: Yes | F68: 0.1 | G68: 0.9 | K68: PAR | L68: 0.2 | Q68: 0
A69: Chispazo | B69: Eléctrico | C69: <30% PAR | D69: Yes | F69: 0.1 | G69: 0.9 | K69: PAR | L69: 0.3 | Q69: 0
A70: Chupavidas | B70: Bicho | C70: Heal +2HP | D70: Yes | F70: 0.1 | G70: 0.9 | Q70: 0 | Z70: 0.5
A71: Ciclón | B71: Dragón | C71: <10% foe flinch | D71: Yes | F71: 0.1 | G71: 0.9 | M71: FNC | N71: 0.1
A72: Cola dragón | D72: Yes
A73: Cola férrea | B73: Acero | C73: <10% foe flinch | D73: Yes | F73: 0.1 | G73: 0.9 | M73: FNC | N73: 0.1 | Q73: 0
A74: Colm. ígneo | B74: Fuego | C74: <10% BRN | D74: Yes | F74: 0.2 | G74: 0.9 | K74: BRN | L74: 0.1
A75: Colm. Rayo | B75: Eléctrico | C75: <10% PAR | D75: Yes | F75: 0.2 | G75: 0.9 | K75: PAR | L75: 0.1 | Q75: 0
A76: Colm. Veneno | B76: Veneno | C76: <10% PSN | D76: Yes
A77: Come sueños | B77: Psíquico | C77: Only works if foe SLP. Heal +6HP | D77: Yes | F77: 0.1 | G77: 0.9 | AA77: 0.7
A78: Cometa draco | B78: Dragón | C78: Hace el doble de daño, pero el próximo turno el PKMN no puede atacar. | D78: Yes | E78: 2 | F78: 0.1 | G78: 0.8 | O78: RCH | P78: 1
A79: Concha filo | B79: Agua | C79: Critical aumento | D79: Yes | F79: 0.2 | G79: 0.9 | Q79: 0
A80: Confusión | B80: Psíquico | C80: <10% CNF | D80: Yes | F80: 0.1 | G80: 0.9 | M80: CNF | N80: 0.1
A81: Constricción | B81: Normal | C81: Foe cant switch | D81: Yes | F81: 0.1 | G81: 0.9 | M81: TRP | N81: 1
A82: Contraataque | B82: Lucha | C82: Prioridad -1. Golpe recibido hace la mitad de daño, contraataca haciendo el mismo daño al rival. | D82: Yes | F82: No | G82: 1
A83: Copión | B83: Normal | C83: Use one of foe's moves | D83: No | F83: No | G83: 1
A84: Cornada | B84: Normal | C84: - | D84: Yes | F84: 0.1 | G84: 0.9
A85: Corte furia | B85: Bicho | C85: Repeat move = power +1 | D85: Yes | F85: 0.1 | G85: 0.9 | Q85: 0
A86: Cuerno certero | D86: Yes
A87: Cuerpo pesado | D87: Yes
A88: Danza aleteo | B88: Bicho | C88: DMG. User speed +1. | D88: Yes | F88: 0.1 | G88: 0.9 | AD88: 1 | AE88: 1 | AF88: 1 | AG88: 1 | AJ88: THR | AK88: 1
A89: Danza dragón | B89: Dragón | C89: No DMG. User attack and speed +1. | D89: No | AD89: 1 | AE89: 1 | AF89: 1 | AG89: 1
A90: Danza espada | B90: Normal | C90: No DMG. UserATQ +4 | D90: No | F90: No | G90: 1 | AD90: 3
A91: Danza pétalo | B91: Planta | C91: DMG. User attack +1. | D91: Yes | F91: 0.1 | G91: 0.9 | AD91: 1 | AE91: 1 | AF91: 1 | AG91: 1 | AJ91: THR | AK91: 1
A92: Defensa férrea | B92: Acero | C92: Los ataques enemigos hacen -4 de daño (un uso) | D92: No | F92: 0.1 | G92: 1 | Q92: 0 | AH92: 3 | AI92: 1
A93: Demolición | B93: Lucha | C93: break defense changes | D93: Yes | F93: 0.1 | G93: 0.9
A94: Derribo | D94: Yes
A95: Desarme | B95: Siniestro | C95: Remove foe held item during the battle. | D95: Yes
A96: Desarrollo | D96: No
A97: Descanso | B97: Normal | C97: No DMG. Heal All HP + cure status + put PKMN to SLP (2 turns) | D97: No | F97: No | G97: 1 | Z97: 1 | AJ97: SLP | AK97: 1
A98: Deseo | D98: No
A99: Deseo cura | B99: Psíquico | C99: Heal one ally if dice result = 6 | D99: No | F99: No | G99: 0.5
A100: Deslumbrar | B100: Normal | C100: No DMG. <70% PAR | D100: No | F100: No | G100: 1 | K100: PAR | L100: 0.7
...

Sheet Movimientos
A1: Movimiento | B1: Tipo | C1: Descripción | D1: DMG | E1: BONUS | F1: CRITICAL | G1: 1HIT ACC. | H1: REPEAT | I1: MIN | J1: MAX | K1: STATUS | L1: P1 | M1: CONDITION | N1: P2 | O1: BATTLE | P1: P3 | Q1: PRIORITY | R1: P4 | S1: ATQ | T1: P5 | U1: SPD | V1: P6 | W1: DEF | X1: P7 | Y1: HEALFIX | Z1: HEALXCENT | AA1: DMGDEALT | AB1: DMGTKN | AC1: HEALSTAT | AD1: ATQ | AE1: P8 | AF1: SPD | AG1: P9 | AH1: DEF | AI1: P10 | AJ1: AUTOSTAT | AK1: P11
A2: A bocajarro | D2: Yes
A3: Absorbefuerza | D3: No
A4: Absorber | B4: Planta | C4: Heal +1HP | D4: Yes | F4: 0.1 | G4: 0.9 | AA4: 0.1
A5: Ácido | B5: Veneno | C5: <10% PSN | D5: Yes
A6: Acoso | D6: Yes
A7: Acróbata | D7: Yes
A8: Acua cola | B8: Agua | C8: - | D8: Yes | F8: 0.1 | G8: 0.9 | Q8: 0
A9: Acua jet | B9: Agua | C9: Priority +1 | D9: Yes | F9: 0.1 | G9: 0.9 | Q9: 1
A10: Adaptación | D10: Yes
A11: Aerochorro | D11: Yes
A12: Afilagarras | D12: No
A13: Agarre | B13: Normal | C13: TRAPPED | D13: Yes | F13: 0.2 | G13: 0.9 | M13: TRP | N13: 1
A14: Aguijón letal | B14: Bicho | C14: AL DERROTAR A UN ENEMIGO SUBE ATAQUE EN 2 NV | D14: Yes | F14: 0.1 | G14: 0.9 | Q14: 0
A15: Ala bis | B15: Volador | C15: Hit again if dice result = 5/6 (x2 max). No CRT | D15: Yes
A16: Ala de acero | D16: Yes
A17: Alboroto | D17: Yes
A18: Aligerar | B18: Acero | C18: No DMG. User speed +6. | D18: No | F18: 0.1 | G18: 1 | Q18: 0 | AF18: 6 | AG18: 1
A19: Alto voltaje | D19: Yes
A20: Alud | D20: Yes
A21: Amortiguador | B21: Normal | C21: No DMG. Heal +10HP | D21: No | F21: No | G21: 1 | Z21: 0.5
A22: Anulación | B22: Normal | C22: Foe can't use last move (only one move) | D22: No | F22: No | G22: 1
A23: Arañazo | B23: Normal | C23: - | D23: Yes | F23: 0.1 | G23: 0.9
A24: Arenas ardientes | B24: Tierra | C24: DMG. <50% foe BRN. | D24: Yes
A25: Aromaterapia | B25: Planta | C25: No DMG. Heal status all team | D25: No | F25: No | G25: 1 | AC25: ALL
A26: Arrumaco | D26: Yes
A27: Ascuas | B27: Fuego | C27: <10% BRN | D27: Yes | F27: 0.1 | G27: 0.9 | K27: BRN | L27: 0.1
A28: At. Arena | D28: Yes
A29: At. Rápido | B29: Normal | C29: Priority +1 | D29: Yes | F29: 0.1 | G29: 0.9 | Q29: 1
A30: Atadura | D30: Yes
A31: Ataque aéreo | B31: Volador | C31: Priority +1 | D31: Yes
A32: Ataque ala | B32: Volador | C32: - | D32: Yes
A33: Ataque furia | B33: Normal | C33: Hit again if dice result = 6 (x5 max). No CRT | D33: Yes | E33: 0.5 | F33: 0.1 | G33: 0.7
A34: Atracción | D34: No
A35: Aullido | D35: No
A36: Autodestrucción | B36: Normal | C36: El usuario explota y se debilita causando el x2 DMG al oponente. | D36: Yes | E36: 2 | F36: 0.1 | G36: 1 | AB36: 1
A37: Avalancha | B37: Roca | C37: <20% foe flinch | D37: Yes
A38: Batido | D38: No
A39: Beso amoroso | D39: No
A40: Beso drenaje | D40: Yes
A41: Beso dulce | D41: No
A42: Bilis | D42: Yes
A43: Bofetón Lodo | B43: Tierra | C43: - | D43: Yes
A44: Bola de hielo | D44: Yes
A45: Bola de polen | D45: Yes
A46: Bola sombra | B46: Fantasma | C46: prob bajar def | D46: Yes | F46: 0.1 | G46: 0.9 | W46: -1 | X46: 0.1
A47: Bola voltio | D47: Yes
A48: Bomba ácida | B48: Veneno | C48: DMG. Foe hability desactivated. | D48: Yes
A49: Bomba fango | B49: Tierra | C49: - | D49: Yes
A50: Bomba germen | D50: Yes
A51: Bomba imán | B51: Acero | C51: - | D51: Yes | F51: 0.1 | G51: 0.9 | Q51: 0
A52: Bomba lodo | B52: Veneno | C52: <20% PSN | D52: Yes
A53: Bostezo | D53: No
A54: Bote | D54: Yes
A55: Brillo mágico | D55: Yes
A56: Burbuja | B56: Agua | C56: SPD reduction 20% | D56: Yes | F56: 0.1 | G56: 0.9 | Q56: 0 | U56: -1 | V56: 0.2
A57: Cabeza de hierro | D57: Yes
A58: Cabezazo zen | B58: Psíquico | C58: <10% foe flinch | D58: Yes | F58: 0.1 | G58: 0.9 | M58: FNC | N58: 0.1
A59: Calcinación | D59: Yes
A60: Canon | D60: Yes
A61: Canto | B61: Normal | C61: No DMG. <60% SLP | D61: No | F61: No | G61: 0.6 | K61: SLP | L61: 0.6
A62: Canto helado | B62: Hielo | C62: Priority +1 | D62: Yes | F62: 0.1 | G62: 0.9 | Q62: 1
A63: Carámbano | B63: Hielo | C63: Hit again if dice result = 6 (x5 max). No CRT | D63: Yes | E63: 0.75 | F63: No | G63: 0.7 | Q63: 0
A64: Carantoña | B64: Hada | C64: HIGH CRT | D64: Yes | F64: 0.3 | G64: 0.8 | Q64: 0
A65: Carga dragón | D65: Yes
A66: Carga tóxica | B66: Veneno | C66: <10% PSN. If foe PSN damage x2 | D66: Yes
A67: Cascada | B67: Agua | C67: <20% foe flinch | D67: Yes | F67: 0.1 | G67: 0.9 | M67: FNC | N67: 0.2 | Q67: 0
A68: Chispa | B68: Eléctrico | C68: <20% PAR | D68: Yes | F68: 0.1 | G68: 0.9 | K68: PAR | L68: 0.2 | Q68: 0
A69: Chispazo | B69: Eléctrico | C69: <30% PAR | D69: Yes | F69: 0.1 | G69: 0.9 | K69: PAR | L69: 0.3 | Q69: 0
A70: Chupavidas | B70: Bicho | C70: Heal +2HP | D70: Yes | F70: 0.1 | G70: 0.9 | Q70: 0 | Z70: 0.5
A71: Ciclón | B71: Dragón | C71: <10% foe flinch | D71: Yes | F71: 0.1 | G71: 0.9 | M71: FNC | N71: 0.1
A72: Cola dragón | D72: Yes
A73: Cola férrea | B73: Acero | C73: <10% foe flinch | D73: Yes | F73: 0.1 | G73: 0.9 | M73: FNC | N73: 0.1 | Q73: 0
A74: Colm. ígneo | B74: Fuego | C74: <10% BRN | D74: Yes | F74: 0.2 | G74: 0.9 | K74: BRN | L74: 0.1
A75: Colm. Rayo | B75: Eléctrico | C75: <10% PAR | D75: Yes | F75: 0.2 | G75: 0.9 | K75: PAR | L75: 0.1 | Q75: 0
A76: Colm. Veneno | B76: Veneno | C76: <10% PSN | D76: Yes
A77: Come sueños | B77: Psíquico | C77: Only works if foe SLP. Heal +6HP | D77: Yes | F77: 0.1 | G77: 0.9 | AA77: 0.7
A78: Cometa draco | B78: Dragón | C78: Hace el doble de daño, pero el próximo turno el PKMN no puede atacar. | D78: Yes | E78: 2 | F78: 0.1 | G78: 0.8 | O78: RCH | P78: 1
A79: Concha filo | B79: Agua | C79: Critical aumento | D79: Yes | F79: 0.2 | G79: 0.9 | Q79: 0
A80: Confusión | B80: Psíquico | C80: <10% CNF | D80: Yes | F80: 0.1 | G80: 0.9 | M80: CNF | N80: 0.1
A81: Constricción | B81: Normal | C81: Foe cant switch | D81: Yes | F81: 0.1 | G81: 0.9 | M81: TRP | N81: 1
A82: Contraataque | B82: Lucha | C82: Prioridad -1. Golpe recibido hace la mitad de daño, contraataca haciendo el mismo daño al rival. | D82: Yes | F82: No | G82: 1
A83: Copión | B83: Normal | C83: Use one of foe's moves | D83: No | F83: No | G83: 1
A84: Cornada | B84: Normal | C84: - | D84: Yes | F84: 0.1 | G84: 0.9
A85: Corte furia | B85: Bicho | C85: Repeat move = power +1 | D85: Yes | F85: 0.1 | G85: 0.9 | Q85: 0
A86: Cuerno certero | D86: Yes
A87: Cuerpo pesado | D87: Yes
A88: Danza aleteo | B88: Bicho | C88: DMG. User speed +1. | D88: Yes | F88: 0.1 | G88: 0.9 | AD88: 1 | AE88: 1 | AF88: 1 | AG88: 1 | AJ88: THR | AK88: 1
A89: Danza dragón | B89: Dragón | C89: No DMG. User attack and speed +1. | D89: No | AD89: 1 | AE89: 1 | AF89: 1 | AG89: 1
A90: Danza espada | B90: Normal | C90: No DMG. UserATQ +4 | D90: No | F90: No | G90: 1 | AD90: 3
A91: Danza pétalo | B91: Planta | C91: DMG. User attack +1. | D91: Yes | F91: 0.1 | G91: 0.9 | AD91: 1 | AE91: 1 | AF91: 1 | AG91: 1 | AJ91: THR | AK91: 1
A92: Defensa férrea | B92: Acero | C92: Los ataques enemigos hacen -4 de daño (un uso) | D92: No | F92: 0.1 | G92: 1 | Q92: 0 | AH92: 3 | AI92: 1
A93: Demolición | B93: Lucha | C93: break defense changes | D93: Yes | F93: 0.1 | G93: 0.9
A94: Derribo | D94: Yes
A95: Desarme | B95: Siniestro | C95: Remove foe held item during the battle. | D95: Yes
A96: Desarrollo | D96: No
A97: Descanso | B97: Normal | C97: No DMG. Heal All HP + cure status + put PKMN to SLP (2 turns) | D97: No | F97: No | G97: 1 | Z97: 1 | AJ97: SLP | AK97: 1
A98: Deseo | D98: No
A99: Deseo cura | B99: Psíquico | C99: Heal one ally if dice result = 6 | D99: No | F99: No | G99: 0.5
A100: Deslumbrar | B100: Normal | C100: No DMG. <70% PAR | D100: No | F100: No | G100: 1 | K100: PAR | L100: 0.7
...

Sheet Habs
B2: Habilidad | C2: Tipo | D2: Descripción
B3: ¡Al ring! | C3: T | D3: En un duelo, si tienes a Hitmonchan en el equipo, decides que PKMN usa tu contrincante.
B4: Aclimatación | C4: T | D4: Puedes tratar la casilla en la que has caído como si se tratase de una casilla de "hierba alta". 1 turno de recarga.
B5: Afortunado | C5: T | D5: Al caer en una casilla de objetos clave puedes coger dos cartas y decidir cuál te quedas.
B6: Agallas | C6: C | D6: Su poder de ataque aumenta en +3 si sufre un problema de estado.
B7: Ágil | C7: T | D7: Puedes doblar el resultado de una tirada de movimiento en tierra firme. Recarga 2 turnos.
B8: Alas vendaval | C8: C | D8: Los ataques de tipo volador siempre van primero.
B9: Alborotador | C9: T | D9: Magikarp solo puede evolucionar saliendo victorioso en un combate. Para ello, puedes enfrentarte a los PKMN salvajes que te aparezcan.
B10: Allanamiento | C10: T | D10: Cuándo un jugador juega una carta de evento puedes jugarla tu también. Recaga 2 turnos.
B11: Amistoso | C11: T | D11: Al finalizar cualquier tipo de combate todo tu equipo sanará.
B12: Anticipación | C12: T | D12: Si alguna vez el resultado de una tirada de movimiento es 6, Dratini evoluciona directamente.
B13: Aspirante | C13: T | D13: Puedes utilizar un PKMN adicional en las batallas contra líderes de gimnasio.
... B45: Fuga | C45: C | D45: El PKMN puede retirarse en cualquier momento durante un duelo. No hay ganadores.
B46: Gas reactivo | C46: C | D46: Anula las habilidades de los demás PKMN durante el combate. Esto afecta a PKMN rivales + propio equipo. Solo funciona si Koffing/Weezing participan en el combate. | E46: *
B47: Guardián | C47: C | D47: Ivysaur aumenta su poder de ataque en +2 si ninguno de los PKMN en tu equipo ha llegado a su última fase evolutiva.
B48: Hacker | C48: T | D48: Evoluciona cualquier PKMN a su máxima etapa evolutiva sin necesidad de objetos
B49: Huraño | C49: C | D49: Charmeleon aumenta su poder de ataque en +2 si no tienes más de 3 PKMN en tu equipo.
B50: Hurto | C50: C | D50: Cuando tu oponente utiliza un objeto en combate, Ninetales roba los efectos.
B51: Iluminación | C51: T | D51: Al evolucionar un PKMN puedes evolucionarlo directamente a su máxima etapa evolutiva. Recarga 3 turnos.
B52: Ilusión | C52: C | D52: El PKMN puede hacer que el rival repita su tirada de ataque una vez por turno.
B53: Imán | C53: C | D53: Por cada Magnemite / Magneton en tu equipo aumenta su poder de ataque en +2.
B54: Imitación | C54: T | D54: Puedes moverte el mismo número de casillas que el jugador anterior. Recarga 1 turno.
B55: Impasible | C55: T | D55: En un duelo, si tienes a Tentacool/Tentacruel en el equipo, tus oponentes nunca podrán elegir que PKMN has de utilizar. | E55: *
B56: Indefenso | C56: C | D56: Las tiradas de ataque nunca fallan. Sacar un 1 equivale a sacar un 2.
B57: Intimidación | C57: C | D57: Reduce el ataque de todos los PKMN a los que se enfrenta en -2.
B58: Intrépido | C58: C | D58: Si el PKMN es más rápido, todos sus ataque son críticos.
B59: Irascible | C59: C | D59: Aumenta su poder de ataque en +4 si recibe un golpe crítico.
B60: Jaqueca | C60: C | D60: Si su movimiento falla, Psyduck enloquece y duplica su poder de ataque durante todo el combate.
B61: Jugón | C61: T | D61: Cuándo un duelo tenga lugar puedes apostar por quien saldrá victorioso. Si aciertas puedes tomar una carta de objeto. Recarga 1 turno.
B62: Justiciero | C62: T | D62: Protege al jugador de cualquier intento de robo de objetos / cartas por parte de otros jugadores.
B63: Ladrón | C63: T | D63: Cuándo el team rocket roba un objeto a un rival, recibes el objeto robado.
B64: Lealtad | C64: C | D64: Si tienes a Nidoking y a Nidoqueen en tu equipo, el poder de ataque de ambos aumenta en +2.
B65: Mafioso | C65: T | D65: Cuándo el team rocket roba un objeto o un PKMN a un rival, recibes el objeto o el PKMN robado.
B66: Marsupial | D66: Puedes llevar contigo hasta 8 pokémon (en vez de 6). | E66: *
B67: Miedoso | C67: C | D67: Charmander aumenta su ataque +2 si es el único PKMN en el equipo.
B68: Mudar | C68: C | D68: Tu PKMN tiene un 50% de probabilidades de librarse de los problemas de estado al finalizar cada turno. | E68: *
B69: Mutación | C69: T | D69: Al evolucionar a eevee tira un dado para determinar su evolución: 1/2 = jolteon; 3/4 = flareon; 5/6 = vaporeon.
B70: Nadador | C70: T | D70: Permite moverse el doble de rápido por el agua.
B71: Ojo compuesto | C71: T | D71: Puedes cambiar en cualquier momento el resultado de una tirada de movimiento o captura por el resultado del lado opuesto del dado. Recarga 1 turno. | E71: *
B72: Oráculo | C72: T | D72: Al aterrizar en una casilla de evento, puedes mirar las dos cartas que estén en la parte superior y escoger la que más te convenga (descarta la otra).
B73: Otra vez | C73: T | D73: Puedes volver a tirar el dado de movimiento o de captura. Recarga 2 turnos.
B74: Pantallahumo | C74: T | D74: Puedes elegir no activar una carta de evento. Recarga 1 turno.
B75: Peleón | C75: T | D75: En cualquier momento puedes tomar una casilla de "encuentro PKMN" como si fuera una casilla de duelo.
B76: Pestilente | C76: T | D76: En el momento que quieras puedes descartar dos de tus objetos para volver a tirar el dado de captura en una ruta.
B77: Pies rápidos | C77: T | D77: Puedes modificar el resultado del dado en una tirada de movimiento en +1. Recarga 1 turno. | E77: *
B78: Poder antiguo | C78: T | D78: Puedes repetir cualquier tirada de dado (captura, combate, movimiento…). Recarga 1 turno.
B79: Policía | C79: T | D79: Los asaltos del team rocket no tienen efecto sobre ti.
B80: Predicción | C80: T | D80: Puedes decidir el resultado de tu tirada de movimiento. Recarga 1 turno.
B81: Presión | C81: C | D81: Al usar a Zapdos en combate, todos los PKMN del rival que tengan menos de 7 puntos de ataque pierden inmediatamente.
B82: Primeros auxilios | C82: T | D82: Al acabar un combate todo tu equipo es curado.
B83: Protector | C83: C | D83: Bulbasaur aumenta su poder de ataque en +2 si el resto de los PKMN en tu equipo están en su primera fase evolutiva.
B84: Pura potencia | C84: C | D84: Puedes convertir el efecto secundario de tu ataque en +4 de daño.
B85: Receptor | C85: C | D85: El poseedor adquiere la habilidad de un aliado que caiga debilitado en combate.
B86: Reclamo | C86: T | D86: Si Nidoran (M/H) no tiene un compañero del sexo opuesto, tira un dado al inicio de cada turno. Si sale 2, añádelo a a tu equipo.
B87: Recogida | C87: C | D87: Cuando tu oponente utiliza un objeto en combate, Vulpix también recibe los efectos.
B88: Regateador | C88: T | D88: El coste de las cartas de objeto en tienda se reduce un 50%.
B89: Regeneración | C89: C | D89: Al intercambiar al PKMN durante un combate este recupera el 50% de sus HP máximos.
... B113: Habilidad | C113: Tipo | D113: Descripción
C114: T | D114: En vez de tirar el dado de movimiento puedes moverte una casilla hacia delante o hacia atrás.
B115: Salto | C115: T | D115: En caso de caer en una casilla de evento, duelo o team rocket, puedes saltar a la siguiente casilla.
C116: T | D116: Puedes moverte 3 casillas en cualquier dirección en vez de tirar el dado de movimiento.
D117: Durante un combate, si este PKMN está en el equipo de combate, restaura 2HP a todos sus compañeros al finalizar cada turno.
C118: C | D118: Mientras este PKMN esté en el equipo de combate (pero no combatiendo), puede recibir el daño en lugar de su compañero combatiente.
C119: C | D119: Al usar a "X" en combate, puedes repetir la tirada de ataque.
C121: C | D121: Si eres el jugador con más PKMN debilitados tu PKMN tiene +1 punto de ataque.
C122: C | D122: Si eres el jugador con más PKMN debilitados tu PKMN tiene +2 punto de ataque.
C124: C | D124: Tus ataques tienen un 100% de probabilidades de activar su efecto secundario.
C125: C | D125: X puede repetir una vez por turno la tirada de ataque. Cuenta el valor más alto.
C126: C | D126: Una vez por combate puede realizar el doble de daño.
B127: Cálculo final | C127: C | D127: Potencia el movimiento si es el último en atacar.
B131: Clorofila | C131: C | D131: Si el día que juegas hace un clima soleado, este PKMN aumenta su poder de ataque y su velocidad en +2 (solo funciona de día).
B132: Hedor | C132: T | D132: Los jugadores rivales no podrán situarse en una casilla adyacente a la tuya, teniendo que cesar su acción de movimiento si fuese necesario.
B133: Sacrificio | C133: C | D133: En tu turno de ataque puedes sacrificar a tu PKMN, provocando daño al PKMN rival equivalente a los HP restantes del usuario.
B134: Entusiasmo | C134: C | D134: Disminuye precisión (2 = fallo), pero su poder de ataque aumenta en +4.
B135: Escama especial | C135: C | D135: Reduce el daño recibido en combate a la mitad si sus HP están completos.
B136: Sorpresa | C136: C | D136: Al entrar en combate hace 2 de daño al PKMN rival.
B137: Impulso | C137: C | D137: La velocidad de este PKMN aumenta en +3 cada turno que pasa.
B138: Experto | C138: C | D138: Potencia los movimientos superfeficaces (+2 daño).
B139: Adaptable | C139: C | D139: Potencia los movimientos del mismo tipo que el PKMN (daño +2).
B140: Velo sagrado | C140: C | D140: No puede sufrir problemas de estado.
B141: Espejo mágico | C141: C | D141: Devuelve los problemas de estado al agresor (el PKMN con esta habilidad es inmune a problemas de estado).
... B167: Poltergeist | C167: C | D167: If user has held item, DMG x2.

Sheet MISC
A1: DMG | B1: PERCENT | C1: TYPE DMG | D1: PRIORITY | E1: INCREASE | F1: AMOUNT | I1: 49 | J1: SSS | K1: 4 | M1: 41 | N1: SSS | O1: 4
A2: Yes | B2: 0.1 | C2: BASIC | D2: -3 | E2: -20 | F2: 0.5 | I2: 48 | J2: SSS | K2: 4 | M2: 40 | N2: SSS | O2: 4
A3: No | B3: 0.2 | C3: FIX | D3: -2 | E3: -6 | F3: 0.75 | I3: 47 | J3: SSS | K3: 4 | M3: 39 | N3: SSS | O3: 4
B4: 0.3 | C4: PERCENTAGE | D4: -1 | E4: -4 | F4: 1 | I4: 46 | J4: SSS | K4: 4 | M4: 38 | N4: SS | O4: 4
B5: 0.4 | D5: 0 | E5: -3 | F5: 1.5 | I5: 45 | J5: SSS | K5: 4 | M5: 37 | N5: SS | O5: 3
B6: 0.5 | D6: 1 | E6: -2 | F6: 2 | I6: 44 | J6: SS | K6: 4 | M6: 36 | N6: SS | O6: 3
B7: 0.6 | D7: 2 | E7: -1 | F7: 2.5 | I7: 43 | J7: SS | K7: 4 | M7: 35 | N7: S | O7: 3
B8: 0.7 | D8: 3 | E8: 1 | F8: 3 | I8: 42 | J8: SS | K8: 4 | M8: 34 | N8: S | O8: 3
B9: 0.8 | E9: 2 | F9: 4 | I9: 41 | J9: SS | K9: 4 | M9: 33 | N9: A+ | O9: 3
B10: 0.9 | E10: 3 | F10: 6 | I10: 40 | J10: S | K10: 4 | M10: 32 | N10: A+ | O10: 3
B11: 1 | E11: 4 | F11: 8 | I11: 39 | J11: S | K11: 4 | M11: 31 | N11: A | O11: 3
B12: No | E12: 6 | F12: 10 | I12: 38 | J12: S | K12: 4 | M12: 30 | N12: A | O12: 3
E13: 20 | F13: 12 | I13: 37 | J13: A+ | K13: 3 | M13: 29 | N13: A- | O13: 3
F14: 15 | I14: 36 | J14: A+ | K14: 3 | M14: 28 | N14: A- | O14: 3
F15: 20 | I15: 35 | J15: A+ | K15: 3 | M15: 27 | N15: B+ | O15: 2
F16: 25 | I16: 34 | J16: A | K16: 3 | M16: 26 | N16: B+ | O16: 2
F17: 0.5 | I17: 33 | J17: A | K17: 3 | M17: 25 | N17: B | O17: 2
F18: 0.75 | I18: 32 | J18: A | K18: 3 | M18: 24 | N18: B | O18: 2
F19: 30 | I19: 31 | J19: A- | K19: 3 | M19: 23 | N19: B- | O19: 2
I20: 30 | J20: A- | K20: 3 | M20: 22 | N20: B- | O20: 2
I21: 29 | J21: B+ | K21: 3 | M21: 21 | N21: C+ | O21: 1
I22: 28 | J22: B+ | K22: 3 | M22: 20 | N22: C+ | O22: 1
I23: 27 | J23: B | K23: 2 | M23: 19 | N23: C | O23: 1
I24: 26 | J24: B | K24: 2 | M24: 18 | N24: C | O24: 1
I25: 25 | J25: B- | K25: 2 | M25: 17 | N25: C- | O25: 1
I26: 24 | J26: B- | K26: 2 | M26: 16 | N26: C- | O26: 1
I27: 23 | J27: C+ | K27: 2 | M27: 15 | N27: D | O27: 1
I28: 22 | J28: C+ | K28: 2 | M28: 14 | N28: E | O28: 1
I29: 21 | J29: C | K29: 1 | M29: 13 | N29: F | O29: 1
I30: 20 | J30: C | K30: 1 | M30: 12 | N30: F | O30: 1
I31: 19 | J31: C- | K31: 1
I32: 18 | J32: C- | K32: 1
I33: 17 | J33: D | K33: 1
I34: 16 | J34: D | K34: 1
I35: 15 | J35: E | K35: 1
I36: 14 | J36: E | K36: 1
I37: 13 | J37: E | K37: 1

Sheet Status
A1: Status | B1: Type | C1: Short | D1: Desc. | E1: PROBAB | F1: TURNS | H1: Types
A2: Burn | B2: Permanent | C2: BRN | D2: The burn condition (BRN) inflicts damage every turn and lowers a Pokémon attack stat to it's 75% normal value. The damage taken is equal to 1/12 of the Pokemon HP. | H2: Permanent | I2: A permanent status condition is a status condition that remains outside of battle and after being switched out. It's displayed in the party screen, and the Pokémon's summary. A Pokémon cannot gain a permanent status condition if it's already afflicted by another one.
A3: Paralyzed | B3: Permanent | C3: PAR | D3: The paralysis condition (PAR) reduces the Pokémon's Speed stat and causes it to have a 25% chance of being unable to use a move ("fully paralyzed") when trying to use one. 50% of its normal value | H3: Volatile | I3: A volatile status is a status condition that is inflicted by a move or ability from another Pokémon and will wear off when a Pokémon is switched out of battle or when a battle is over. Many volatile status conditions will also wear off after a number of turns have passed. A Pokémon can be affected by multiple volatile status conditions at a time. A volatile status condition is not indicated by an icon.
A4: Freeze | B4: Permanent | C4: FRZ | D4: The freeze condition (FRZ) causes a Pokémon to be unable to use moves. If a frozen Pokémon is hit by a damaging Fire-type move it will be thawed. The frozen Pokémon has a 30% chance to be thawed at the end of each turn (including the first one). | H4: Battle
A5: Poisoned | B5: Permanent | C5: PSN | D5: The poison condition (PSN) inflicts damage every turn, with the amount of damage increasing each turn. It initially inflicts damage equal to 1/12 of the Pokémon's maximum HP, with the damage inflicted increasing by 1/16 each turn (2/16 on the second turn, 3/16 on the third turn, etc.).
A6: Sleep | B6: Permanent | C6: SLP | D6: The sleep condition (SLP) causes a Pokémon to be unable to use moves, except Snore and Sleep Talk. The minimum and maximum sleep count is 1 turn higher, lasting 2 to 4 turns (probability to awake at the beginning of the turn equal to 25%).If a Pokémon puts itself to sleep using Rest, it will sleep for exactly 2 turns.
A7: Random | B7: Permanent | C7: RND | D7: Can lead to FRZ, BRN or PAR with 1/3 probability.
A8: Altered | B8: Permanent | C8: ALT | D8: Can lead to PSN, Par or SLP with 1/3 probability.
A9: Bound | B9: Volatile | C9: BND | D9: Pokemon takes damage at the end of each turn and cannot switch out or flee. This lasts 2-4 turns (30% probability to unbound at the end of each turn).
A10: Trapped | B10: Volatile | C10: TRP | D10: A Pokémon that can't escape is unable to switch out or flee as long as the Pokémon that trapped it is on the field.
A11: Confusion | B11: Volatile | C11: CNF | D11: The confused condition causes a Pokémon to sometimes hurt itself in its confusion instead of executing a selected move. The chance to hurt itself is 50%; the damage taken is equal to 1/12 of the Pokemon HP. Confusion wears off after 2-5 attacking turns (30% probability). Once the Pokémon switchs or faints the effect dissapear.
A12: Curse | B12: Volatile | C12: CRS | D12: If a Ghost-type Pokémon uses Curse, its target will be afflicted by the cursed condition. A cursed Pokémon takes damage equal to ¼ of its maximum HP every turn. Once the Pokémon switchs or faints the effect dissapear.
A13: Drowsy | B13: Volatile | C13: DRW | D13: At the end of the next turn, the drowsy Pokémon will fall asleep, unless it is already afflicted by a permanent status condition. If a drowsy Pokémon switches out, it loses its drowsiness.
A14: Embargo | B14: Volatile | C14: EMB | D14: A Pokémon under the effect of Embargo is unable to use its held item and its Trainer cannot use items on it. Once the Pokémon switchs or faints the effect dissapear.
A15: Encore | B15: Volatile | C15: ENC | D15: Encore forces the Pokémon to repeat its last attack for 2-5 turns (40% probability to move each turn). Once the Pokémon attacks, the encore effect dissapear. Once the Pokémon switchs or faints the effect dissapear.
A16: Flinch | B16: Volatile | C16: FNC | D16: The flinch status is a one-turn status that prevents a Pokémon from attacking. A Pokémon can only flinch if it is hit by another Pokémon's move before using its move.
... A22: Torment | B22: Volatile | C22: TOR | D22: A tormented Pokémon cannot use the same move twice in a row. If the Pokémon is holding a Choice item it is forced to use Struggle (normal type move) every second turn. Receiving 50% of the damage dealt.
A23: Aqua ring | B23: Battle | C23: AQR
A24: Defense curl | B24: Battle | C24: DFC
A25: Rooting | B25: Battle | C25: ROT
A26: Magic coat | B26: Battle | C26: MGC
A27: Magnetic levitation | B27: Battle | C27: MGL
A28: Mimic | B28: Battle | C28: MMC
A29: Minimize | B29: Battle | C29: MIN
A30: Protection | B30: Battle | C30: PRT
A31: Recharging | B31: Battle | C31: RCH
A32: Invulnerable turn | B32: Battle | C32: INV
A33: Substitute | B33: Battle | C33: SUB
A34: Thrashing | B34: Battle | C34: THR
... A36: Transformed | B36: Battle | C36: TRF

Sheet Estados
A1: Status | B1: Type | C1: Short | D1: Desc. | E1: Efecto.
A2: Envenenado | B2: Permanent | C2: ENV | D2: Un Pokémon envenenado pierde un 12.5% de su PS máximo al final de cada turno. Los Pokémon de tipo Acero son inmunes al veneno. | E2: Un Pokémon envenenado pierde un 1PS al final de cada turno. Su Velocidad se reduce en un nivel. Los Pokémon de tipo Acero y Veneno son inmunes al envenenamiento.
A3: Paralizado | B3: Permanent | C3: PAR | D3: Un Pokémon paralizado puede no atacar en su turno en un 25% de los casos y su Velocidad se reduce en un 50%. Los Pokémon de tipo Eléctrico son inmunes a la parálisis. | E3: Un Pokémon paralizado puede no atacar en su turno en un 30% de los casos. Su Velocidad se reduce en dos niveles. Los Pokémon de tipo Eléctrico son inmunes a la parálisis.
A4: Somnoliento | B4: Permanent | C4: SOM | D4: Un Pokémon somnoliento puede no atacar en su turno en un 25% de los casos y recibe más daño de los movimientos del rival. | E4: Un Pokémon somnoliento puede no atacar en su turno en un 30% de los casos. Su dado de Defensa se reduce en un nivel.
A5: Quemado | B5: Permanent | C5: QUE | D5: Un Pokémon quemado pierde un 6.25% de su PS máximo al final de cada turno, y el daño de sus ataques físicos se reduce en un 50%. | E5: Un Pokémon quemado pierde 1PS al final de cada turno. El dado de Ataque reduce en uno su tamaño. Los Pokémon de tipo Fuego son inmunes a las quemaduras.
A6: Helado | B6: Permanent | C6: CON | D6: Un Pokémon helado pierde un 6.25% de su PS máximo al final de cada turno, y el daño de sus ataques especiales se reduce en un 50%. Los Pokémon de tipo Hielo son inmunes al helamiento. | E6: Un Pokémon helado pierde 1PS al final de cada turno. El dado de Ataque reduce en uno su tamaño. Los Pokémon de tipo Hielo son inmunes al helamiento.
A7: Debilitado | B7: Permanent | C7: DEB | D7: El Pokémon no tiene PS restantes y no puede entrar en combate. | E7: El Pokémon no tiene PS restantes y no puede entrar en combate.
A8: Furioso | B8: Volatile | C8: FUR | D8: El Pokémon enfurece al utilizar un movimiento. Mientras dure este estado, aumenta la potencia de dicho movimiento, pero también el daño que el Pokémon recibe. | E8: El Pokémon enfurece al utilizar un movimiento. Mientras dure este estado, aumenta Ataque y Ataque Especial del usuario en un nivel, pero también baja su Defensa y su Defensa Especial en un nivel.
A9: Confuso | B9: Volatile | C9: CNF | D9: El Pokémon tiene un 50% de probabilidad de dañarse a sí mismo en lugar de ejecutar un movimiento seleccionado. La confusión desaparece en cuanto el usuario es capaz de asestar un golpe, es cambiado o cae debilitado. | E9: El Pokémon tiene un 50% de probabilidad de dañarse a sí mismo (con el resultado de su tirada de ataque) en lugar de ejecutar un movimiento seleccionado. La confusión desaparece en cuanto el usuario es capaz de asestar un golpe, es cambiado o cae debilitado.
A10: Maldito | B10: Volatile | C10: CRS | D10: El Pokémon que se encuentra bajo los efectos de una maldición pierde 1/4HP al final de cada turno. | E10: El Pokémon que se encuentra bajo los efectos de una maldición pierde 2PS al final de cada turno.
A11: Bloqueado | B11: Volatile | C11: EMB | D11: El Pokémon no puede utilizar el objeto que tiene equipado y su entrenador no puede utilizar objetos sobre él. Una vez que el Pokémon es cambiado o cae debilitado, el efecto desaparece. | E11: El Pokémon no puede utilizar el objeto que tiene equipado y su entrenador no puede utilizar objetos sobre él. Una vez que el Pokémon es cambiado o cae debilitado, el efecto desaparece.
A12: Incurable | B12: Volatile | C12: HBK | D12: El Pokémon no puede recuperar HP por ningún método. Una vez que el Pokémon es cambiado o cae debilitado, el efecto desaparece. | E12: El Pokémon no puede recuperar PS por ningún método. Una vez que el Pokémon es cambiado o cae debilitado, el efecto desaparece.
... A22: Infectado | B22: Volatile | C22: SED | D22: Cada turno, un Pokémon infectado pierde 1/12 de sus puntos de vida máximos. El Pokémon que lo infectó se cura en la misma cantidad. Cuando el Pokémon es cambiado o cae debilitado, el efecto desaparece. | E22: Un Pokémon infectado tiene un 50% de probabilidad de recibir 1PS de daño al final de cada turno. El Pokémon que lo infectó se cura en la misma cantidad. Cuando el Pokémon es cambiado o cae debilitado, el efecto desaparece.

Sheet STR-WEAK
A1: TYPE | B1: NOR | C1: FIR | D1: WAT | E1: ELE | F1: GRA | G1: ICE | H1: FIG | I1: POI | J1: GRO | K1: FLY | L1: PSY | M1: BUG | N1: ROC | O1: GHO | P1: DRA | Q1: DAR | R1: STE | S1: FAI | T1: Weak | U1: Resistant | V1: Inmune
A2: NORMAL | B2: - | C2: - | D2: - | E2: - | F2: - | G2: - | H2: W | I2: - | J2: - | K2: - | L2: - | M2: - | N2: - | O2: I | P2: - | Q2: - | R2: - | S2: - | T2: =COUNTIF($B2:$S2,"W") -> 1 | U2: =COUNTIF($B2:$S2,"R") -> 0 | V2: =COUNTIF($B2:$S2,"I") -> 1
A3: NORMAL / FIRE | B3: - | C3: R | D3: W | E3: - | F3: R | G3: R | H3: W | I3: - | J3: W | K3: - | L3: - | M3: R | N3: W | O3: I | P3: - | Q3: - | R3: R | S3: R | T3: =COUNTIF($B3:$S3,"W") -> 4 | U3: =COUNTIF($B3:$S3,"R") -> 6 | V3: =COUNTIF($B3:$S3,"I") -> 1
A4: NORMAL / WATER | B4: - | C4: R | D4: R | E4: W | F4: W | G4: R | H4: W | I4: - | J4: - | K4: - | L4: - | M4: - | N4: - | O4: I | P4: - | Q4: - | R4: R | S4: - | T4: =COUNTIF($B4:$S4,"W") -> 3 | U4: =COUNTIF($B4:$S4,"R") -> 4 | V4: =COUNTIF($B4:$S4,"I") -> 1
A5: NORMAL / ELECTRIC | B5: - | C5: - | D5: - | E5: R | F5: - | G5: - | H5: W | I5: - | J5: W | K5: R | L5: - | M5: - | N5: - | O5: I | P5: - | Q5: - | R5: R | S5: - | T5: =COUNTIF($B5:$S5,"W") -> 2 | U5: =COUNTIF($B5:$S5,"R") -> 3 | V5: =COUNTIF($B5:$S5,"I") -> 1
A6: NORMAL / GRASS | B6: - | C6: W | D6: R | E6: R | F6: R | G6: W | H6: W | I6: W | J6: R | K6: W | L6: - | M6: W | N6: - | O6: I | P6: - | Q6: - | R6: - | S6: - | T6: =COUNTIF($B6:$S6,"W") -> 6 | U6: =COUNTIF($B6:$S6,"R") -> 4 | V6: =COUNTIF($B6:$S6,"I") -> 1
A7: NORMAL / ICE | B7: - | C7: W | D7: - | E7: - | F7: - | G7: R | H7: W | I7: - | J7: - | K7: - | L7: - | M7: - | N7: W | O7: I | P7: - | Q7: - | R7: W | S7: - | T7: =COUNTIF($B7:$S7,"W") -> 4 | U7: =COUNTIF($B7:$S7,"R") -> 1 | V7: =COUNTIF($B7:$S7,"I") -> 1
A8: NORMAL / FIGHTING | B8: - | C8: - | D8: - | E8: - | F8: - | G8: - | H8: W | I8: - | J8: - | K8: W | L8: W | M8: R | N8: R | O8: I | P8: - | Q8: R | R8: - | S8: W | T8: =COUNTIF($B8:$S8,"W") -> 4 | U8: =COUNTIF($B8:$S8,"R") -> 3 | V8: =COUNTIF($B8:$S8,"I") -> 1
A9: NORMAL / POISON | B9: - | C9: - | D9: - | E9: - | F9: R | G9: - | H9: - | I9: R | J9: W | K9: - | L9: W | M9: R | N9: - | O9: I | P9: - | Q9: - | R9: - | S9: R | T9: =COUNTIF($B9:$S9,"W") -> 2 | U9: =COUNTIF($B9:$S9,"R") -> 4 | V9: =COUNTIF($B9:$S9,"I") -> 1
A10: NORMAL / GROUND | B10: - | C10: - | D10: W | E10: I | F10: W | G10: W | H10: W | I10: R | J10: - | K10: - | L10: - | M10: - | N10: R | O10: I | P10: - | Q10: - | R10: - | S10: - | T10: =COUNTIF($B10:$S10,"W") -> 4 | U10: =COUNTIF($B10:$S10,"R") -> 2 | V10: =COUNTIF($B10:$S10,"I") -> 2
A11: NORMAL / FLYING | B11: - | C11: - | D11: - | E11: W | F11: R | G11: W | H11: - | I11: - | J11: I | K11: - | L11: - | M11: R | N11: W | O11: I | P11: - | Q11: - | R11: - | S11: - | T11: =COUNTIF($B11:$S11,"W") -> 3 | U11: =COUNTIF($B11:$S11,"R") -> 2 | V11: =COUNTIF($B11:$S11,"I") -> 2
A12: NORMAL / PSYCHIC | B12: - | C12: - | D12: - | E12: - | F12: - | G12: - | H12: - | I12: - | J12: - | K12: - | L12: R | M12: W | N12: - | O12: I | P12: - | Q12: W | R12: - | S12: - | T12: =COUNTIF($B12:$S12,"W") -> 2 | U12: =COUNTIF($B12:$S12,"R") -> 1 | V12: =COUNTIF($B12:$S12,"I") -> 1
A13: NORMAL / BUG | B13: - | C13: W | D13: - | E13: - | F13: R | G13: - | H13: - | I13: - | J13: R | K13: W | L13: - | M13: - | N13: W | O13: I | P13: - | Q13: - | R13: - | S13: - | T13: =COUNTIF($B13:$S13,"W") -> 3 | U13: =COUNTIF($B13:$S13,"R") -> 2 | V13: =COUNTIF($B13:$S13,"I") -> 1
... A325: FAIRY / STEEL | B325: R | C325: W | D325: - | E325: - | F325: R | G325: R | H325: - | I325: I | J325: W | K325: R | L325: R | M325: R | N325: R | O325: - | P325: I | Q325: R | R325: - | S325: R | T325: =COUNTIF($B325:$S325,"W") -> 2 | U325: =COUNTIF($B325:$S325,"R") -> 9 | V325: =COUNTIF($B325:$S325,"I") -> 2

Sheet STR-WEAK OFFICIAL
A1: TYPE | B1: NOR | C1: FIR | D1: WAT | E1: ELE | F1: GRA | G1: ICE | H1: FIG | I1: POI | J1: GRO | K1: FLY | L1: PSY | M1: BUG | N1: ROC | O1: GHO | P1: DRA | Q1: DAR | R1: STE | S1: FAI
A2: NORMAL | B2: - | C2: - | D2: - | E2: - | F2: - | G2: - | H2: 2 | I2: - | J2: - | K2: - | L2: - | M2: - | N2: - | O2: 0 | P2: - | Q2: - | R2: - | S2: -
A3: NORMAL / FIRE | B3: - | C3: 0.5 | D3: 2 | E3: - | F3: 0.5 | G3: 0.5 | H3: 2 | I3: - | J3: 2 | K3: - | L3: - | M3: 0.5 | N3: 2 | O3: 0 | P3: - | Q3: - | R3: 0.5 | S3: 0.5
A4: NORMAL / WATER | B4: - | C4: 0.5 | D4: 0.5 | E4: 2 | F4: 2 | G4: 0.5 | H4: 2 | I4: - | J4: - | K4: - | L4: - | M4: - | N4: - | O4: 0 | P4: - | Q4: - | R4: 0.5 | S4: -
A5: NORMAL / ELECTRIC | B5: - | C5: - | D5: - | E5: 0.5 | F5: - | G5: - | H5: 2 | I5: - | J5: 2 | K5: 0.5 | L5: - | M5: - | N5: - | O5: 0 | P5: - | Q5: - | R5: 0.5 | S5: -
A6: NORMAL / GRASS | B6: - | C6: 2 | D6: 0.5 | E6: 0.5 | F6: 0.5 | G6: 2 | H6: 2 | I6: 2 | J6: 0.5 | K6: 2 | L6: - | M6: 2 | N6: - | O6: 0 | P6: - | Q6: - | R6: - | S6: -
A7: NORMAL / ICE | B7: - | C7: 2 | D7: - | E7: - | F7: - | G7: 0.5 | H7: 4 | I7: - | J7: - | K7: - | L7: - | M7: - | N7: 2 | O7: 0 | P7: - | Q7: - | R7: 2 | S7: -
A8: NORMAL / FIGHTING | B8: - | C8: - | D8: - | E8: - | F8: - | G8: - | H8: 2 | I8: - | J8: - | K8: 2 | L8: 2 | M8: 0.5 | N8: 0.5 | O8: 0 | P8: - | Q8: 0.5 | R8: - | S8: 2
A9: NORMAL / POISON | B9: - | C9: - | D9: - | E9: - | F9: 0.5 | G9: - | H9: - | I9: 0.5 | J9: 2 | K9: - | L9: 2 | M9: 0.5 | N9: - | O9: 0 | P9: - | Q9: - | R9: - | S9: 0.5
A10: NORMAL / GROUND | B10: - | C10: - | D10: 2 | E10: 0 | F10: 2 | G10: 2 | H10: 2 | I10: 0.5 | J10: - | K10: - | L10: - | M10: - | N10: 0.5 | O10: 0 | P10: - | Q10: - | R10: - | S10: -
A11: NORMAL / FLYING | B11: - | C11: - | D11: - | E11: 2 | F11: 0.5 | G11: 2 | H11: - | I11: - | J11: 0 | K11: - | L11: - | M11: 0.5 | N11: 2 | O11: 0 | P11: - | Q11: - | R11: - | S11: -
A12: NORMAL / PSYCHIC | B12: - | C12: - | D12: - | E12: - | F12: - | G12: - | H12: - | I12: - | J12: - | K12: - | L12: 0.5 | M12: 2 | N12: - | O12: 0 | P12: - | Q12: 2 | R12: - | S12: -
A13: NORMAL / BUG | B13: - | C13: 2 | D13: - | E13: - | F13: 0.5 | G13: - | H13: - | I13: - | J13: 0.5 | K13: 2 | L13: - | M13: - | N13: 2 | O13: 0 | P13: - | Q13: - | R13: - | S13: -
A14: NORMAL / ROCK | B14: 0.5 | C14: 0.5 | D14: 2 | E14: - | F14: 2 | G14: - | H14: 4 | I14: 0.5 | J14: 2 | K14: 0.5 | L14: - | M14: - | N14: - | O14: 0 | P14: - | Q14: - | R14: 2 | S14: -
A15: NORMAL / GHOST | B15: 0 | C15: - | D15: - | E15: - | F15: - | G15: - | H15: 0 | I15: 0.5 | J15: - | K15: - | L15: - | M15: 0.5 | N15: - | O15: 0 | P15: - | Q15: 2 | R15: - | S15: -
A16: NORMAL / DRAGON | B16: - | C16: 0.5 | D16: 0.5 | E16: 0.5 | F16: 0.5 | G16: 2 | H16: 2 | I16: - | J16: - | K16: - | L16: - | M16: - | N16: - | O16: 0 | P16: 2 | Q16: - | R16: - | S16: 2
A17: NORMAL / DARK | B17: - | C17: - | D17: - | E17: - | F17: - | G17: - | H17: 4 | I17: - | J17: - | K17: - | L17: 0 | M17: 2 | N17: - | O17: 0 | P17: - | Q17: 0.5 | R17: - | S17: 2
A18: NORMAL / STEEL | B18: 0.5 | C18: 2 | D18: - | E18: - | F18: 0.5 | G18: 0.5 | H18: 4 | I18: 0 | J18: 2 | K18: 0.5 | L18: 0.5 | M18: 0.5 | N18: 0.5 | O18: 0 | P18: 0.5 | Q18: - | R18: 0.5 | S18: 0.5
A19: NORMAL / FAIRY | B19: - | C19: - | D19: - | E19: - | F19: - | G19: - | H19: - | I19: 2 | J19: - | K19: - | L19: - | M19: 0.5 | N19: - | O19: 0 | P19: 0 | Q19: 0.5 | R19: 2 | S19: -
A20: FIRE | B20: - | C20: 0.5 | D20: 2 | E20: - | F20: 0.5 | G20: 0.5 | H20: - | I20: - | J20: 2 | K20: - | L20: - | M20: 0.5 | N20: 2 | O20: - | P20: - | Q20: - | R20: 0.5 | S20: 0.5
A21: FIRE / NORMAL | B21: - | C21: 0.5 | D21: 2 | E21: - | F21: 0.5 | G21: 0.5 | H21: 2 | I21: - | J21: 2 | K21: - | L21: - | M21: 0.5 | N21: 2 | O21: 0 | P21: - | Q21: - | R21: 0.5 | S21: 0.5
A22: FIRE / WATER | B22: - | C22: 0.25 | D22: - | E22: 2 | F22: - | G22: 0.25 | H22: - | I22: - | J22: 2 | K22: - | L22: - | M22: 0.5 | N22: 2 | O22: - | P22: - | Q22: - | R22: 0.25 | S22: 0.5
A23: FIRE / ELECTRIC | B23: - | C23: 0.5 | D23: 2 | E23: 0.5 | F23: 0.5 | G23: 0.5 | H23: - | I23: - | J23: 4 | K23: 0.5 | L23: - | M23: 0.5 | N23: 2 | O23: - | P23: - | Q23: - | R23: 0.25 | S23: 0.5
A24: FIRE / GRASS | B24: - | C24: - | D24: - | E24: 0.5 | F24: 0.25 | G24: - | H24: - | I24: 2 | J24: - | K24: 2 | L24: - | M24: - | N24: 2 | O24: - | P24: - | Q24: - | R24: 0.5 | S24: 0.5
A25: FIRE / ICE | B25: - | C25: - | D25: 2 | E25: - | F25: 0.5 | G25: 0.25 | H25: 2 | I25: - | J25: 2 | K25: - | L25: - | M25: 0.5 | N25: 4 | O25: - | P25: - | Q25: - | R25: - | S25: 0.5
A26: FIRE / FIGHTING | B26: - | C26: 0.5 | D26: 2 | E26: - | F26: 0.5 | G26: 0.5 | H26: - | I26: - | J26: 2 | K26: 2 | L26: 2 | M26: 0.25 | N26: - | O26: - | P26: - | Q26: 0.5 | R26: 0.5 | S26: -
A27: FIRE / POISON | B27: - | C27: 0.5 | D27: 2 | E27: - | F27: 0.25 | G27: 0.5 | H27: 0.5 | I27: 0.5 | J27: 4 | K27: - | L27: 2 | M27: 0.25 | N27: 2 | O27: - | P27: - | Q27: - | R27: 0.5 | S27: 0.25
A28: FIRE / GROUND | B28: - | C28: 0.5 | D28: 4 | E28: 0 | F28: - | G28: - | H28: - | I28: 0.5 | J28: 2 | K28: - | L28: - | M28: 0.5 | N28: - | O28: - | P28: - | Q28: - | R28: 0.5 | S28: 0.5
A29: FIRE / FLYING | B29: - | C29: 0.5 | D29: 2 | E29: 2 | F29: 0.25 | G29: - | H29: 0.5 | I29: - | J29: 0 | K29: - | L29: - | M29: 0.25 | N29: 4 | O29: - | P29: - | Q29: - | R29: 0.5 | S29: 0.5
A30: FIRE / PSYCHIC | B30: - | C30: 0.5 | D30: 2 | E30: - | F30: 0.5 | G30: 0.5 | H30: 0.5 | I30: - | J30: 2 | K30: - | L30: 0.5 | M30: - | N30: 2 | O30: 2 | P30: - | Q30: 2 | R30: 0.5 | S30: 0.5
A31: FIRE / BUG | B31: - | C31: - | D31: 2 | E31: - | F31: 0.25 | G31: 0.5 | H31: 0.5 | I31: - | J31: - | K31: 2 | L31: - | M31: 0.5 | N31: 4 | O31: - | P31: - | Q31: - | R31: 0.5 | S31: 0.5
A32: FIRE / ROCK | B32: 0.5 | C32: 0.25 | D32: 4 | E32: - | F32: - | G32: 0.5 | H32: 2 | I32: 0.5 | J32: 4 | K32: 0.5 | L32: - | M32: 0.5 | N32: 2 | O32: - | P32: - | Q32: - | R32: - | S32: 0.5
A33: FIRE / GHOST | B33: 0 | C33: 0.5 | D33: 2 | E33: - | F33: 0.5 | G33: 0.5 | H33: 0 | I33: 0.5 | J33: 2 | K33: - | L33: - | M33: 0.25 | N33: 2 | O33: 2 | P33: - | Q33: 2 | R33: 0.5 | S33: 0.5
A34: FIRE / DRAGON | B34: - | C34: 0.25 | D34: - | E34: 0.5 | F34: 0.25 | G34: - | H34: - | I34: - | J34: 2 | K34: - | L34: - | M34: 0.5 | N34: 2 | O34: - | P34: 2 | Q34: - | R34: 0.5 | S34: -
A35: FIRE / DARK | B35: - | C35: 0.5 | D35: 2 | E35: - | F35: 0.5 | G35: 0.5 | H35: 2 | I35: - | J35: 2 | K35: - | L35: 0 | M35: - | N35: 2 | O35: 0.5 | P35: - | Q35: 0.5 | R35: 0.5 | S35: -
A36: FIRE / STEEL | B36: 0.5 | C36: - | D36: 2 | E36: - | F36: 0.25 | G36: 0.25 | H36: 2 | I36: 0 | J36: 4 | K36: 0.5 | L36: 0.5 | M36: 0.25 | N36: - | O36: - | P36: 0.5 | Q36: - | R36: 0.25 | S36: 0.25
A37: FIRE / FAIRY | B37: - | C37: 0.5 | D37: 2 | E37: - | F37: 0.5 | G37: 0.5 | H37: 0.5 | I37: 2 | J37: 2 | K37: - | L37: - | M37: 0.25 | N37: 2 | O37: - | P37: 0 | Q37: 0.5 | R37: - | S37: 0.5
A38: WATER | B38: - | C38: 0.5 | D38: 0.5 | E38: 2 | F38: 2 | G38: 0.5 | H38: - | I38: - | J38: - | K38: - | L38: - | M38: - | N38: - | O38: - | P38: - | Q38: - | R38: 0.5 | S38: -
A39: WATER / NORMAL | B39: - | C39: 0.5 | D39: 0.5 | E39: 2 | F39: 2 | G39: 0.5 | H39: 2 | I39: - | J39: - | K39: - | L39: - | M39: - | N39: - | O39: 0 | P39: - | Q39: - | R39: 0.5 | S39: -
